CPU/Register.v
module Register (
    input wire clk,              // Tín hiệu xung nhịp
    input wire reset,            // Tín hiệu reset
    input wire reg_write,        // Cho phép ghi vào thanh ghi
    input wire [31:0] data_in,   // Dữ liệu đầu vào
    output reg [31:0] data_out   // Dữ liệu đầu ra
);

    // Cập nhật thanh ghi khi có xung dương và tín hiệu cho phép ghi
    always @(posedge clk) begin
        if (reset) begin
            // Reset thanh ghi về 0
            data_out <= 32'b0;
        end else if (reg_write) begin
            // Ghi dữ liệu khi có tín hiệu cho phép
            data_out <= data_in;
        end
        // Nếu không, giữ nguyên giá trị hiện tại
    end

endmodule

Register/Register_tb.v
`timescale 1ns / 1ps

module Register_tb;
    // Tham số
    parameter CLK_PERIOD = 10; // 10ns = 100MHz

    // Các tín hiệu đầu vào
    reg clk;
    reg reset;
    reg reg_write;
    reg [31:0] data_in;

    // Tín hiệu đầu ra
    wire [31:0] data_out;

    // Tạo xung nhịp
    always #(CLK_PERIOD/2) clk = ~clk;

    // Khởi tạo đối tượng cần kiểm tra
    Register uut (
        .clk(clk),
        .reset(reset),
        .reg_write(reg_write),
        .data_in(data_in),
        .data_out(data_out)
    );

    // Tạo file VCD để xem dạng sóng
    initial begin
        $dumpfile("register_waveform.vcd");
        $dumpvars(0, Register_tb);
    end

    // Biến đếm test case và kết quả mong đợi
    integer test_case;
    reg [31:0] expected_data;

    // Hàm hiển thị kết quả kiểm tra
    task display_test_result;
        input [8*30:1] test_name;
        begin
            $display("Test Case %0d: %s", test_case, test_name);
            $display("  data_in = %h, reg_write = %b", data_in, reg_write);
            $display("  Expected: data_out = %h", expected_data);
            $display("  Actual:   data_out = %h", data_out);
            
            if (data_out !== expected_data) begin
                $display("  TEST FAILED!");
            end else begin
                $display("  Test passed.");
            end
            $display("--------------------------------------");
        end
    endtask

    // Quy trình kiểm tra chính
    initial begin
        // Khởi tạo các tín hiệu đầu vào
        clk = 0;
        reset = 1;
        reg_write = 0;
        data_in = 0;
        test_case = 0;
        expected_data = 0;

        // Đợi reset hoàn tất
        #(CLK_PERIOD*2);
        reset = 0;
        #CLK_PERIOD;

        // Test 1: Ghi dữ liệu khi reg_write=1
        test_case = test_case + 1;
        data_in = 32'h12345678;
        reg_write = 1;
        expected_data = 32'h12345678;
        #CLK_PERIOD;
        display_test_result("Ghi dữ liệu khi reg_write=1");

        // Test 2: Giữ giá trị khi reg_write=0
        test_case = test_case + 1;
        data_in = 32'h87654321;
        reg_write = 0;
        expected_data = 32'h12345678; // Giữ giá trị cũ
        #CLK_PERIOD;
        display_test_result("Giữ giá trị khi reg_write=0");

        // Test 3: Ghi dữ liệu mới khi reg_write=1
        test_case = test_case + 1;
        data_in = 32'hABCDEF01;
        reg_write = 1;
        expected_data = 32'hABCDEF01;
        #CLK_PERIOD;
        display_test_result("Ghi dữ liệu mới khi reg_write=1");

        // Test 4: Reset thanh ghi
        test_case = test_case + 1;
        reset = 1;
        expected_data = 32'h00000000;
        #CLK_PERIOD;
        display_test_result("Reset thanh ghi");
        reset = 0;

        // Test 5: Ghi dữ liệu sau khi reset
        test_case = test_case + 1;
        data_in = 32'h55555555;
        reg_write = 1;
        expected_data = 32'h55555555;
        #CLK_PERIOD;
        display_test_result("Ghi dữ liệu sau khi reset");

        // Test 6: Kiểm tra với giá trị nhỏ
        test_case = test_case + 1;
        data_in = 32'h00000001;
        reg_write = 1;
        expected_data = 32'h00000001;
        #CLK_PERIOD;
        display_test_result("Kiểm tra với giá trị nhỏ");

        // Test 7: Kiểm tra với giá trị lớn nhất
        test_case = test_case + 1;
        data_in = 32'hFFFFFFFF;
        reg_write = 1;
        expected_data = 32'hFFFFFFFF;
        #CLK_PERIOD;
        display_test_result("Kiểm tra với giá trị lớn nhất");

        // Test 8: Kiểm tra với giá trị 0
        test_case = test_case + 1;
        data_in = 32'h00000000;
        reg_write = 1;
        expected_data = 32'h00000000;
        #CLK_PERIOD;
        display_test_result("Kiểm tra với giá trị 0");

        // Kết thúc mô phỏng
        $display("Tất cả các test đã hoàn thành!");
        #(CLK_PERIOD*2);
        $finish;
    end

endmodule

Register/register_waveform.vcd
$date
	Fri Jun 20 20:50:12 2025
$end
$version
	Icarus Verilog
$end
$timescale
	1ps
$end
$scope module Register_tb $end
$var wire 32 ! data_out [31:0] $end
$var parameter 32 " CLK_PERIOD $end
$var reg 1 # clk $end
$var reg 32 $ data_in [31:0] $end
$var reg 32 % expected_data [31:0] $end
$var reg 1 & reg_write $end
$var reg 1 ' reset $end
$var integer 32 ( test_case [31:0] $end
$scope module uut $end
$var wire 1 # clk $end
$var wire 32 ) data_in [31:0] $end
$var wire 1 & reg_write $end
$var wire 1 ' reset $end
$var reg 32 * data_out [31:0] $end
$upscope $end
$scope task display_test_result $end
$var reg 240 + test_name [240:1] $end
$upscope $end
$upscope $end
$enddefinitions $end
$comment Show the parameter values. $end
$dumpall
b1010 "
$end
#0
$dumpvars
bx +
bx *
b0 )
b0 (
1'
0&
b0 %
b0 $
0#
bx !
$end
#5000
b0 !
b0 *
1#
#10000
0#
#15000
1#
#20000
0#
0'
#25000
1#
#30000
0#
b10010001101000101011001111000 %
1&
b10010001101000101011001111000 $
b10010001101000101011001111000 )
b1 (
#35000
b10010001101000101011001111000 !
b10010001101000101011001111000 *
1#
#40000
0#
0&
b10000111011001010100001100100001 $
b10000111011001010100001100100001 )
b10 (
b11010000110100100100000011001001110000110111011101011110010000001101100011010011110000110111011100001110111010100100000011010110110100001101001001000000111001001100101011001110101111101110111011100100110100101110100011001010011110100110001 +
#45000
1#
#50000
0#
b10101011110011011110111100000001 %
1&
b10101011110011011110111100000001 $
b10101011110011011110111100000001 )
b11 (
b111000011011101110101111001000000110011101101001110000111010000100100000011101000111001011100001101110111000101100100000011010110110100001101001001000000111001001100101011001110101111101110111011100100110100101110100011001010011110100110000 +
#55000
b10101011110011011110111100000001 !
b10101011110011011110111100000001 *
1#
#60000
0#
b0 %
1'
b100 (
b101011110010000001101100011010011110000110111011100001110111010100100000011011011110000110111011100110110110100100100000011010110110100001101001001000000111001001100101011001110101111101110111011100100110100101110100011001010011110100110001 +
#65000
b0 !
b0 *
1#
#70000
0#
b1010101010101010101010101010101 %
b1010101010101010101010101010101 $
b1010101010101010101010101010101 )
b101 (
0'
b10100100110010101110011011001010111010000100000011101000110100001100001011011100110100000100000011001110110100001101001 +
#75000
b1010101010101010101010101010101 !
b1010101010101010101010101010101 *
1#
#80000
0#
b1 %
b1 $
b1 )
b110 (
b100011101101000011010011111111111111111111111111011101110101111001000000110110001101001111111111111111110000111011101010010000001110011011000010111010100100000011010110110100001101001001000000111001001100101011100110110010101110100 +
#85000
b1 !
b1 *
1#
#90000
0#
b11111111111111111111111111111111 %
b11111111111111111111111111111111 $
b11111111111111111111111111111111 )
b111 (
b101110111000001101101101001000000111010001110010011000010010000001110110111000011011101110011011011010010010000001100111011010011100001110100001001000000111010001110010111000011011101110001011001000000110111001101000111000011011101110001111 +
#95000
b11111111111111111111111111111111 !
b11111111111111111111111111111111 *
1#
#100000
0#
b0 %
b0 $
b0 )
b1000 (
b1000000111011011100001101110111001101101101001001000000110011101101001110000111010000100100000011101000111001011100001101110111000101100100000011011001110000110111011100110110110111000100000011011100110100011100001101110101010010101110100 +
#105000
b0 !
b0 *
1#
#110000
0#
b111111111111111111111111111000011111111110000011011011010010000001110100011100100110000100100000111111111111111111111111100110110110100100100000011001110110100111111111101000010010000001110100111111111111111111111111100010110010000000110000 +
