CPU/Memory_Address_Register.v
module Memory_Address_Register (
    input wire clk,
    input wire reset,
    input wire mar_write,
    input wire [31:0] address_in,
    output reg [31:0] address_out
);

    // Synchronous update of memory address register
    always @(posedge clk or posedge reset) begin
        if (reset) begin
            address_out <= 32'h0; // Reset to 0
        end else if (mar_write) begin
            address_out <= address_in; // Update when mar_write is enabled
        end
    end

endmodule

Memory_Address_Register/Memory_Address_Register_tb.v
module Memory_Address_Register_tb;
    // Parameters
    parameter CLK_PERIOD = 10; // 10ns clock period (100MHz)
    
    // Inputs
    reg clk;
    reg reset;
    reg mar_write;
    reg [31:0] address_in;
    
    // Outputs
    wire [31:0] address_out;
    
    // Instantiate the Memory Address Register
    Memory_Address_Register dut (
        .clk(clk),
        .reset(reset),
        .mar_write(mar_write),
        .address_in(address_in),
        .address_out(address_out)
    );
    
    // Clock generation
    initial begin
        clk = 0;
        forever #(CLK_PERIOD/2) clk = ~clk;
    end
    
    // Test sequence
    initial begin
        // Initialize inputs
        reset = 1;
        mar_write = 0;
        address_in = 32'h0;
        
        // Apply reset
        #(CLK_PERIOD*2);
        reset = 0;
        #CLK_PERIOD;
        
        // Test 1: Write address to MAR
        address_in = 32'h12345678;
        mar_write = 1;
        #CLK_PERIOD;
        mar_write = 0;
        
        // Verify address was written
        if (address_out !== 32'h12345678) begin
            $display("Test 1 Failed: address_out = %h, expected = %h", address_out, 32'h12345678);
        end else begin
            $display("Test 1 Passed: address_out = %h", address_out);
        end
        
        // Test 2: Change address_in without mar_write (should not update)
        address_in = 32'h87654321;
        #CLK_PERIOD;
        
        // Verify address was not written
        if (address_out !== 32'h12345678) begin
            $display("Test 2 Failed: address_out = %h, expected = %h", address_out, 32'h12345678);
        end else begin
            $display("Test 2 Passed: address_out unchanged when mar_write=0");
        end
        
        // Test 3: Write new address to MAR
        address_in = 32'hAABBCCDD;
        mar_write = 1;
        #CLK_PERIOD;
        mar_write = 0;
        
        // Verify new address was written
        if (address_out !== 32'hAABBCCDD) begin
            $display("Test 3 Failed: address_out = %h, expected = %h", address_out, 32'hAABBCCDD);
        end else begin
            $display("Test 3 Passed: address_out = %h", address_out);
        end
        
        // Test 4: Reset MAR
        reset = 1;
        #CLK_PERIOD;
        reset = 0;
        
        // Verify address was reset to 0
        if (address_out !== 32'h0) begin
            $display("Test 4 Failed: address_out = %h, expected = %h", address_out, 32'h0);
        end else begin
            $display("Test 4 Passed: address_out reset to 0");
        end
        
        // Test 5: Reset has priority over write
        address_in = 32'hFFFFFFFF;
        mar_write = 1;
        reset = 1;
        #CLK_PERIOD;
        reset = 0;
        mar_write = 0;
        
        // Verify address was reset to 0 despite mar_write being 1
        if (address_out !== 32'h0) begin
            $display("Test 5 Failed: address_out = %h, expected = %h", address_out, 32'h0);
        end else begin
            $display("Test 5 Passed: reset has priority over write");
        end
        
        $display("All tests completed");
        $finish;
    end
    
    // Optional: Generate VCD file for waveform viewing
    initial begin
        $dumpfile("memory_address_register_waveform.vcd");
        $dumpvars(0, Memory_Address_Register_tb);
    end
    
endmodule

Memory_Address_Register/memory_address_register_waveform.vcd
$date
	Fri Jun 20 22:56:43 2025
$end
$version
	Icarus Verilog
$end
$timescale
	1s
$end
$scope module Memory_Address_Register_tb $end
$var wire 32 ! address_out [31:0] $end
$var parameter 32 " CLK_PERIOD $end
$var reg 32 # address_in [31:0] $end
$var reg 1 $ clk $end
$var reg 1 % mar_write $end
$var reg 1 & reset $end
$scope module dut $end
$var wire 32 ' address_in [31:0] $end
$var wire 1 $ clk $end
$var wire 1 % mar_write $end
$var wire 1 & reset $end
$var reg 32 ( address_out [31:0] $end
$upscope $end
$upscope $end
$enddefinitions $end
$comment Show the parameter values. $end
$dumpall
b1010 "
$end
#0
$dumpvars
b0 (
b0 '
1&
0%
0$
b0 #
b0 !
$end
#5
1$
#10
0$
#15
1$
#20
0$
0&
#25
1$
#30
0$
1%
b10010001101000101011001111000 #
b10010001101000101011001111000 '
#35
b10010001101000101011001111000 !
b10010001101000101011001111000 (
1$
#40
0$
b10000111011001010100001100100001 #
b10000111011001010100001100100001 '
0%
#45
1$
#50
0$
1%
b10101010101110111100110011011101 #
b10101010101110111100110011011101 '
#55
b10101010101110111100110011011101 !
b10101010101110111100110011011101 (
1$
#60
b0 !
b0 (
0$
1&
0%
#65
1$
#70
0$
1%
b11111111111111111111111111111111 #
b11111111111111111111111111111111 '
1&
#75
1$
#80
0$
0%
0&
