Memory/Memory.v
module Memory (
    input wire clk,
    input wire [31:0] address,
    input wire [31:0] write_data,
    input wire mem_write,
    input wire mem_read,
    input wire [1:0] size,  // 00: byte, 01: half-word, 10: word
    output reg [31:0] read_data
);

    // Define memory size (8KB = 2048 words)
    parameter MEM_SIZE = 2048;
    
    // Memory array (byte addressable)
    reg [7:0] memory [0:MEM_SIZE*4-1];
    
    // Declare the loop variable outside the initial block
    integer i;
    
    // Read operation (combinational)
    always @(*) begin
        if (mem_read) begin
            case (size)
                2'b00: begin // Byte
                    read_data = {{24{memory[address][7]}}, memory[address]};
                end
                2'b01: begin // Half-word
                    read_data = {{16{memory[address+1][7]}}, memory[address+1], memory[address]};
                end
                2'b10: begin // Word
                    read_data = {memory[address+3], memory[address+2], memory[address+1], memory[address]};
                end
                default: begin
                    read_data = {memory[address+3], memory[address+2], memory[address+1], memory[address]};
                end
            endcase
        end else begin
            read_data = 32'h0;
        end
    end
    
    // Write operation (synchronous)
    always @(posedge clk) begin
        if (mem_write) begin
            case (size)
                2'b00: begin // Byte
                    memory[address] <= write_data[7:0];
                end
                2'b01: begin // Half-word
                    memory[address] <= write_data[7:0];
                    memory[address+1] <= write_data[15:8];
                end
                2'b10: begin // Word
                    memory[address] <= write_data[7:0];
                    memory[address+1] <= write_data[15:8];
                    memory[address+2] <= write_data[23:16];
                    memory[address+3] <= write_data[31:24];
                end
                default: begin
                    memory[address] <= write_data[7:0];
                    memory[address+1] <= write_data[15:8];
                    memory[address+2] <= write_data[23:16];
                    memory[address+3] <= write_data[31:24];
                end
            endcase
        end
    end
    
    // Initialize memory (optional)
    // Can be used to load a program or initial data
    initial begin
        for (i = 0; i < MEM_SIZE*4; i = i + 1) begin
            memory[i] = 8'h0;
        end
        
        // Example: Load a simple program (optional)
        // memory[0] = 8'h13; // addi x0, x0, 0 (NOP)
        // memory[1] = 8'h01;
        // memory[2] = 8'h00;
        // memory[3] = 8'h00;
    end

endmodule

Memory/Memory_tb.v
module Memory_tb;
    // Parameters
    parameter CLK_PERIOD = 10; // 10ns clock period (100MHz)
    
    // Inputs
    reg clk;
    reg [31:0] address;
    reg [31:0] write_data;
    reg mem_write;
    reg mem_read;
    reg [1:0] size;
    
    // Outputs
    wire [31:0] read_data;
    
    // Instantiate the Memory module
    Memory dut (
        .clk(clk),
        .address(address),
        .write_data(write_data),
        .mem_write(mem_write),
        .mem_read(mem_read),
        .size(size),
        .read_data(read_data)
    );
    
    // Clock generation
    initial begin
        clk = 0;
        forever #(CLK_PERIOD/2) clk = ~clk;
    end
    
    // Test sequence
    initial begin
        // Initialize inputs
        address = 32'h0;
        write_data = 32'h0;
        mem_write = 0;
        mem_read = 0;
        size = 2'b10; // Word size
        
        // Wait for a few clock cycles
        #(CLK_PERIOD*2);
        
        // Test 1: Write a word to memory
        address = 32'h00000000;
        write_data = 32'h12345678;
        mem_write = 1;
        size = 2'b10; // Word
        #CLK_PERIOD;
        mem_write = 0;
        
        // Read the word back
        mem_read = 1;
        #CLK_PERIOD;
        
        // Verify read data
        if (read_data !== 32'h12345678) begin
            $display("Test 1 Failed: read_data = %h, expected = %h", read_data, 32'h12345678);
        end else begin
            $display("Test 1 Passed: read_data = %h", read_data);
        end
        
        // Test 2: Write a half-word to memory
        address = 32'h00000004;
        write_data = 32'h0000ABCD;
        mem_write = 1;
        size = 2'b01; // Half-word
        #CLK_PERIOD;
        mem_write = 0;
        
        // Read the half-word back
        mem_read = 1;
        #CLK_PERIOD;
        
        // Verify read data (sign-extended)
        if (read_data !== 32'hFFFFABCD) begin
            $display("Test 2 Failed: read_data = %h, expected = %h", read_data, 32'hFFFFABCD);
        end else begin
            $display("Test 2 Passed: read_data = %h", read_data);
        end
        
        // Test 3: Write a byte to memory
        address = 32'h00000008;
        write_data = 32'h000000FF;
        mem_write = 1;
        size = 2'b00; // Byte
        #CLK_PERIOD;
        mem_write = 0;
        
        // Read the byte back
        mem_read = 1;
        #CLK_PERIOD;
        
        // Verify read data (sign-extended)
        if (read_data !== 32'hFFFFFFFF) begin
            $display("Test 3 Failed: read_data = %h, expected = %h", read_data, 32'hFFFFFFFF);
        end else begin
            $display("Test 3 Passed: read_data = %h", read_data);
        end
        
        // Test 4: Write a positive byte to memory (no sign extension)
        address = 32'h0000000C;
        write_data = 32'h0000007F;
        mem_write = 1;
        size = 2'b00; // Byte
        #CLK_PERIOD;
        mem_write = 0;
        
        // Read the byte back
        mem_read = 1;
        #CLK_PERIOD;
        
        // Verify read data (sign-extended, but positive)
        if (read_data !== 32'h0000007F) begin
            $display("Test 4 Failed: read_data = %h, expected = %h", read_data, 32'h0000007F);
        end else begin
            $display("Test 4 Passed: read_data = %h", read_data);
        end
        
        // Test 5: Write a word and read it back in parts
        address = 32'h00000010;
        write_data = 32'h12345678;
        mem_write = 1;
        size = 2'b10; // Word
        #CLK_PERIOD;
        mem_write = 0;
        
        // Read the lower half-word
        address = 32'h00000010;
        mem_read = 1;
        size = 2'b01; // Half-word
        #CLK_PERIOD;
        
        // Verify read data
        if (read_data !== 32'h00005678) begin
            $display("Test 5a Failed: read_data = %h, expected = %h", read_data, 32'h00005678);
        end else begin
            $display("Test 5a Passed: read_data = %h", read_data);
        end
        
        // Read the upper half-word
        address = 32'h00000012;
        #CLK_PERIOD;
        
        // Verify read data
        if (read_data !== 32'h00001234) begin
            $display("Test 5b Failed: read_data = %h, expected = %h", read_data, 32'h00001234);
        end else begin
            $display("Test 5b Passed: read_data = %h", read_data);
        end
        
        // Test 6: Test mem_read control
        mem_read = 0;
        #CLK_PERIOD;
        
        // Verify read data is 0 when mem_read=0
        if (read_data !== 32'h0) begin
            $display("Test 6 Failed: read_data = %h, expected = %h", read_data, 32'h0);
        end else begin
            $display("Test 6 Passed: read_data = %h when mem_read=0", read_data);
        end
        
        $display("All tests completed");
        $finish;
    end
    
    // Optional: Generate VCD file for waveform viewing
    initial begin
        $dumpfile("memory_waveform.vcd");
        $dumpvars(0, Memory_tb);
    end
    
endmodule

Memory/memory_waveform.vcd
$date
	Fri Jun 20 22:45:59 2025
$end
$version
	Icarus Verilog
$end
$timescale
	1s
$end
$scope module Memory_tb $end
$var wire 32 ! read_data [31:0] $end
$var parameter 32 " CLK_PERIOD $end
$var reg 32 # address [31:0] $end
$var reg 1 $ clk $end
$var reg 1 % mem_read $end
$var reg 1 & mem_write $end
$var reg 2 ' size [1:0] $end
$var reg 32 ( write_data [31:0] $end
$scope module dut $end
$var wire 32 ) address [31:0] $end
$var wire 1 $ clk $end
$var wire 1 % mem_read $end
$var wire 1 & mem_write $end
$var wire 2 * size [1:0] $end
$var wire 32 + write_data [31:0] $end
$var parameter 32 , MEM_SIZE $end
$var reg 32 - read_data [31:0] $end
$var integer 32 . i [31:0] $end
$upscope $end
$upscope $end
$enddefinitions $end
$comment Show the parameter values. $end
$dumpall
b100000000000 ,
b1010 "
$end
#0
$dumpvars
b10000000000000 .
b0 -
b0 +
b10 *
b0 )
b0 (
b10 '
0&
0%
0$
b0 #
b0 !
$end
#5
1$
#10
0$
#15
1$
#20
0$
1&
b10010001101000101011001111000 (
b10010001101000101011001111000 +
#25
1$
#30
b10010001101000101011001111000 !
b10010001101000101011001111000 -
0$
1%
0&
#35
1$
#40
b0 !
b0 -
0$
b1 '
b1 *
1&
b1010101111001101 (
b1010101111001101 +
b100 #
b100 )
#45
b11111111111111111010101111001101 !
b11111111111111111010101111001101 -
1$
#50
0$
0&
#55
1$
#60
b0 !
b0 -
0$
b0 '
b0 *
1&
b11111111 (
b11111111 +
b1000 #
b1000 )
#65
b11111111111111111111111111111111 !
b11111111111111111111111111111111 -
1$
#70
0$
0&
#75
1$
#80
b0 !
b0 -
0$
1&
b1111111 (
b1111111 +
b1100 #
b1100 )
#85
b1111111 !
b1111111 -
1$
#90
0$
0&
#95
1$
#100
b0 !
b0 -
0$
b10 '
b10 *
1&
b10010001101000101011001111000 (
b10010001101000101011001111000 +
b10000 #
b10000 )
#105
b10010001101000101011001111000 !
b10010001101000101011001111000 -
1$
#110
b101011001111000 !
b101011001111000 -
0$
b1 '
b1 *
0&
#115
1$
#120
b1001000110100 !
b1001000110100 -
0$
b10010 #
b10010 )
#125
1$
#130
b0 !
b0 -
0$
0%
