src/alu.v
// Arithmetic Logic Unit (ALU)
// Supports ADD/SUB/AND/OR/XOR/SLT/SLTU/SLL/SRL/SRA operations
// Based on Blog.md section 2.1 item 6)

// =============================================================================
// Local Constants (moved from riscv_constants.vh)
// =============================================================================
`define DATA_WIDTH          32          // 32-bit data bus

// ALU Operation Constants (4-bit encoding)
`define ALU_ADD             4'b0000         // Addition
`define ALU_SUB             4'b0001         // Subtraction
`define ALU_AND             4'b0010         // Bitwise AND
`define ALU_OR              4'b0011         // Bitwise OR
`define ALU_XOR             4'b0100         // Bitwise XOR
`define ALU_SLT             4'b0101         // Set Less Than (signed)
`define ALU_SLTU            4'b0110         // Set Less Than Unsigned
`define ALU_SLL             4'b0111         // Shift Left Logical
`define ALU_SRL             4'b1000         // Shift Right Logical
`define ALU_SRA             4'b1001         // Shift Right Arithmetic

module alu (
    // Input operands (from register/immediate/PC via AluSrc mux)
    input  wire [`DATA_WIDTH-1:0]  operand1,
    input  wire [`DATA_WIDTH-1:0]  operand2,
    
    // ALU operation control
    input  wire [3:0]               alu_control,
    
    // ALU result output
    output reg  [`DATA_WIDTH-1:0]  alu_result,
    
    // Zero flag (useful for branch conditions)
    output wire                     zero_flag
);

    // Shift amount (lower 5 bits of operand2)
    wire [4:0] shift_amount;
    assign shift_amount = operand2[4:0];
    
    // Signed operands for comparison
    wire signed [`DATA_WIDTH-1:0] signed_op1, signed_op2;
    assign signed_op1 = operand1;
    assign signed_op2 = operand2;
    
    always @(*) begin
        case (alu_control)
            `ALU_ADD: begin
                alu_result = operand1 + operand2;
            end
            
            `ALU_SUB: begin
                alu_result = operand1 - operand2;
            end
            
            `ALU_AND: begin
                alu_result = operand1 & operand2;
            end
            
            `ALU_OR: begin
                alu_result = operand1 | operand2;
            end
            
            `ALU_XOR: begin
                alu_result = operand1 ^ operand2;
            end
            
            `ALU_SLT: begin
                // Set less than (signed)
                alu_result = (signed_op1 < signed_op2) ? 32'h00000001 : 32'h00000000;
            end
            
            `ALU_SLTU: begin
                // Set less than unsigned
                alu_result = (operand1 < operand2) ? 32'h00000001 : 32'h00000000;
            end
            
            `ALU_SLL: begin
                // Shift left logical
                alu_result = operand1 << shift_amount;
            end
            
            `ALU_SRL: begin
                // Shift right logical  
                alu_result = operand1 >> shift_amount;
            end
            
            `ALU_SRA: begin
                // Shift right arithmetic
                alu_result = signed_op1 >>> shift_amount;
            end
            
            default: begin
                alu_result = 32'h00000000;
            end
        endcase
    end
    
    // Zero flag for branch conditions
    assign zero_flag = (alu_result == 32'h00000000);

endmodule

verify/testbench/alu_tb.v
// =============================================================================
// ALU Testbench - Comprehensive Verification
// =============================================================================
// Description: Exhaustive testing of ALU operations with corner cases
// Author: Auto-generated testbench
// Date: September 23, 2025
// Features: - All ALU operations testing
//          - Corner case verification  
//          - Randomized testing
//          - Performance monitoring
//          - Self-checking testbench
// =============================================================================

`timescale 1ns / 1ps

module alu_tb;

    // =================================================================
    // Testbench Parameters
    // =================================================================
    parameter CLOCK_PERIOD = 10;
    parameter NUM_RANDOM_TESTS = 1000;
    parameter VERBOSE_MODE = 1;
    
    // =================================================================
    // Test Signal Declarations
    // =================================================================
    reg [31:0]  operand1;
    reg [31:0]  operand2;
    reg [3:0]   alu_control;
    wire [31:0] alu_result;
    wire        zero_flag;
    
    // Test control variables
    reg clk;
    integer test_count;
    integer pass_count;
    integer fail_count;
    
    // =================================================================
    // ALU Operation Constants (matching alu.v)
    // =================================================================
    localparam ALU_ADD  = 4'b0000;
    localparam ALU_SUB  = 4'b0001;
    localparam ALU_AND  = 4'b0010;
    localparam ALU_OR   = 4'b0011;
    localparam ALU_XOR  = 4'b0100;
    localparam ALU_SLT  = 4'b0101;
    localparam ALU_SLTU = 4'b0110;
    localparam ALU_SLL  = 4'b0111;
    localparam ALU_SRL  = 4'b1000;
    localparam ALU_SRA  = 4'b1001;
    
    // =================================================================
    // Device Under Test (DUT)
    // =================================================================
    alu dut (
        .operand1(operand1),
        .operand2(operand2),
        .alu_control(alu_control),
        .alu_result(alu_result),
        .zero_flag(zero_flag)
    );
    
    // =================================================================
    // Clock Generation (for sequential testing)
    // =================================================================
    initial begin
        clk = 0;
        forever #(CLOCK_PERIOD/2) clk = ~clk;
    end
    
    // =================================================================
    // Test Execution Control
    // =================================================================
    initial begin
        // Initialize test counters
        test_count = 0;
        pass_count = 0;
        fail_count = 0;
        
        // Initialize inputs
        operand1 = 32'h0;
        operand2 = 32'h0;
        alu_control = 4'h0;
        
        $display("========================================");
        $display("ALU TESTBENCH STARTING");
        $display("========================================");
        $display("Time: %0t", $time);
        
        // Wait for initial settling
        #(CLOCK_PERIOD * 2);
        
        // Run test suites
        run_basic_arithmetic_tests();
        run_logic_operation_tests();
        run_comparison_tests();
        run_shift_operation_tests();
        run_corner_case_tests();
        run_randomized_tests();
        run_zero_flag_tests();
        
        // Display final results
        display_test_summary();
        
        // Finish simulation
        #100;
        $finish;
    end
    
    // =================================================================
    // Test Suite: Basic Arithmetic Operations
    // =================================================================
    task run_basic_arithmetic_tests();
        begin
            $display("\n[%0t] Running Basic Arithmetic Tests...", $time);
            
            // ADD Tests
            test_alu_operation(ALU_ADD, 32'h12345678, 32'h87654321, 32'h99999999, "ADD: Normal case");
            test_alu_operation(ALU_ADD, 32'h00000000, 32'h12345678, 32'h12345678, "ADD: Zero + value");
            test_alu_operation(ALU_ADD, 32'hFFFFFFFF, 32'h00000001, 32'h00000000, "ADD: Overflow wrap");
            test_alu_operation(ALU_ADD, 32'h7FFFFFFF, 32'h00000001, 32'h80000000, "ADD: Positive overflow");
            
            // SUB Tests
            test_alu_operation(ALU_SUB, 32'h87654321, 32'h12345678, 32'h751FDB09, "SUB: Normal case");
            test_alu_operation(ALU_SUB, 32'h12345678, 32'h12345678, 32'h00000000, "SUB: Same operands");
            test_alu_operation(ALU_SUB, 32'h00000000, 32'h12345678, 32'hEDCBA988, "SUB: Zero - value");
            test_alu_operation(ALU_SUB, 32'h80000000, 32'h00000001, 32'h7FFFFFFF, "SUB: Underflow wrap");
            
            $display("Basic Arithmetic Tests Completed");
        end
    endtask
    
    // =================================================================
    // Test Suite: Logic Operations
    // =================================================================
    task run_logic_operation_tests();
        begin
            $display("\n[%0t] Running Logic Operation Tests...", $time);
            
            // AND Tests
            test_alu_operation(ALU_AND, 32'hFFFFFFFF, 32'h12345678, 32'h12345678, "AND: All 1s & value");
            test_alu_operation(ALU_AND, 32'h00000000, 32'h12345678, 32'h00000000, "AND: All 0s & value");
            test_alu_operation(ALU_AND, 32'hAAAAAAAA, 32'h55555555, 32'h00000000, "AND: Alternating bits");
            test_alu_operation(ALU_AND, 32'hF0F0F0F0, 32'h0F0F0F0F, 32'h00000000, "AND: Complement masks");
            
            // OR Tests
            test_alu_operation(ALU_OR, 32'h00000000, 32'h12345678, 32'h12345678, "OR: Zero | value");
            test_alu_operation(ALU_OR, 32'hFFFFFFFF, 32'h12345678, 32'hFFFFFFFF, "OR: All 1s | value");
            test_alu_operation(ALU_OR, 32'hAAAAAAAA, 32'h55555555, 32'hFFFFFFFF, "OR: Alternating bits");
            test_alu_operation(ALU_OR, 32'hF0F0F0F0, 32'h0F0F0F0F, 32'hFFFFFFFF, "OR: Complement masks");
            
            // XOR Tests
            test_alu_operation(ALU_XOR, 32'h00000000, 32'h12345678, 32'h12345678, "XOR: Zero ^ value");
            test_alu_operation(ALU_XOR, 32'hFFFFFFFF, 32'h12345678, 32'hEDCBA987, "XOR: All 1s ^ value");
            test_alu_operation(ALU_XOR, 32'h12345678, 32'h12345678, 32'h00000000, "XOR: Same operands");
            test_alu_operation(ALU_XOR, 32'hAAAAAAAA, 32'h55555555, 32'hFFFFFFFF, "XOR: Alternating bits");
            
            $display("Logic Operation Tests Completed");
        end
    endtask
    
    // =================================================================
    // Test Suite: Comparison Operations
    // =================================================================
    task run_comparison_tests();
        begin
            $display("\n[%0t] Running Comparison Tests...", $time);
            
            // SLT (Set Less Than - Signed) Tests
            test_alu_operation(ALU_SLT, 32'h7FFFFFFF, 32'h80000000, 32'h00000000, "SLT: Max positive < Min negative (signed)");
            test_alu_operation(ALU_SLT, 32'h80000000, 32'h7FFFFFFF, 32'h00000001, "SLT: Min negative < Max positive (signed)");
            test_alu_operation(ALU_SLT, 32'hFFFFFFFF, 32'h00000000, 32'h00000001, "SLT: -1 < 0 (signed)");
            test_alu_operation(ALU_SLT, 32'h00000000, 32'hFFFFFFFF, 32'h00000000, "SLT: 0 < -1 (signed)");
            test_alu_operation(ALU_SLT, 32'h12345678, 32'h12345678, 32'h00000000, "SLT: Equal values (signed)");
            
            // SLTU (Set Less Than - Unsigned) Tests
            test_alu_operation(ALU_SLTU, 32'h7FFFFFFF, 32'h80000000, 32'h00000001, "SLTU: 0x7FFF... < 0x8000... (unsigned)");
            test_alu_operation(ALU_SLTU, 32'h80000000, 32'h7FFFFFFF, 32'h00000000, "SLTU: 0x8000... < 0x7FFF... (unsigned)");
            test_alu_operation(ALU_SLTU, 32'hFFFFFFFF, 32'h00000000, 32'h00000000, "SLTU: Max < 0 (unsigned)");
            test_alu_operation(ALU_SLTU, 32'h00000000, 32'hFFFFFFFF, 32'h00000001, "SLTU: 0 < Max (unsigned)");
            test_alu_operation(ALU_SLTU, 32'h12345678, 32'h12345678, 32'h00000000, "SLTU: Equal values (unsigned)");
            
            $display("Comparison Tests Completed");
        end
    endtask
    
    // =================================================================
    // Test Suite: Shift Operations
    // =================================================================
    task run_shift_operation_tests();
        begin
            $display("\n[%0t] Running Shift Operation Tests...", $time);
            
            // SLL (Shift Left Logical) Tests
            test_alu_operation(ALU_SLL, 32'h12345678, 32'h00000000, 32'h12345678, "SLL: Shift by 0");
            test_alu_operation(ALU_SLL, 32'h12345678, 32'h00000004, 32'h23456780, "SLL: Shift by 4");
            test_alu_operation(ALU_SLL, 32'h12345678, 32'h0000001F, 32'h00000000, "SLL: Shift by 31");
            test_alu_operation(ALU_SLL, 32'h00000001, 32'h0000001F, 32'h80000000, "SLL: 1 shift by 31");
            test_alu_operation(ALU_SLL, 32'h12345678, 32'h00000020, 32'h12345678, "SLL: Shift by 32 (only use 5 bits)");
            
            // SRL (Shift Right Logical) Tests
            test_alu_operation(ALU_SRL, 32'h12345678, 32'h00000000, 32'h12345678, "SRL: Shift by 0");
            test_alu_operation(ALU_SRL, 32'h12345678, 32'h00000004, 32'h01234567, "SRL: Shift by 4");
            test_alu_operation(ALU_SRL, 32'h12345678, 32'h0000001F, 32'h00000000, "SRL: Shift by 31");
            test_alu_operation(ALU_SRL, 32'h80000000, 32'h0000001F, 32'h00000001, "SRL: MSB shift by 31");
            test_alu_operation(ALU_SRL, 32'hFFFFFFFF, 32'h00000001, 32'h7FFFFFFF, "SRL: All 1s shift by 1");
            
            // SRA (Shift Right Arithmetic) Tests
            test_alu_operation(ALU_SRA, 32'h12345678, 32'h00000000, 32'h12345678, "SRA: Positive shift by 0");
            test_alu_operation(ALU_SRA, 32'h12345678, 32'h00000004, 32'h01234567, "SRA: Positive shift by 4");
            test_alu_operation(ALU_SRA, 32'h80000000, 32'h00000001, 32'hC0000000, "SRA: Negative shift by 1");
            test_alu_operation(ALU_SRA, 32'h80000000, 32'h0000001F, 32'hFFFFFFFF, "SRA: Negative shift by 31");
            test_alu_operation(ALU_SRA, 32'hFFFFFFFF, 32'h00000001, 32'hFFFFFFFF, "SRA: -1 shift by 1");
            
            $display("Shift Operation Tests Completed");
        end
    endtask
    
    // =================================================================
    // Test Suite: Corner Cases
    // =================================================================
    task run_corner_case_tests();
        begin
            $display("\n[%0t] Running Corner Case Tests...", $time);
            
            // Maximum and minimum values
            test_alu_operation(ALU_ADD, 32'hFFFFFFFF, 32'hFFFFFFFF, 32'hFFFFFFFE, "Corner: Max + Max");
            test_alu_operation(ALU_SUB, 32'h00000000, 32'hFFFFFFFF, 32'h00000001, "Corner: Min - Max");
            
            // Zero operand cases
            test_alu_operation(ALU_AND, 32'h00000000, 32'hFFFFFFFF, 32'h00000000, "Corner: Zero AND Max");
            test_alu_operation(ALU_OR, 32'h00000000, 32'h00000000, 32'h00000000, "Corner: Zero OR Zero");
            
            // Sign extension corner cases
            test_alu_operation(ALU_SRA, 32'h80000001, 32'h0000001F, 32'hFFFFFFFF, "Corner: SRA sign extension");
            test_alu_operation(ALU_SLT, 32'h80000001, 32'h80000000, 32'h00000000, "Corner: SLT negative comparison");
            
            // Invalid operation code
            test_alu_operation(4'b1111, 32'h12345678, 32'h87654321, 32'h00000000, "Corner: Invalid opcode");
            
            $display("Corner Case Tests Completed");
        end
    endtask
    
    // =================================================================
    // Test Suite: Zero Flag Verification
    // =================================================================
    task run_zero_flag_tests();
        begin
            $display("\n[%0t] Running Zero Flag Tests...", $time);
            
            // Test cases that should produce zero result
            test_zero_flag(ALU_SUB, 32'h12345678, 32'h12345678, 1'b1, "Zero flag: SUB equal operands");
            test_zero_flag(ALU_XOR, 32'h12345678, 32'h12345678, 1'b1, "Zero flag: XOR equal operands");
            test_zero_flag(ALU_AND, 32'h12345678, 32'h00000000, 1'b1, "Zero flag: AND with zero");
            test_zero_flag(ALU_SLL, 32'h00000000, 32'h00000005, 1'b1, "Zero flag: SLL zero value");
            
            // Test cases that should produce non-zero result
            test_zero_flag(ALU_ADD, 32'h00000001, 32'h00000001, 1'b0, "Zero flag: ADD non-zero result");
            test_zero_flag(ALU_OR, 32'h00000001, 32'h00000000, 1'b0, "Zero flag: OR non-zero result");
            test_zero_flag(ALU_SLT, 32'h00000000, 32'h00000001, 1'b0, "Zero flag: SLT non-zero result");
            
            $display("Zero Flag Tests Completed");
        end
    endtask
    
    // =================================================================
    // Test Suite: Randomized Testing
    // =================================================================
    task run_randomized_tests();
        integer i;
        reg [31:0] rand_op1, rand_op2;
        reg [3:0] rand_ctrl;
        begin
            $display("\n[%0t] Running Randomized Tests (%0d iterations)...", $time, NUM_RANDOM_TESTS);
            
            for (i = 0; i < NUM_RANDOM_TESTS; i = i + 1) begin
                rand_op1 = $random;
                rand_op2 = $random;
                rand_ctrl = $random % 10; // Valid operations only (0-9)
                
                // Apply inputs
                operand1 = rand_op1;
                operand2 = rand_op2;
                alu_control = rand_ctrl;
                
                // Wait for propagation
                #1;
                
                // Basic sanity check - result should be stable
                if (alu_result === 32'hx || alu_result === 32'hz) begin
                    $display("ERROR: Invalid result for random test %0d: op1=0x%08h, op2=0x%08h, ctrl=%0d", 
                             i, rand_op1, rand_op2, rand_ctrl);
                    fail_count = fail_count + 1;
                end else begin
                    pass_count = pass_count + 1;
                end
                test_count = test_count + 1;
                
                if (i % (NUM_RANDOM_TESTS/10) == 0) begin
                    $display("  Random test progress: %0d%%", (i * 100) / NUM_RANDOM_TESTS);
                end
            end
            
            $display("Randomized Tests Completed");
        end
    endtask
    
    // =================================================================
    // Helper Task: Test ALU Operation
    // =================================================================
    task test_alu_operation(
        input [3:0]  op_code,
        input [31:0] op1,
        input [31:0] op2,
        input [31:0] expected_result,
        input [200*8:1] test_name
    );
        begin
            test_count = test_count + 1;
            
            // Apply inputs
            alu_control = op_code;
            operand1 = op1;
            operand2 = op2;
            
            // Wait for propagation delay
            #1;
            
            // Check result
            if (alu_result === expected_result) begin
                pass_count = pass_count + 1;
                if (VERBOSE_MODE) begin
                    $display("  ✅ PASS: %0s", test_name);
                    $display("      Op1: 0x%08h, Op2: 0x%08h, Result: 0x%08h", op1, op2, alu_result);
                end
            end else begin
                fail_count = fail_count + 1;
                $display("  ❌ FAIL: %0s", test_name);
                $display("      Op1: 0x%08h, Op2: 0x%08h", op1, op2);
                $display("      Expected: 0x%08h, Got: 0x%08h", expected_result, alu_result);
            end
        end
    endtask
    
    // =================================================================
    // Helper Task: Test Zero Flag
    // =================================================================
    task test_zero_flag(
        input [3:0]  op_code,
        input [31:0] op1,
        input [31:0] op2,
        input        expected_zero_flag,
        input [200*8:1] test_name
    );
        begin
            test_count = test_count + 1;
            
            // Apply inputs
            alu_control = op_code;
            operand1 = op1;
            operand2 = op2;
            
            // Wait for propagation delay
            #1;
            
            // Check zero flag
            if (zero_flag === expected_zero_flag) begin
                pass_count = pass_count + 1;
                if (VERBOSE_MODE) begin
                    $display("  ✅ PASS: %0s", test_name);
                    $display("      Zero flag: %0b, Result: 0x%08h", zero_flag, alu_result);
                end
            end else begin
                fail_count = fail_count + 1;
                $display("  ❌ FAIL: %0s", test_name);
                $display("      Expected zero flag: %0b, Got: %0b", expected_zero_flag, zero_flag);
                $display("      Result: 0x%08h", alu_result);
            end
        end
    endtask
    
    // =================================================================
    // Test Summary Display
    // =================================================================
    task display_test_summary();
        real pass_rate;
        begin
            $display("\n========================================");
            $display("ALU TESTBENCH SUMMARY");
            $display("========================================");
            $display("Total Tests:  %0d", test_count);
            $display("Passed:       %0d", pass_count);
            $display("Failed:       %0d", fail_count);
            
            if (test_count > 0) begin
                pass_rate = ($itor(pass_count) / $itor(test_count)) * 100.0;
                $display("Pass Rate:    %0.1f%%", pass_rate);
                
                if (fail_count == 0) begin
                    $display("🎉 ALL TESTS PASSED! ALU implementation is correct.");
                end else begin
                    $display("⚠️  Some tests failed. Review ALU implementation.");
                end
            end
            
            $display("========================================");
            $display("Simulation completed at time: %0t", $time);
        end
    endtask
    
    // =================================================================
    // Waveform Dumping
    // =================================================================
    initial begin
        $dumpfile("alu_tb.vcd");
        $dumpvars(0, alu_tb);
    end

endmodule

verify/results/alu_tb.vcd
$date
	Wed Oct  1 01:25:42 2025
$end
$version
	Icarus Verilog
$end
$timescale
	1ps
$end
$scope module alu_tb $end
$var wire 1 ! zero_flag $end
$var wire 32 " alu_result [31:0] $end
$var parameter 4 # ALU_ADD $end
$var parameter 4 $ ALU_AND $end
$var parameter 4 % ALU_OR $end
$var parameter 4 & ALU_SLL $end
$var parameter 4 ' ALU_SLT $end
$var parameter 4 ( ALU_SLTU $end
$var parameter 4 ) ALU_SRA $end
$var parameter 4 * ALU_SRL $end
$var parameter 4 + ALU_SUB $end
$var parameter 4 , ALU_XOR $end
$var parameter 32 - CLOCK_PERIOD $end
$var parameter 32 . NUM_RANDOM_TESTS $end
$var parameter 32 / VERBOSE_MODE $end
$var reg 4 0 alu_control [3:0] $end
$var reg 1 1 clk $end
$var reg 32 2 operand1 [31:0] $end
$var reg 32 3 operand2 [31:0] $end
$var integer 32 4 fail_count [31:0] $end
$var integer 32 5 pass_count [31:0] $end
$var integer 32 6 test_count [31:0] $end
$scope module dut $end
$var wire 4 7 alu_control [3:0] $end
$var wire 32 8 operand1 [31:0] $end
$var wire 32 9 operand2 [31:0] $end
$var wire 32 : signed_op1 [31:0] $end
$var wire 32 ; signed_op2 [31:0] $end
$var wire 1 ! zero_flag $end
$var wire 5 < shift_amount [4:0] $end
$var reg 32 = alu_result [31:0] $end
$upscope $end
$scope task display_test_summary $end
$var real 1 > pass_rate $end
$upscope $end
$scope task run_basic_arithmetic_tests $end
$upscope $end
$scope task run_comparison_tests $end
$upscope $end
$scope task run_corner_case_tests $end
$upscope $end
$scope task run_logic_operation_tests $end
$upscope $end
$scope task run_randomized_tests $end
$var reg 4 ? rand_ctrl [3:0] $end
$var reg 32 @ rand_op1 [31:0] $end
$var reg 32 A rand_op2 [31:0] $end
$var integer 32 B i [31:0] $end
$upscope $end
$scope task run_shift_operation_tests $end
$upscope $end
$scope task run_zero_flag_tests $end
$upscope $end
$scope task test_alu_operation $end
$var reg 32 C expected_result [31:0] $end
$var reg 32 D op1 [31:0] $end
$var reg 32 E op2 [31:0] $end
$var reg 4 F op_code [3:0] $end
$var reg 1600 G test_name [1600:1] $end
$upscope $end
$scope task test_zero_flag $end
$var reg 1 H expected_zero_flag $end
$var reg 32 I op1 [31:0] $end
$var reg 32 J op2 [31:0] $end
$var reg 4 K op_code [3:0] $end
$var reg 1600 L test_name [1600:1] $end
$upscope $end
$upscope $end
$enddefinitions $end
$comment Show the parameter values. $end
$dumpall
b1 /
b1111101000 .
b1010 -
b100 ,
b1 +
b1000 *
b1001 )
b110 (
b101 '
b111 &
b11 %
b10 $
b0 #
$end
#0
$dumpvars
bx L
bx K
bx J
bx I
xH
bx G
bx F
bx E
bx D
bx C
bx B
bx A
bx @
bx ?
r0 >
b0 =
b0 <
b0 ;
b0 :
b0 9
b0 8
b0 7
b0 6
b0 5
b0 4
b0 3
b0 2
01
b0 0
b0 "
1!
$end
#5000
11
#10000
01
#15000
11
#20000
b1 <
0!
b10011001100110011001100110011001 "
b10011001100110011001100110011001 =
01
b10000111011001010100001100100001 ;
b10000111011001010100001100100001 3
b10000111011001010100001100100001 9
b10010001101000101011001111000 :
b10010001101000101011001111000 2
b10010001101000101011001111000 8
b1 6
b1000001010001000100010000111010001000000100111001101111011100100110110101100001011011000010000001100011011000010111001101100101 G
b10011001100110011001100110011001 C
b10000111011001010100001100100001 E
b10010001101000101011001111000 D
b0 F
#21000
b11000 <
b10010001101000101011001111000 "
b10010001101000101011001111000 =
b10010001101000101011001111000 ;
b10010001101000101011001111000 3
b10010001101000101011001111000 9
b0 :
b0 2
b0 8
b10 6
b100000101000100010001000011101000100000010110100110010101110010011011110010000000101011001000000111011001100001011011000111010101100101 G
b10010001101000101011001111000 C
b10010001101000101011001111000 E
b0 D
b1 5
#22000
b1 <
1!
b0 "
b0 =
b1 ;
b1 3
b1 9
b11111111111111111111111111111111 :
b11111111111111111111111111111111 2
b11111111111111111111111111111111 8
b11 6
b10000010100010001000100001110100010000001001111011101100110010101110010011001100110110001101111011101110010000001110111011100100110000101110000 G
b0 C
b1 E
b11111111111111111111111111111111 D
b10 5
#23000
0!
b10000000000000000000000000000000 "
b10000000000000000000000000000000 =
b1111111111111111111111111111111 :
b1111111111111111111111111111111 2
b1111111111111111111111111111111 8
b100 6
b1000001010001000100010000111010001000000101000001101111011100110110100101110100011010010111011001100101001000000110111101110110011001010111001001100110011011000110111101110111 G
b10000000000000000000000000000000 C
b1111111111111111111111111111111 D
b11 5
#24000
b11000 <
b1110101001100001110110010101001 "
b1110101001100001110110010101001 =
b10010001101000101011001111000 ;
b10010001101000101011001111000 3
b10010001101000101011001111000 9
b10000111011001010100001100100001 :
b10000111011001010100001100100001 2
b10000111011001010100001100100001 8
b1 0
b1 7
b101 6
b1010011010101010100001000111010001000000100111001101111011100100110110101100001011011000010000001100011011000010111001101100101 G
b1110101000111111101101100001001 C
b10010001101000101011001111000 E
b10000111011001010100001100100001 D
b1 F
b100 5
#25000
1!
b0 "
b0 =
b10010001101000101011001111000 :
b10010001101000101011001111000 2
b10010001101000101011001111000 8
b110 6
b10100110101010101000010001110100010000001010011011000010110110101100101001000000110111101110000011001010111001001100001011011100110010001110011 G
b0 C
b10010001101000101011001111000 D
b1 4
11
#26000
0!
b11101101110010111010100110001000 "
b11101101110010111010100110001000 =
b0 :
b0 2
b0 8
b111 6
b101001101010101010000100011101000100000010110100110010101110010011011110010000000101101001000000111011001100001011011000111010101100101 G
b11101101110010111010100110001000 C
b0 D
b101 5
#27000
b1 <
b1111111111111111111111111111111 "
b1111111111111111111111111111111 =
b1 ;
b1 3
b1 9
b10000000000000000000000000000000 :
b10000000000000000000000000000000 2
b10000000000000000000000000000000 8
b1000 6
b1010011010101010100001000111010001000000101010101101110011001000110010101110010011001100110110001101111011101110010000001110111011100100110000101110000 G
b1111111111111111111111111111111 C
b1 E
b10000000000000000000000000000000 D
b110 5
#28000
b11000 <
b10010001101000101011001111000 "
b10010001101000101011001111000 =
b10010001101000101011001111000 ;
b10010001101000101011001111000 3
b10010001101000101011001111000 9
b11111111111111111111111111111111 :
b11111111111111111111111111111111 2
b11111111111111111111111111111111 8
b10 0
b10 7
b1001 6
b1000001010011100100010000111010001000000100000101101100011011000010000000110001011100110010000000100110001000000111011001100001011011000111010101100101 G
b10010001101000101011001111000 C
b10010001101000101011001111000 E
b11111111111111111111111111111111 D
b10 F
b111 5
#29000
1!
b0 "
b0 =
b0 :
b0 2
b0 8
b1010 6
b1000001010011100100010000111010001000000100000101101100011011000010000000110000011100110010000000100110001000000111011001100001011011000111010101100101 G
b0 C
b0 D
b1000 5
#30000
b10101 <
b1010101010101010101010101010101 ;
b1010101010101010101010101010101 3
b1010101010101010101010101010101 9
b10101010101010101010101010101010 :
b10101010101010101010101010101010 2
b10101010101010101010101010101010 8
b1011 6
b10000010100111001000100001110100010000001000001011011000111010001100101011100100110111001100001011101000110100101101110011001110010000001100010011010010111010001110011 G
b1010101010101010101010101010101 E
b10101010101010101010101010101010 D
b1001 5
01
#31000
b1111 <
b1111000011110000111100001111 ;
b1111000011110000111100001111 3
b1111000011110000111100001111 9
b11110000111100001111000011110000 :
b11110000111100001111000011110000 2
b11110000111100001111000011110000 8
b1100 6
b10000010100111001000100001110100010000001000011011011110110110101110000011011000110010101101101011001010110111001110100001000000110110101100001011100110110101101110011 G
b1111000011110000111100001111 E
b11110000111100001111000011110000 D
b1010 5
#32000
b11000 <
0!
b10010001101000101011001111000 "
b10010001101000101011001111000 =
b10010001101000101011001111000 ;
b10010001101000101011001111000 3
b10010001101000101011001111000 9
b0 :
b0 2
b0 8
b11 0
b11 7
b1101 6
b1001111010100100011101000100000010110100110010101110010011011110010000001111100001000000111011001100001011011000111010101100101 G
b10010001101000101011001111000 C
b10010001101000101011001111000 E
b0 D
b11 F
b1011 5
#33000
b11111111111111111111111111111111 "
b11111111111111111111111111111111 =
b11111111111111111111111111111111 :
b11111111111111111111111111111111 2
b11111111111111111111111111111111 8
b1110 6
b10011110101001000111010001000000100000101101100011011000010000000110001011100110010000001111100001000000111011001100001011011000111010101100101 G
b11111111111111111111111111111111 C
b11111111111111111111111111111111 D
b1100 5
#34000
b10101 <
b1010101010101010101010101010101 ;
b1010101010101010101010101010101 3
b1010101010101010101010101010101 9
b10101010101010101010101010101010 :
b10101010101010101010101010101010 2
b10101010101010101010101010101010 8
b1111 6
b100111101010010001110100010000001000001011011000111010001100101011100100110111001100001011101000110100101101110011001110010000001100010011010010111010001110011 G
b1010101010101010101010101010101 E
b10101010101010101010101010101010 D
b1101 5
#35000
b1111 <
b1111000011110000111100001111 ;
b1111000011110000111100001111 3
b1111000011110000111100001111 9
b11110000111100001111000011110000 :
b11110000111100001111000011110000 2
b11110000111100001111000011110000 8
b10000 6
b100111101010010001110100010000001000011011011110110110101110000011011000110010101101101011001010110111001110100001000000110110101100001011100110110101101110011 G
b1111000011110000111100001111 E
b11110000111100001111000011110000 D
b1110 5
11
#36000
b11000 <
b10010001101000101011001111000 "
b10010001101000101011001111000 =
b10010001101000101011001111000 ;
b10010001101000101011001111000 3
b10010001101000101011001111000 9
b0 :
b0 2
b0 8
b100 0
b100 7
b10001 6
b101100001001111010100100011101000100000010110100110010101110010011011110010000001011110001000000111011001100001011011000111010101100101 G
b10010001101000101011001111000 C
b10010001101000101011001111000 E
b0 D
b100 F
b1111 5
#37000
b11101101110010111010100110000111 "
b11101101110010111010100110000111 =
b11111111111111111111111111111111 :
b11111111111111111111111111111111 2
b11111111111111111111111111111111 8
b10010 6
b1011000010011110101001000111010001000000100000101101100011011000010000000110001011100110010000001011110001000000111011001100001011011000111010101100101 G
b11101101110010111010100110000111 C
b11111111111111111111111111111111 D
b10000 5
#38000
1!
b0 "
b0 =
b10010001101000101011001111000 :
b10010001101000101011001111000 2
b10010001101000101011001111000 8
b10011 6
b10110000100111101010010001110100010000001010011011000010110110101100101001000000110111101110000011001010111001001100001011011100110010001110011 G
b0 C
b10010001101000101011001111000 D
b10001 5
#39000
b10101 <
0!
b11111111111111111111111111111111 "
b11111111111111111111111111111111 =
b1010101010101010101010101010101 ;
b1010101010101010101010101010101 3
b1010101010101010101010101010101 9
b10101010101010101010101010101010 :
b10101010101010101010101010101010 2
b10101010101010101010101010101010 8
b10100 6
b10110000100111101010010001110100010000001000001011011000111010001100101011100100110111001100001011101000110100101101110011001110010000001100010011010010111010001110011 G
b11111111111111111111111111111111 C
b1010101010101010101010101010101 E
b10101010101010101010101010101010 D
b10010 5
#40000
b0 <
1!
b0 "
b0 =
b10000000000000000000000000000000 ;
b10000000000000000000000000000000 3
b10000000000000000000000000000000 9
b1111111111111111111111111111111 :
b1111111111111111111111111111111 2
b1111111111111111111111111111111 8
b101 0
b101 7
b10101 6
b101001101001100010101000011101000100000010011010110000101111000001000000111000001101111011100110110100101110100011010010111011001100101001000000011110000100000010011010110100101101110001000000110111001100101011001110110000101110100011010010111011001100101001000000010100001110011011010010110011101101110011001010110010000101001 G
b0 C
b10000000000000000000000000000000 E
b1111111111111111111111111111111 D
b101 F
b10011 5
01
#41000
b11111 <
0!
b1 "
b1 =
b1111111111111111111111111111111 ;
b1111111111111111111111111111111 3
b1111111111111111111111111111111 9
b10000000000000000000000000000000 :
b10000000000000000000000000000000 2
b10000000000000000000000000000000 8
b10110 6
b101001101001100010101000011101000100000010011010110100101101110001000000110111001100101011001110110000101110100011010010111011001100101001000000011110000100000010011010110000101111000001000000111000001101111011100110110100101110100011010010111011001100101001000000010100001110011011010010110011101101110011001010110010000101001 G
b1 C
b1111111111111111111111111111111 E
b10000000000000000000000000000000 D
b10100 5
#42000
b0 <
b0 ;
b0 3
b0 9
b11111111111111111111111111111111 :
b11111111111111111111111111111111 2
b11111111111111111111111111111111 8
b10111 6
b101001101001100010101000011101000100000001011010011000100100000001111000010000000110000001000000010100001110011011010010110011101101110011001010110010000101001 G
b0 E
b11111111111111111111111111111111 D
b10101 5
#43000
b11111 <
1!
b0 "
b0 =
b11111111111111111111111111111111 ;
b11111111111111111111111111111111 3
b11111111111111111111111111111111 9
b0 :
b0 2
b0 8
b11000 6
b101001101001100010101000011101000100000001100000010000000111100001000000010110100110001001000000010100001110011011010010110011101101110011001010110010000101001 G
b0 C
b11111111111111111111111111111111 E
b0 D
b10110 5
