src/branch_decision.v
// Branch Decision Module
// Compares operands based on branch type and generates branch decision
// Based on Blog.md section 2.1 item 5)

// =============================================================================
// Local Constants (moved from riscv_constants.vh)
// =============================================================================
`define DATA_WIDTH          32          // 32-bit data bus

// Branch Type Constants (3-bit encoding)
`define BRANCH_EQ           3'b000          // Branch if Equal
`define BRANCH_NE           3'b001          // Branch if Not Equal  
`define BRANCH_LT           3'b100          // Branch if Less Than
`define BRANCH_GE           3'b101          // Branch if Greater or Equal
`define BRANCH_LTU          3'b110          // Branch if Less Than Unsigned
`define BRANCH_GEU          3'b111          // Branch if Greater or Equal Unsigned

module branch_decision (
    // Operands for comparison (usually rs1 and rs2, possibly forwarded)
    input  wire [`DATA_WIDTH-1:0]  operand1,
    input  wire [`DATA_WIDTH-1:0]  operand2,
    
    // Branch type control signal
    input  wire [2:0]               branch_type,
    
    // Branch decision output
    output reg                      branch_taken
);

    // Signed comparison helpers
    wire signed [`DATA_WIDTH-1:0] signed_op1, signed_op2;
    assign signed_op1 = operand1;
    assign signed_op2 = operand2;
    
    always @(*) begin
        case (branch_type)
            `BRANCH_EQ: begin
                // BEQ: branch if equal
                branch_taken = (operand1 == operand2);
            end
            
            `BRANCH_NE: begin
                // BNE: branch if not equal  
                branch_taken = (operand1 != operand2);
            end
            
            `BRANCH_LT: begin
                // BLT: branch if less than (signed)
                branch_taken = (signed_op1 < signed_op2);
            end
            
            `BRANCH_GE: begin
                // BGE: branch if greater than or equal (signed)
                branch_taken = (signed_op1 >= signed_op2);
            end
            
            `BRANCH_LTU: begin
                // BLTU: branch if less than (unsigned)
                branch_taken = (operand1 < operand2);
            end
            
            `BRANCH_GEU: begin
                // BGEU: branch if greater than or equal (unsigned)  
                branch_taken = (operand1 >= operand2);
            end
            
            default: begin
                branch_taken = 1'b0;
            end
        endcase
    end

endmodule

verify/testbench/branch_decision_tb.v
// =============================================================================
// Branch Decision Testbench - Comprehensive Verification
// =============================================================================
// Description: Tests branch condition evaluation for all RISC-V branch types
// Author: Auto-generated testbench  
// Date: September 23, 2025
// Features: - All branch types testing (BEQ, BNE, BLT, BGE, BLTU, BGEU)
//          - Signed/unsigned comparison verification
//          - Corner cases and boundary testing
// =============================================================================

`timescale 1ns / 1ps

module branch_decision_tb;

    // =================================================================
    // Testbench Parameters
    // =================================================================
    parameter VERBOSE_MODE = 1;
    
    // =================================================================
    // Test Signal Declarations
    // =================================================================  
    reg [31:0]  operand1;
    reg [31:0]  operand2;
    reg [2:0]   branch_type;
    wire        branch_taken;
    
    // Test control
    integer test_count;
    integer pass_count;
    integer fail_count;
    
    // =================================================================
    // Constants (matching branch_decision.v)
    // =================================================================
    localparam BRANCH_EQ  = 3'b000;
    localparam BRANCH_NE  = 3'b001;
    localparam BRANCH_LT  = 3'b100;
    localparam BRANCH_GE  = 3'b101;
    localparam BRANCH_LTU = 3'b110;
    localparam BRANCH_GEU = 3'b111;
    
    // =================================================================
    // Device Under Test (DUT)
    // =================================================================
    branch_decision dut (
        .operand1(operand1),
        .operand2(operand2),
        .branch_type(branch_type),
        .branch_taken(branch_taken)
    );
    
    // =================================================================
    // Test Execution Control
    // =================================================================
    initial begin
        // Initialize counters
        test_count = 0;
        pass_count = 0;
        fail_count = 0;
        
        // Initialize inputs
        operand1 = 32'h0;
        operand2 = 32'h0;
        branch_type = 3'h0;
        
        $display("========================================");
        $display("BRANCH DECISION TESTBENCH STARTING");
        $display("========================================");
        $display("Time: %0t", $time);
        
        // Run test suites
        #10;
        run_beq_tests();
        run_bne_tests();
        run_blt_tests();
        run_bge_tests();
        run_bltu_tests();
        run_bgeu_tests();
        run_corner_case_tests();
        
        // Display results
        display_test_summary();
        
        #100;
        $finish;
    end
    
    // =================================================================
    // Test Suite: BEQ (Branch if Equal)
    // =================================================================
    task run_beq_tests();
        begin
            $display("\n[%0t] Running BEQ Tests...", $time);
            
            // Equal operands - should take branch
            test_branch_decision(32'h12345678, 32'h12345678, BRANCH_EQ, 1'b1, "BEQ: Equal operands");
            test_branch_decision(32'h00000000, 32'h00000000, BRANCH_EQ, 1'b1, "BEQ: Both zero");
            test_branch_decision(32'hFFFFFFFF, 32'hFFFFFFFF, BRANCH_EQ, 1'b1, "BEQ: Both all 1s");
            
            // Unequal operands - should not take branch
            test_branch_decision(32'h12345678, 32'h87654321, BRANCH_EQ, 1'b0, "BEQ: Different operands");
            test_branch_decision(32'h00000000, 32'h00000001, BRANCH_EQ, 1'b0, "BEQ: Zero vs one");
            test_branch_decision(32'h7FFFFFFF, 32'h80000000, BRANCH_EQ, 1'b0, "BEQ: Max positive vs min negative");
            
            $display("BEQ Tests Completed");
        end
    endtask
    
    // =================================================================
    // Test Suite: BNE (Branch if Not Equal)
    // =================================================================
    task run_bne_tests();
        begin
            $display("\n[%0t] Running BNE Tests...", $time);
            
            // Unequal operands - should take branch
            test_branch_decision(32'h12345678, 32'h87654321, BRANCH_NE, 1'b1, "BNE: Different operands");
            test_branch_decision(32'h00000000, 32'h00000001, BRANCH_NE, 1'b1, "BNE: Zero vs one");
            test_branch_decision(32'h7FFFFFFF, 32'h80000000, BRANCH_NE, 1'b1, "BNE: Max positive vs min negative");
            
            // Equal operands - should not take branch
            test_branch_decision(32'h12345678, 32'h12345678, BRANCH_NE, 1'b0, "BNE: Equal operands");
            test_branch_decision(32'h00000000, 32'h00000000, BRANCH_NE, 1'b0, "BNE: Both zero");
            test_branch_decision(32'hFFFFFFFF, 32'hFFFFFFFF, BRANCH_NE, 1'b0, "BNE: Both all 1s");
            
            $display("BNE Tests Completed");
        end
    endtask
    
    // =================================================================
    // Test Suite: BLT (Branch if Less Than - Signed)
    // =================================================================
    task run_blt_tests();
        begin
            $display("\n[%0t] Running BLT Tests...", $time);
            
            // op1 < op2 (signed) - should take branch
            test_branch_decision(32'h80000000, 32'h7FFFFFFF, BRANCH_LT, 1'b1, "BLT: Min negative < Max positive");
            test_branch_decision(32'hFFFFFFFF, 32'h00000000, BRANCH_LT, 1'b1, "BLT: -1 < 0");
            test_branch_decision(32'hFFFFFFFE, 32'hFFFFFFFF, BRANCH_LT, 1'b1, "BLT: -2 < -1");
            test_branch_decision(32'h00000000, 32'h00000001, BRANCH_LT, 1'b1, "BLT: 0 < 1");
            
            // op1 >= op2 (signed) - should not take branch  
            test_branch_decision(32'h7FFFFFFF, 32'h80000000, BRANCH_LT, 1'b0, "BLT: Max positive >= Min negative");
            test_branch_decision(32'h00000000, 32'hFFFFFFFF, BRANCH_LT, 1'b0, "BLT: 0 >= -1");
            test_branch_decision(32'h12345678, 32'h12345678, BRANCH_LT, 1'b0, "BLT: Equal operands");
            test_branch_decision(32'h00000001, 32'h00000000, BRANCH_LT, 1'b0, "BLT: 1 >= 0");
            
            $display("BLT Tests Completed");
        end
    endtask
    
    // =================================================================
    // Test Suite: BGE (Branch if Greater than or Equal - Signed)
    // =================================================================
    task run_bge_tests();
        begin
            $display("\n[%0t] Running BGE Tests...", $time);
            
            // op1 >= op2 (signed) - should take branch
            test_branch_decision(32'h7FFFFFFF, 32'h80000000, BRANCH_GE, 1'b1, "BGE: Max positive >= Min negative");
            test_branch_decision(32'h00000000, 32'hFFFFFFFF, BRANCH_GE, 1'b1, "BGE: 0 >= -1");
            test_branch_decision(32'h12345678, 32'h12345678, BRANCH_GE, 1'b1, "BGE: Equal operands");
            test_branch_decision(32'h00000001, 32'h00000000, BRANCH_GE, 1'b1, "BGE: 1 >= 0");
            test_branch_decision(32'hFFFFFFFF, 32'hFFFFFFFE, BRANCH_GE, 1'b1, "BGE: -1 >= -2");
            
            // op1 < op2 (signed) - should not take branch
            test_branch_decision(32'h80000000, 32'h7FFFFFFF, BRANCH_GE, 1'b0, "BGE: Min negative < Max positive");
            test_branch_decision(32'hFFFFFFFF, 32'h00000000, BRANCH_GE, 1'b0, "BGE: -1 < 0");
            test_branch_decision(32'h00000000, 32'h00000001, BRANCH_GE, 1'b0, "BGE: 0 < 1");
            
            $display("BGE Tests Completed");
        end
    endtask
    
    // =================================================================
    // Test Suite: BLTU (Branch if Less Than - Unsigned)
    // =================================================================
    task run_bltu_tests();
        begin
            $display("\n[%0t] Running BLTU Tests...", $time);
            
            // op1 < op2 (unsigned) - should take branch
            test_branch_decision(32'h7FFFFFFF, 32'h80000000, BRANCH_LTU, 1'b1, "BLTU: 0x7FFF... < 0x8000...");
            test_branch_decision(32'h00000000, 32'h00000001, BRANCH_LTU, 1'b1, "BLTU: 0 < 1");
            test_branch_decision(32'h00000000, 32'hFFFFFFFF, BRANCH_LTU, 1'b1, "BLTU: 0 < Max unsigned");
            test_branch_decision(32'hFFFFFFFE, 32'hFFFFFFFF, BRANCH_LTU, 1'b1, "BLTU: Max-1 < Max");
            
            // op1 >= op2 (unsigned) - should not take branch
            test_branch_decision(32'h80000000, 32'h7FFFFFFF, BRANCH_LTU, 1'b0, "BLTU: 0x8000... >= 0x7FFF...");
            test_branch_decision(32'hFFFFFFFF, 32'h00000000, BRANCH_LTU, 1'b0, "BLTU: Max >= 0");
            test_branch_decision(32'h12345678, 32'h12345678, BRANCH_LTU, 1'b0, "BLTU: Equal operands");
            test_branch_decision(32'h00000001, 32'h00000000, BRANCH_LTU, 1'b0, "BLTU: 1 >= 0");
            
            $display("BLTU Tests Completed");
        end
    endtask
    
    // =================================================================
    // Test Suite: BGEU (Branch if Greater than or Equal - Unsigned)
    // =================================================================
    task run_bgeu_tests();
        begin
            $display("\n[%0t] Running BGEU Tests...", $time);
            
            // op1 >= op2 (unsigned) - should take branch
            test_branch_decision(32'h80000000, 32'h7FFFFFFF, BRANCH_GEU, 1'b1, "BGEU: 0x8000... >= 0x7FFF...");
            test_branch_decision(32'hFFFFFFFF, 32'h00000000, BRANCH_GEU, 1'b1, "BGEU: Max >= 0");
            test_branch_decision(32'h12345678, 32'h12345678, BRANCH_GEU, 1'b1, "BGEU: Equal operands");
            test_branch_decision(32'h00000001, 32'h00000000, BRANCH_GEU, 1'b1, "BGEU: 1 >= 0");
            test_branch_decision(32'hFFFFFFFF, 32'hFFFFFFFE, BRANCH_GEU, 1'b1, "BGEU: Max >= Max-1");
            
            // op1 < op2 (unsigned) - should not take branch  
            test_branch_decision(32'h7FFFFFFF, 32'h80000000, BRANCH_GEU, 1'b0, "BGEU: 0x7FFF... < 0x8000...");
            test_branch_decision(32'h00000000, 32'h00000001, BRANCH_GEU, 1'b0, "BGEU: 0 < 1");
            test_branch_decision(32'h00000000, 32'hFFFFFFFF, BRANCH_GEU, 1'b0, "BGEU: 0 < Max");
            
            $display("BGEU Tests Completed");
        end
    endtask
    
    // =================================================================
    // Test Suite: Corner Cases
    // =================================================================
    task run_corner_case_tests();
        begin
            $display("\n[%0t] Running Corner Case Tests...", $time);
            
            // Invalid branch type - should not take branch
            test_branch_decision(32'h12345678, 32'h87654321, 3'b010, 1'b0, "Corner: Invalid branch type 010");
            test_branch_decision(32'h12345678, 32'h87654321, 3'b011, 1'b0, "Corner: Invalid branch type 011");
            
            // Boundary values
            test_branch_decision(32'h7FFFFFFF, 32'h7FFFFFFF, BRANCH_EQ, 1'b1, "Corner: Max positive equal");
            test_branch_decision(32'h80000000, 32'h80000000, BRANCH_EQ, 1'b1, "Corner: Min negative equal");
            
            // One's complement vs two's complement edge cases
            test_branch_decision(32'h7FFFFFFF, 32'h80000001, BRANCH_LT, 1'b0, "Corner: Signed comparison edge");
            test_branch_decision(32'h7FFFFFFF, 32'h80000001, BRANCH_LTU, 1'b1, "Corner: Unsigned comparison edge");
            
            // Zero vs negative one
            test_branch_decision(32'h00000000, 32'hFFFFFFFF, BRANCH_LT, 1'b0, "Corner: 0 vs -1 signed");
            test_branch_decision(32'h00000000, 32'hFFFFFFFF, BRANCH_LTU, 1'b1, "Corner: 0 vs -1 unsigned");
            
            $display("Corner Case Tests Completed");
        end
    endtask
    
    // =================================================================
    // Helper Task: Test Branch Decision
    // =================================================================
    task test_branch_decision(
        input [31:0] op1,
        input [31:0] op2,
        input [2:0]  br_type,
        input        expected_taken,
        input [200*8:1] test_name
    );
        begin
            test_count = test_count + 1;
            
            // Apply inputs
            operand1 = op1;
            operand2 = op2;
            branch_type = br_type;
            
            // Wait for propagation
            #1;
            
            // Check result
            if (branch_taken === expected_taken) begin
                pass_count = pass_count + 1;
                if (VERBOSE_MODE) begin
                    $display("  ✅ PASS: %0s", test_name);
                    $display("      Op1: 0x%08h, Op2: 0x%08h, Type: %0d, Taken: %0b", 
                             op1, op2, br_type, branch_taken);
                end
            end else begin
                fail_count = fail_count + 1;
                $display("  ❌ FAIL: %0s", test_name);
                $display("      Op1: 0x%08h, Op2: 0x%08h, Type: %0d", op1, op2, br_type);
                $display("      Expected: %0b, Got: %0b", expected_taken, branch_taken);
            end
        end
    endtask
    
    // =================================================================
    // Test Summary Display
    // =================================================================
    task display_test_summary();
        real pass_rate;
        begin
            $display("\n========================================");
            $display("BRANCH DECISION TESTBENCH SUMMARY");
            $display("========================================");
            $display("Total Tests:  %0d", test_count);
            $display("Passed:       %0d", pass_count);
            $display("Failed:       %0d", fail_count);
            
            if (test_count > 0) begin
                pass_rate = ($itor(pass_count) / $itor(test_count)) * 100.0;
                $display("Pass Rate:    %0.1f%%", pass_rate);
                
                if (fail_count == 0) begin
                    $display("🎉 ALL TESTS PASSED! Branch Decision implementation is correct.");
                end else begin
                    $display("⚠️  Some tests failed. Review Branch Decision implementation.");
                end
            end
            
            $display("========================================");
            $display("Simulation completed at time: %0t", $time);
        end
    endtask
    
    // =================================================================
    // Waveform Dumping
    // =================================================================
    initial begin
        $dumpfile("branch_decision_tb.vcd");
        $dumpvars(0, branch_decision_tb);
    end

endmodule

verify/results/branch_decision_tb.vcd
$date
	Tue Sep 23 21:46:15 2025
$end
$version
	Icarus Verilog
$end
$timescale
	1ps
$end
$scope module branch_decision_tb $end
$var wire 1 ! branch_taken $end
$var parameter 3 " BRANCH_EQ $end
$var parameter 3 # BRANCH_GE $end
$var parameter 3 $ BRANCH_GEU $end
$var parameter 3 % BRANCH_LT $end
$var parameter 3 & BRANCH_LTU $end
$var parameter 3 ' BRANCH_NE $end
$var parameter 32 ( VERBOSE_MODE $end
$var reg 3 ) branch_type [2:0] $end
$var reg 32 * operand1 [31:0] $end
$var reg 32 + operand2 [31:0] $end
$var integer 32 , fail_count [31:0] $end
$var integer 32 - pass_count [31:0] $end
$var integer 32 . test_count [31:0] $end
$scope module dut $end
$var wire 3 / branch_type [2:0] $end
$var wire 32 0 operand1 [31:0] $end
$var wire 32 1 operand2 [31:0] $end
$var wire 32 2 signed_op1 [31:0] $end
$var wire 32 3 signed_op2 [31:0] $end
$var reg 1 ! branch_taken $end
$upscope $end
$scope task display_test_summary $end
$var real 1 4 pass_rate $end
$upscope $end
$scope task run_beq_tests $end
$upscope $end
$scope task run_bge_tests $end
$upscope $end
$scope task run_bgeu_tests $end
$upscope $end
$scope task run_blt_tests $end
$upscope $end
$scope task run_bltu_tests $end
$upscope $end
$scope task run_bne_tests $end
$upscope $end
$scope task run_corner_case_tests $end
$upscope $end
$scope task test_branch_decision $end
$var reg 3 5 br_type [2:0] $end
$var reg 1 6 expected_taken $end
$var reg 32 7 op1 [31:0] $end
$var reg 32 8 op2 [31:0] $end
$var reg 1600 9 test_name [1600:1] $end
$upscope $end
$upscope $end
$enddefinitions $end
$comment Show the parameter values. $end
$dumpall
b1 (
b1 '
b110 &
b100 %
b111 $
b101 #
b0 "
$end
#0
$dumpvars
bx 9
bx 8
bx 7
x6
bx 5
r0 4
b0 3
b0 2
b0 1
b0 0
b0 /
b0 .
b0 -
b0 ,
b0 +
b0 *
b0 )
1!
$end
#10000
b10010001101000101011001111000 3
b10010001101000101011001111000 +
b10010001101000101011001111000 1
b10010001101000101011001111000 2
b10010001101000101011001111000 *
b10010001101000101011001111000 0
b1 .
b1000010010001010101000100111010001000000100010101110001011101010110000101101100001000000110111101110000011001010111001001100001011011100110010001110011 9
16
b0 5
b10010001101000101011001111000 8
b10010001101000101011001111000 7
#11000
b0 3
b0 +
b0 1
b0 2
b0 *
b0 0
b10 .
b100001001000101010100010011101000100000010000100110111101110100011010000010000001111010011001010111001001101111 9
b0 8
b0 7
b1 -
#12000
b11111111111111111111111111111111 3
b11111111111111111111111111111111 +
b11111111111111111111111111111111 1
b11111111111111111111111111111111 2
b11111111111111111111111111111111 *
b11111111111111111111111111111111 0
b11 .
b1000010010001010101000100111010001000000100001001101111011101000110100000100000011000010110110001101100001000000011000101110011 9
b11111111111111111111111111111111 8
b11111111111111111111111111111111 7
b10 -
#13000
0!
b10000111011001010100001100100001 3
b10000111011001010100001100100001 +
b10000111011001010100001100100001 1
b10010001101000101011001111000 2
b10010001101000101011001111000 *
b10010001101000101011001111000 0
b100 .
b100001001000101010100010011101000100000010001000110100101100110011001100110010101110010011001010110111001110100001000000110111101110000011001010111001001100001011011100110010001110011 9
06
b10000111011001010100001100100001 8
b10010001101000101011001111000 7
b11 -
#14000
b1 3
b1 +
b1 1
b0 2
b0 *
b0 0
b101 .
b1000010010001010101000100111010001000000101101001100101011100100110111100100000011101100111001100100000011011110110111001100101 9
b1 8
b0 7
b100 -
#15000
b10000000000000000000000000000000 3
b10000000000000000000000000000000 +
b10000000000000000000000000000000 1
b1111111111111111111111111111111 2
b1111111111111111111111111111111 *
b1111111111111111111111111111111 0
b110 .
b10000100100010101010001001110100010000001001101011000010111100000100000011100000110111101110011011010010111010001101001011101100110010100100000011101100111001100100000011011010110100101101110001000000110111001100101011001110110000101110100011010010111011001100101 9
b10000000000000000000000000000000 8
b1111111111111111111111111111111 7
b101 -
#16000
1!
b1 )
b1 /
b10000111011001010100001100100001 3
b10000111011001010100001100100001 +
b10000111011001010100001100100001 1
b10010001101000101011001111000 2
b10010001101000101011001111000 *
b10010001101000101011001111000 0
b111 .
b100001001001110010001010011101000100000010001000110100101100110011001100110010101110010011001010110111001110100001000000110111101110000011001010111001001100001011011100110010001110011 9
16
b1 5
b10000111011001010100001100100001 8
b10010001101000101011001111000 7
b110 -
#17000
b1 3
b1 +
b1 1
b0 2
b0 *
b0 0
b1000 .
b1000010010011100100010100111010001000000101101001100101011100100110111100100000011101100111001100100000011011110110111001100101 9
b1 8
b0 7
b111 -
#18000
b10000000000000000000000000000000 3
b10000000000000000000000000000000 +
b10000000000000000000000000000000 1
b1111111111111111111111111111111 2
b1111111111111111111111111111111 *
b1111111111111111111111111111111 0
b1001 .
b10000100100111001000101001110100010000001001101011000010111100000100000011100000110111101110011011010010111010001101001011101100110010100100000011101100111001100100000011011010110100101101110001000000110111001100101011001110110000101110100011010010111011001100101 9
b10000000000000000000000000000000 8
b1111111111111111111111111111111 7
b1000 -
#19000
0!
b10010001101000101011001111000 3
b10010001101000101011001111000 +
b10010001101000101011001111000 1
b10010001101000101011001111000 2
b10010001101000101011001111000 *
b10010001101000101011001111000 0
b1010 .
b1000010010011100100010100111010001000000100010101110001011101010110000101101100001000000110111101110000011001010111001001100001011011100110010001110011 9
06
b10010001101000101011001111000 8
b10010001101000101011001111000 7
b1001 -
#20000
b0 3
b0 +
b0 1
b0 2
b0 *
b0 0
b1011 .
b100001001001110010001010011101000100000010000100110111101110100011010000010000001111010011001010111001001101111 9
b0 8
b0 7
b1010 -
#21000
b11111111111111111111111111111111 3
b11111111111111111111111111111111 +
b11111111111111111111111111111111 1
b11111111111111111111111111111111 2
b11111111111111111111111111111111 *
b11111111111111111111111111111111 0
b1100 .
b1000010010011100100010100111010001000000100001001101111011101000110100000100000011000010110110001101100001000000011000101110011 9
b11111111111111111111111111111111 8
b11111111111111111111111111111111 7
b1011 -
#22000
1!
b100 )
b100 /
b1111111111111111111111111111111 3
b1111111111111111111111111111111 +
b1111111111111111111111111111111 1
b10000000000000000000000000000000 2
b10000000000000000000000000000000 *
b10000000000000000000000000000000 0
b1101 .
b100001001001100010101000011101000100000010011010110100101101110001000000110111001100101011001110110000101110100011010010111011001100101001000000011110000100000010011010110000101111000001000000111000001101111011100110110100101110100011010010111011001100101 9
16
b100 5
b1111111111111111111111111111111 8
b10000000000000000000000000000000 7
b1100 -
#23000
b0 3
b0 +
b0 1
b11111111111111111111111111111111 2
b11111111111111111111111111111111 *
b11111111111111111111111111111111 0
b1110 .
b100001001001100010101000011101000100000001011010011000100100000001111000010000000110000 9
b0 8
b11111111111111111111111111111111 7
b1101 -
#24000
b11111111111111111111111111111111 3
b11111111111111111111111111111111 +
b11111111111111111111111111111111 1
b11111111111111111111111111111110 2
b11111111111111111111111111111110 *
b11111111111111111111111111111110 0
b1111 .
b10000100100110001010100001110100010000000101101001100100010000000111100001000000010110100110001 9
b11111111111111111111111111111111 8
b11111111111111111111111111111110 7
b1110 -
#25000
b1 3
b1 +
b1 1
b0 2
b0 *
b0 0
b10000 .
b1000010010011000101010000111010001000000011000000100000001111000010000000110001 9
b1 8
b0 7
b1111 -
#26000
0!
b10000000000000000000000000000000 3
b10000000000000000000000000000000 +
b10000000000000000000000000000000 1
b1111111111111111111111111111111 2
b1111111111111111111111111111111 *
b1111111111111111111111111111111 0
b10001 .
b10000100100110001010100001110100010000001001101011000010111100000100000011100000110111101110011011010010111010001101001011101100110010100100000001111100011110100100000010011010110100101101110001000000110111001100101011001110110000101110100011010010111011001100101 9
06
b10000000000000000000000000000000 8
b1111111111111111111111111111111 7
b10000 -
#27000
b11111111111111111111111111111111 3
b11111111111111111111111111111111 +
b11111111111111111111111111111111 1
b0 2
b0 *
b0 0
b10010 .
b10000100100110001010100001110100010000000110000001000000011111000111101001000000010110100110001 9
b11111111111111111111111111111111 8
b0 7
b10001 -
#28000
b10010001101000101011001111000 3
b10010001101000101011001111000 +
b10010001101000101011001111000 1
b10010001101000101011001111000 2
b10010001101000101011001111000 *
b10010001101000101011001111000 0
b10011 .
b1000010010011000101010000111010001000000100010101110001011101010110000101101100001000000110111101110000011001010111001001100001011011100110010001110011 9
b10010001101000101011001111000 8
b10010001101000101011001111000 7
b10010 -
#29000
b0 3
b0 +
b0 1
b1 2
b1 *
b1 0
b10100 .
b100001001001100010101000011101000100000001100010010000000111110001111010010000000110000 9
b0 8
b1 7
b10011 -
#30000
1!
b101 )
b101 /
b10000000000000000000000000000000 3
b10000000000000000000000000000000 +
b10000000000000000000000000000000 1
b1111111111111111111111111111111 2
b1111111111111111111111111111111 *
b1111111111111111111111111111111 0
b10101 .
b10000100100011101000101001110100010000001001101011000010111100000100000011100000110111101110011011010010111010001101001011101100110010100100000001111100011110100100000010011010110100101101110001000000110111001100101011001110110000101110100011010010111011001100101 9
16
b101 5
b10000000000000000000000000000000 8
b1111111111111111111111111111111 7
b10100 -
#31000
b11111111111111111111111111111111 3
b11111111111111111111111111111111 +
b11111111111111111111111111111111 1
b0 2
b0 *
b0 0
b10110 .
b10000100100011101000101001110100010000000110000001000000011111000111101001000000010110100110001 9
b11111111111111111111111111111111 8
b0 7
b10101 -
#32000
b10010001101000101011001111000 3
b10010001101000101011001111000 +
b10010001101000101011001111000 1
b10010001101000101011001111000 2
b10010001101000101011001111000 *
b10010001101000101011001111000 0
b10111 .
b1000010010001110100010100111010001000000100010101110001011101010110000101101100001000000110111101110000011001010111001001100001011011100110010001110011 9
b10010001101000101011001111000 8
b10010001101000101011001111000 7
b10110 -
#33000
b0 3
b0 +
b0 1
b1 2
b1 *
b1 0
b11000 .
b100001001000111010001010011101000100000001100010010000000111110001111010010000000110000 9
b0 8
b1 7
b10111 -
#34000
b11111111111111111111111111111110 3
b11111111111111111111111111111110 +
b11111111111111111111111111111110 1
b11111111111111111111111111111111 2
b11111111111111111111111111111111 *
b11111111111111111111111111111111 0
b11001 .
b1000010010001110100010100111010001000000010110100110001001000000011111000111101001000000010110100110010 9
b11111111111111111111111111111110 8
b11111111111111111111111111111111 7
b11000 -
#35000
0!
b1111111111111111111111111111111 3
b1111111111111111111111111111111 +
b1111111111111111111111111111111 1
b10000000000000000000000000000000 2
b10000000000000000000000000000000 *
b10000000000000000000000000000000 0
b11010 .
b100001001000111010001010011101000100000010011010110100101101110001000000110111001100101011001110110000101110100011010010111011001100101001000000011110000100000010011010110000101111000001000000111000001101111011100110110100101110100011010010111011001100101 9
06
b1111111111111111111111111111111 8
b10000000000000000000000000000000 7
b11001 -
#36000
b0 3
b0 +
b0 1
b11111111111111111111111111111111 2
b11111111111111111111111111111111 *
b11111111111111111111111111111111 0
b11011 .
b100001001000111010001010011101000100000001011010011000100100000001111000010000000110000 9
b0 8
b11111111111111111111111111111111 7
b11010 -
#37000
b1 3
b1 +
b1 1
b0 2
b0 *
b0 0
b11100 .
b1000010010001110100010100111010001000000011000000100000001111000010000000110001 9
b1 8
b0 7
b11011 -
#38000
1!
b110 )
b110 /
b10000000000000000000000000000000 3
b10000000000000000000000000000000 +
b10000000000000000000000000000000 1
b1111111111111111111111111111111 2
b1111111111111111111111111111111 *
b1111111111111111111111111111111 0
b11101 .
b10000100100110001010100010101010011101000100000001100000111100000110111010001100100011001000110001011100010111000101110001000000011110000100000001100000111100000111000001100000011000000110000001011100010111000101110 9
16
b110 5
b10000000000000000000000000000000 8
b1111111111111111111111111111111 7
b11100 -
#39000
b1 3
b1 +
b1 1
b0 2
b0 *
b0 0
b11110 .
b100001001001100010101000101010100111010001000000011000000100000001111000010000000110001 9
b1 8
b0 7
b11101 -
#40000
b11111111111111111111111111111111 3
b11111111111111111111111111111111 +
b11111111111111111111111111111111 1
b11111 .
b1000010010011000101010001010101001110100010000000110000001000000011110000100000010011010110000101111000001000000111010101101110011100110110100101100111011011100110010101100100 9
b11111111111111111111111111111111 8
b11110 -
#41000
b11111111111111111111111111111110 2
b11111111111111111111111111111110 *
b11111111111111111111111111111110 0
b100000 .
b100001001001100010101000101010100111010001000000100110101100001011110000010110100110001001000000011110000100000010011010110000101111000 9
b11111111111111111111111111111110 7
b11111 -
#42000
0!
b1111111111111111111111111111111 3
b1111111111111111111111111111111 +
b1111111111111111111111111111111 1
b10000000000000000000000000000000 2
b10000000000000000000000000000000 *
b10000000000000000000000000000000 0
b100001 .
b1000010010011000101010001010101001110100010000000110000011110000011100000110000001100000011000000101110001011100010111000100000001111100011110100100000001100000111100000110111010001100100011001000110001011100010111000101110 9
06
b1111111111111111111111111111111 8
b10000000000000000000000000000000 7
b100000 -
#43000
b0 3
b0 +
b0 1
b11111111111111111111111111111111 2
b11111111111111111111111111111111 *
b11111111111111111111111111111111 0
b100010 .
b100001001001100010101000101010100111010001000000100110101100001011110000010000000111110001111010010000000110000 9
b0 8
b11111111111111111111111111111111 7
b100001 -
#44000
b10010001101000101011001111000 3
b10010001101000101011001111000 +
b10010001101000101011001111000 1
b10010001101000101011001111000 2
b10010001101000101011001111000 *
b10010001101000101011001111000 0
b100011 .
b100001001001100010101000101010100111010001000000100010101110001011101010110000101101100001000000110111101110000011001010111001001100001011011100110010001110011 9
b10010001101000101011001111000 8
b10010001101000101011001111000 7
b100010 -
#45000
b0 3
b0 +
b0 1
b1 2
b1 *
b1 0
b100100 .
b10000100100110001010100010101010011101000100000001100010010000000111110001111010010000000110000 9
b0 8
b1 7
b100011 -
#46000
1!
b111 )
b111 /
b1111111111111111111111111111111 3
b1111111111111111111111111111111 +
b1111111111111111111111111111111 1
b10000000000000000000000000000000 2
b10000000000000000000000000000000 *
b10000000000000000000000000000000 0
b100101 .
b1000010010001110100010101010101001110100010000000110000011110000011100000110000001100000011000000101110001011100010111000100000001111100011110100100000001100000111100000110111010001100100011001000110001011100010111000101110 9
16
b111 5
b1111111111111111111111111111111 8
b10000000000000000000000000000000 7
b100100 -
#47000
b0 3
b0 +
b0 1
b11111111111111111111111111111111 2
b11111111111111111111111111111111 *
b11111111111111111111111111111111 0
b100110 .
b100001001000111010001010101010100111010001000000100110101100001011110000010000000111110001111010010000000110000 9
b0 8
b11111111111111111111111111111111 7
b100101 -
#48000
b10010001101000101011001111000 3
b10010001101000101011001111000 +
b10010001101000101011001111000 1
b10010001101000101011001111000 2
b10010001101000101011001111000 *
b10010001101000101011001111000 0
b100111 .
b100001001000111010001010101010100111010001000000100010101110001011101010110000101101100001000000110111101110000011001010111001001100001011011100110010001110011 9
b10010001101000101011001111000 8
b10010001101000101011001111000 7
b100110 -
#49000
b0 3
b0 +
b0 1
b1 2
b1 *
b1 0
b101000 .
b10000100100011101000101010101010011101000100000001100010010000000111110001111010010000000110000 9
b0 8
b1 7
b100111 -
#50000
b11111111111111111111111111111110 3
b11111111111111111111111111111110 +
b11111111111111111111111111111110 1
b11111111111111111111111111111111 2
b11111111111111111111111111111111 *
b11111111111111111111111111111111 0
b101001 .
b10000100100011101000101010101010011101000100000010011010110000101111000001000000011111000111101001000000100110101100001011110000010110100110001 9
b11111111111111111111111111111110 8
b11111111111111111111111111111111 7
b101000 -
#51000
0!
b10000000000000000000000000000000 3
b10000000000000000000000000000000 +
b10000000000000000000000000000000 1
b1111111111111111111111111111111 2
b1111111111111111111111111111111 *
b1111111111111111111111111111111 0
b101010 .
b10000100100011101000101010101010011101000100000001100000111100000110111010001100100011001000110001011100010111000101110001000000011110000100000001100000111100000111000001100000011000000110000001011100010111000101110 9
06
b10000000000000000000000000000000 8
b1111111111111111111111111111111 7
b101001 -
#52000
b1 3
b1 +
b1 1
b0 2
b0 *
b0 0
b101011 .
b100001001000111010001010101010100111010001000000011000000100000001111000010000000110001 9
b1 8
b0 7
b101010 -
#53000
b11111111111111111111111111111111 3
b11111111111111111111111111111111 +
b11111111111111111111111111111111 1
b101100 .
b1000010010001110100010101010101001110100010000000110000001000000011110000100000010011010110000101111000 9
b11111111111111111111111111111111 8
b101011 -
