src/data_extension.v
// Data Extension Module
// Handles load data extension for different load sizes (LB, LH, LW, LBU, LHU)
// Based on Blog.md section 2.1 item 8)

// =============================================================================
// Local Constants (moved from riscv_constants.vh)
// =============================================================================
`define DATA_WIDTH          32          // 32-bit data bus

// Funct3 Constants for Load Operations
`define FUNCT3_LB           3'b000          // Load Byte
`define FUNCT3_LH           3'b001          // Load Halfword
`define FUNCT3_LW           3'b010          // Load Word
`define FUNCT3_LBU          3'b100          // Load Byte Unsigned
`define FUNCT3_LHU          3'b101          // Load Halfword Unsigned

module data_extension (
    // 32-bit word from data memory
    input  wire [`DATA_WIDTH-1:0]  memory_data,
    
    // Address bits [1:0] to select byte/halfword within word
    input  wire [1:0]               byte_select,
    
    // Load instruction funct3 to determine extension type
    input  wire [2:0]               load_type,
    
    // Extended data output for register write
    output reg  [`DATA_WIDTH-1:0]  extended_data
);

    // Extract byte and halfword from memory data based on address
    reg [7:0]  selected_byte;
    reg [15:0] selected_halfword;
    
    // Byte selection mux
    always @(*) begin
        case (byte_select)
            2'b00: selected_byte = memory_data[7:0];
            2'b01: selected_byte = memory_data[15:8];
            2'b10: selected_byte = memory_data[23:16];
            2'b11: selected_byte = memory_data[31:24];
        endcase
    end
    
    // Halfword selection mux  
    always @(*) begin
        selected_halfword = byte_select[1] ? memory_data[31:16] : memory_data[15:0];
    end
    
    // Extension logic based on load type
    always @(*) begin
        case (load_type)
            `FUNCT3_LB: begin
                // Load byte with sign extension
                extended_data = {{24{selected_byte[7]}}, selected_byte};
            end
            
            `FUNCT3_LH: begin
                // Load halfword with sign extension
                extended_data = {{16{selected_halfword[15]}}, selected_halfword};
            end
            
            `FUNCT3_LW: begin
                // Load word (no extension needed)
                extended_data = memory_data;
            end
            
            `FUNCT3_LBU: begin
                // Load byte unsigned (zero extension)
                extended_data = {24'h000000, selected_byte};
            end
            
            `FUNCT3_LHU: begin
                // Load halfword unsigned (zero extension)  
                extended_data = {16'h0000, selected_halfword};
            end
            
            default: begin
                // Default to word load
                extended_data = memory_data;
            end
        endcase
    end

endmodule

verify/testbench/data_extension_tb.v
// =============================================================================
// Data Extension Testbench - Comprehensive Verification
// =============================================================================
// Description: Tests data extension for all RISC-V load types (LB, LH, LW, LBU, LHU)
// Author: Auto-generated testbench
// Date: September 23, 2025  
// Features: - All load types testing
//          - Signed/unsigned extension verification
//          - Byte selection testing
//          - Corner cases and boundary testing
// =============================================================================

`timescale 1ns / 1ps

module data_extension_tb;

    // =================================================================
    // Testbench Parameters
    // =================================================================
    parameter VERBOSE_MODE = 1;
    
    // =================================================================
    // Test Signal Declarations
    // =================================================================
    reg [31:0]  memory_data;
    reg [1:0]   byte_select;
    reg [2:0]   load_type;
    wire [31:0] extended_data;
    
    // Test control
    integer test_count;
    integer pass_count;
    integer fail_count;
    
    // =================================================================
    // Constants (matching data_extension.v)
    // =================================================================
    localparam FUNCT3_LB  = 3'b000;
    localparam FUNCT3_LH  = 3'b001;
    localparam FUNCT3_LW  = 3'b010;
    localparam FUNCT3_LBU = 3'b100;
    localparam FUNCT3_LHU = 3'b101;
    
    // =================================================================
    // Device Under Test (DUT)
    // =================================================================
    data_extension dut (
        .memory_data(memory_data),
        .byte_select(byte_select),
        .load_type(load_type),
        .extended_data(extended_data)
    );
    
    // =================================================================
    // Test Execution Control
    // =================================================================
    initial begin
        // Initialize counters
        test_count = 0;
        pass_count = 0;
        fail_count = 0;
        
        // Initialize inputs
        memory_data = 32'h0;
        byte_select = 2'h0;
        load_type = 3'h0;
        
        $display("========================================");
        $display("DATA EXTENSION TESTBENCH STARTING");
        $display("========================================");
        $display("Time: %0t", $time);
        
        // Run test suites
        #10;
        run_lb_tests();
        run_lh_tests();
        run_lw_tests();
        run_lbu_tests();
        run_lhu_tests();
        run_corner_case_tests();
        
        // Display results
        display_test_summary();
        
        #100;
        $finish;
    end
    
    // =================================================================
    // Test Suite: LB (Load Byte - Signed)
    // =================================================================
    task run_lb_tests();
        begin
            $display("\n[%0t] Running LB Tests...", $time);
            
            // Test memory data: 0x87654321
            // Byte 0: 0x21 (positive), Byte 1: 0x43 (positive)  
            // Byte 2: 0x65 (positive), Byte 3: 0x87 (negative)
            
            // Positive byte values (sign extension with 0)
            test_data_extension(32'h87654321, 2'b00, FUNCT3_LB, 32'h00000021, "LB: Byte 0 - positive");
            test_data_extension(32'h87654321, 2'b01, FUNCT3_LB, 32'h00000043, "LB: Byte 1 - positive");
            test_data_extension(32'h87654321, 2'b10, FUNCT3_LB, 32'h00000065, "LB: Byte 2 - positive");
            
            // Negative byte value (sign extension with 1)
            test_data_extension(32'h87654321, 2'b11, FUNCT3_LB, 32'hFFFFFF87, "LB: Byte 3 - negative");
            
            // Test with different memory data
            test_data_extension(32'hFEDCBA98, 2'b00, FUNCT3_LB, 32'hFFFFFF98, "LB: Negative byte at position 0");
            test_data_extension(32'hFEDCBA98, 2'b01, FUNCT3_LB, 32'hFFFFFFBA, "LB: Negative byte at position 1");
            test_data_extension(32'hFEDCBA98, 2'b10, FUNCT3_LB, 32'hFFFFFFDC, "LB: Negative byte at position 2");
            test_data_extension(32'hFEDCBA98, 2'b11, FUNCT3_LB, 32'hFFFFFFFE, "LB: Negative byte at position 3");
            
            // Boundary cases
            test_data_extension(32'h00000000, 2'b00, FUNCT3_LB, 32'h00000000, "LB: Zero byte");
            test_data_extension(32'h7F7F7F7F, 2'b00, FUNCT3_LB, 32'h0000007F, "LB: Maximum positive byte");
            test_data_extension(32'h80808080, 2'b00, FUNCT3_LB, 32'hFFFFFF80, "LB: Minimum negative byte");
            test_data_extension(32'hFFFFFFFF, 2'b00, FUNCT3_LB, 32'hFFFFFFFF, "LB: All 1s");
            
            $display("LB Tests Completed");
        end
    endtask
    
    // =================================================================
    // Test Suite: LH (Load Halfword - Signed)
    // =================================================================
    task run_lh_tests();
        begin
            $display("\n[%0t] Running LH Tests...", $time);
            
            // Test memory data: 0x87654321
            // Lower halfword: 0x4321 (positive), Upper halfword: 0x8765 (negative)
            
            // Positive halfword (sign extension with 0)
            test_data_extension(32'h87654321, 2'b00, FUNCT3_LH, 32'h00004321, "LH: Lower halfword - positive");
            test_data_extension(32'h87654321, 2'b01, FUNCT3_LH, 32'h00004321, "LH: Lower halfword - byte_select[0] ignored");
            
            // Negative halfword (sign extension with 1) 
            test_data_extension(32'h87654321, 2'b10, FUNCT3_LH, 32'hFFFF8765, "LH: Upper halfword - negative");
            test_data_extension(32'h87654321, 2'b11, FUNCT3_LH, 32'hFFFF8765, "LH: Upper halfword - byte_select[0] ignored");
            
            // Test with different memory data
            test_data_extension(32'h12349876, 2'b00, FUNCT3_LH, 32'hFFFF9876, "LH: Negative lower halfword");
            test_data_extension(32'h12349876, 2'b10, FUNCT3_LH, 32'h00001234, "LH: Positive upper halfword");
            
            // Boundary cases
            test_data_extension(32'h00000000, 2'b00, FUNCT3_LH, 32'h00000000, "LH: Zero halfword");
            test_data_extension(32'h7FFF7FFF, 2'b00, FUNCT3_LH, 32'h00007FFF, "LH: Maximum positive halfword");
            test_data_extension(32'h80008000, 2'b00, FUNCT3_LH, 32'hFFFF8000, "LH: Minimum negative halfword");
            test_data_extension(32'hFFFFFFFF, 2'b00, FUNCT3_LH, 32'hFFFFFFFF, "LH: All 1s");
            
            $display("LH Tests Completed");
        end
    endtask
    
    // =================================================================
    // Test Suite: LW (Load Word)
    // =================================================================
    task run_lw_tests();
        begin
            $display("\n[%0t] Running LW Tests...", $time);
            
            // For word loads, byte_select should be ignored and full word returned
            test_data_extension(32'h87654321, 2'b00, FUNCT3_LW, 32'h87654321, "LW: Full word - byte_select 00");
            test_data_extension(32'h87654321, 2'b01, FUNCT3_LW, 32'h87654321, "LW: Full word - byte_select 01");
            test_data_extension(32'h87654321, 2'b10, FUNCT3_LW, 32'h87654321, "LW: Full word - byte_select 10");
            test_data_extension(32'h87654321, 2'b11, FUNCT3_LW, 32'h87654321, "LW: Full word - byte_select 11");
            
            // Test various word values
            test_data_extension(32'h00000000, 2'b00, FUNCT3_LW, 32'h00000000, "LW: Zero word");
            test_data_extension(32'hFFFFFFFF, 2'b00, FUNCT3_LW, 32'hFFFFFFFF, "LW: All 1s word");
            test_data_extension(32'h7FFFFFFF, 2'b00, FUNCT3_LW, 32'h7FFFFFFF, "LW: Maximum positive word");
            test_data_extension(32'h80000000, 2'b00, FUNCT3_LW, 32'h80000000, "LW: Minimum negative word");
            test_data_extension(32'hAAAA5555, 2'b00, FUNCT3_LW, 32'hAAAA5555, "LW: Alternating pattern");
            
            $display("LW Tests Completed");
        end
    endtask
    
    // =================================================================
    // Test Suite: LBU (Load Byte Unsigned - Zero Extension)
    // =================================================================
    task run_lbu_tests();
        begin
            $display("\n[%0t] Running LBU Tests...", $time);
            
            // Test memory data: 0x87654321
            // All bytes should be zero-extended regardless of sign bit
            test_data_extension(32'h87654321, 2'b00, FUNCT3_LBU, 32'h00000021, "LBU: Byte 0 - zero extended");
            test_data_extension(32'h87654321, 2'b01, FUNCT3_LBU, 32'h00000043, "LBU: Byte 1 - zero extended");
            test_data_extension(32'h87654321, 2'b10, FUNCT3_LBU, 32'h00000065, "LBU: Byte 2 - zero extended");
            test_data_extension(32'h87654321, 2'b11, FUNCT3_LBU, 32'h00000087, "LBU: Byte 3 - zero extended (was negative in LB)");
            
            // Test with bytes that have sign bit set (should still zero extend)
            test_data_extension(32'hFEDCBA98, 2'b00, FUNCT3_LBU, 32'h00000098, "LBU: Sign bit byte - zero extended");
            test_data_extension(32'hFEDCBA98, 2'b01, FUNCT3_LBU, 32'h000000BA, "LBU: Sign bit byte - zero extended");
            test_data_extension(32'hFEDCBA98, 2'b10, FUNCT3_LBU, 32'h000000DC, "LBU: Sign bit byte - zero extended");
            test_data_extension(32'hFEDCBA98, 2'b11, FUNCT3_LBU, 32'h000000FE, "LBU: Sign bit byte - zero extended");
            
            // Boundary cases
            test_data_extension(32'h00000000, 2'b00, FUNCT3_LBU, 32'h00000000, "LBU: Zero byte");
            test_data_extension(32'h7F7F7F7F, 2'b00, FUNCT3_LBU, 32'h0000007F, "LBU: Maximum positive byte");
            test_data_extension(32'h80808080, 2'b00, FUNCT3_LBU, 32'h00000080, "LBU: Byte with sign bit set");
            test_data_extension(32'hFFFFFFFF, 2'b00, FUNCT3_LBU, 32'h000000FF, "LBU: Maximum byte value");
            
            $display("LBU Tests Completed");
        end
    endtask
    
    // =================================================================
    // Test Suite: LHU (Load Halfword Unsigned - Zero Extension)
    // =================================================================
    task run_lhu_tests();
        begin
            $display("\n[%0t] Running LHU Tests...", $time);
            
            // Test memory data: 0x87654321
            // All halfwords should be zero-extended regardless of sign bit
            test_data_extension(32'h87654321, 2'b00, FUNCT3_LHU, 32'h00004321, "LHU: Lower halfword - zero extended");
            test_data_extension(32'h87654321, 2'b01, FUNCT3_LHU, 32'h00004321, "LHU: Lower halfword - byte_select[0] ignored");
            test_data_extension(32'h87654321, 2'b10, FUNCT3_LHU, 32'h00008765, "LHU: Upper halfword - zero extended");
            test_data_extension(32'h87654321, 2'b11, FUNCT3_LHU, 32'h00008765, "LHU: Upper halfword - byte_select[0] ignored");
            
            // Test with halfwords that have sign bit set
            test_data_extension(32'h98769876, 2'b00, FUNCT3_LHU, 32'h00009876, "LHU: Sign bit halfword - zero extended");
            test_data_extension(32'h98769876, 2'b10, FUNCT3_LHU, 32'h00009876, "LHU: Sign bit halfword - zero extended");
            
            // Mixed positive/negative halfwords
            test_data_extension(32'h12349876, 2'b00, FUNCT3_LHU, 32'h00009876, "LHU: Negative lower halfword - zero extended");
            test_data_extension(32'h12349876, 2'b10, FUNCT3_LHU, 32'h00001234, "LHU: Positive upper halfword - zero extended");
            
            // Boundary cases
            test_data_extension(32'h00000000, 2'b00, FUNCT3_LHU, 32'h00000000, "LHU: Zero halfword");
            test_data_extension(32'h7FFF7FFF, 2'b00, FUNCT3_LHU, 32'h00007FFF, "LHU: Maximum positive halfword");
            test_data_extension(32'h80008000, 2'b00, FUNCT3_LHU, 32'h00008000, "LHU: Halfword with sign bit set");
            test_data_extension(32'hFFFFFFFF, 2'b00, FUNCT3_LHU, 32'h0000FFFF, "LHU: Maximum halfword value");
            
            $display("LHU Tests Completed");
        end
    endtask
    
    // =================================================================
    // Test Suite: Corner Cases
    // =================================================================
    task run_corner_case_tests();
        begin
            $display("\n[%0t] Running Corner Case Tests...", $time);
            
            // Invalid load type - should default to LW behavior
            test_data_extension(32'h87654321, 2'b00, 3'b011, 32'h87654321, "Corner: Invalid load type - defaults to LW");
            test_data_extension(32'h87654321, 2'b00, 3'b110, 32'h87654321, "Corner: Invalid load type - defaults to LW");
            test_data_extension(32'h87654321, 2'b00, 3'b111, 32'h87654321, "Corner: Invalid load type - defaults to LW");
            
            // Test sign extension boundaries for bytes
            test_data_extension(32'h007F807F, 2'b00, FUNCT3_LB, 32'h0000007F, "Corner: Byte sign boundary - positive");
            test_data_extension(32'h007F807F, 2'b10, FUNCT3_LB, 32'hFFFFFF80, "Corner: Byte sign boundary - negative");
            
            // Test sign extension boundaries for halfwords  
            test_data_extension(32'h7FFF8000, 2'b00, FUNCT3_LH, 32'hFFFF8000, "Corner: Halfword sign boundary - negative");
            test_data_extension(32'h7FFF8000, 2'b10, FUNCT3_LH, 32'h00007FFF, "Corner: Halfword sign boundary - positive");
            
            // Test byte selection with all same bytes
            test_data_extension(32'h12121212, 2'b00, FUNCT3_LB, 32'h00000012, "Corner: All same bytes - select 0");
            test_data_extension(32'h12121212, 2'b01, FUNCT3_LB, 32'h00000012, "Corner: All same bytes - select 1");
            test_data_extension(32'h12121212, 2'b10, FUNCT3_LB, 32'h00000012, "Corner: All same bytes - select 2");
            test_data_extension(32'h12121212, 2'b11, FUNCT3_LB, 32'h00000012, "Corner: All same bytes - select 3");
            
            $display("Corner Case Tests Completed");
        end
    endtask
    
    // =================================================================
    // Helper Task: Test Data Extension
    // =================================================================
    task test_data_extension(
        input [31:0] mem_data,
        input [1:0]  byte_sel,
        input [2:0]  load_typ,
        input [31:0] expected_data,
        input [200*8:1] test_name
    );
        begin
            test_count = test_count + 1;
            
            // Apply inputs
            memory_data = mem_data;
            byte_select = byte_sel;
            load_type = load_typ;
            
            // Wait for propagation
            #1;
            
            // Check result
            if (extended_data === expected_data) begin
                pass_count = pass_count + 1;
                if (VERBOSE_MODE) begin
                    $display("  ✅ PASS: %0s", test_name);
                    $display("      Mem: 0x%08h, Sel: %0d, Type: %0d, Extended: 0x%08h", 
                             mem_data, byte_sel, load_typ, extended_data);
                end
            end else begin
                fail_count = fail_count + 1;
                $display("  ❌ FAIL: %0s", test_name);
                $display("      Mem: 0x%08h, Sel: %0d, Type: %0d", mem_data, byte_sel, load_typ);
                $display("      Expected: 0x%08h, Got: 0x%08h", expected_data, extended_data);
            end
        end
    endtask
    
    // =================================================================
    // Test Summary Display
    // =================================================================
    task display_test_summary();
        real pass_rate;
        begin
            $display("\n========================================");
            $display("DATA EXTENSION TESTBENCH SUMMARY");
            $display("========================================");
            $display("Total Tests:  %0d", test_count);
            $display("Passed:       %0d", pass_count);
            $display("Failed:       %0d", fail_count);
            
            if (test_count > 0) begin
                pass_rate = ($itor(pass_count) / $itor(test_count)) * 100.0;
                $display("Pass Rate:    %0.1f%%", pass_rate);
                
                if (fail_count == 0) begin
                    $display("🎉 ALL TESTS PASSED! Data Extension implementation is correct.");
                end else begin
                    $display("⚠️  Some tests failed. Review Data Extension implementation.");
                end
            end
            
            $display("========================================");
            $display("Simulation completed at time: %0t", $time);
        end
    endtask
    
    // =================================================================
    // Waveform Dumping
    // =================================================================
    initial begin
        $dumpfile("data_extension_tb.vcd");
        $dumpvars(0, data_extension_tb);
    end

endmodule

verify/results/data_extension_tb.vcd
$date
	Thu Sep 25 18:33:14 2025
$end
$version
	Icarus Verilog
$end
$timescale
	1ps
$end
$scope module data_extension_tb $end
$var wire 32 ! extended_data [31:0] $end
$var parameter 3 " FUNCT3_LB $end
$var parameter 3 # FUNCT3_LBU $end
$var parameter 3 $ FUNCT3_LH $end
$var parameter 3 % FUNCT3_LHU $end
$var parameter 3 & FUNCT3_LW $end
$var parameter 32 ' VERBOSE_MODE $end
$var reg 2 ( byte_select [1:0] $end
$var reg 3 ) load_type [2:0] $end
$var reg 32 * memory_data [31:0] $end
$var integer 32 + fail_count [31:0] $end
$var integer 32 , pass_count [31:0] $end
$var integer 32 - test_count [31:0] $end
$scope module dut $end
$var wire 2 . byte_select [1:0] $end
$var wire 3 / load_type [2:0] $end
$var wire 32 0 memory_data [31:0] $end
$var reg 32 1 extended_data [31:0] $end
$var reg 8 2 selected_byte [7:0] $end
$var reg 16 3 selected_halfword [15:0] $end
$upscope $end
$scope task display_test_summary $end
$var real 1 4 pass_rate $end
$upscope $end
$scope task run_corner_case_tests $end
$upscope $end
$scope task run_lb_tests $end
$upscope $end
$scope task run_lbu_tests $end
$upscope $end
$scope task run_lh_tests $end
$upscope $end
$scope task run_lhu_tests $end
$upscope $end
$scope task run_lw_tests $end
$upscope $end
$scope task test_data_extension $end
$var reg 2 5 byte_sel [1:0] $end
$var reg 32 6 expected_data [31:0] $end
$var reg 3 7 load_typ [2:0] $end
$var reg 32 8 mem_data [31:0] $end
$var reg 1600 9 test_name [1600:1] $end
$upscope $end
$upscope $end
$enddefinitions $end
$comment Show the parameter values. $end
$dumpall
b1 '
b10 &
b101 %
b1 $
b100 #
b0 "
$end
#0
$dumpvars
bx 9
bx 8
bx 7
bx 6
bx 5
r0 4
b0 3
b0 2
b0 1
b0 0
b0 /
b0 .
b0 -
b0 ,
b0 +
b0 *
b0 )
b0 (
b0 !
$end
#10000
b100001 !
b100001 1
b100001 2
b100001100100001 3
b10000111011001010100001100100001 *
b10000111011001010100001100100001 0
b1 -
b10011000100001000111010001000000100001001111001011101000110010100100000001100000010000000101101001000000111000001101111011100110110100101110100011010010111011001100101 9
b100001 6
b0 7
b0 5
b10000111011001010100001100100001 8
#11000
b1000011 !
b1000011 1
b1000011 2
b1 (
b1 .
b10 -
b10011000100001000111010001000000100001001111001011101000110010100100000001100010010000000101101001000000111000001101111011100110110100101110100011010010111011001100101 9
b1000011 6
b1 5
b1 ,
#12000
b1100101 !
b1100101 1
b1100101 2
b1000011101100101 3
b10 (
b10 .
b11 -
b10011000100001000111010001000000100001001111001011101000110010100100000001100100010000000101101001000000111000001101111011100110110100101110100011010010111011001100101 9
b1100101 6
b10 5
b10 ,
#13000
b11111111111111111111111110000111 !
b11111111111111111111111110000111 1
b10000111 2
b11 (
b11 .
b100 -
b10011000100001000111010001000000100001001111001011101000110010100100000001100110010000000101101001000000110111001100101011001110110000101110100011010010111011001100101 9
b11111111111111111111111110000111 6
b11 5
b11 ,
#14000
b11111111111111111111111110011000 !
b11111111111111111111111110011000 1
b10011000 2
b1011101010011000 3
b0 (
b0 .
b11111110110111001011101010011000 *
b11111110110111001011101010011000 0
b101 -
b1001100010000100011101000100000010011100110010101100111011000010111010001101001011101100110010100100000011000100111100101110100011001010010000001100001011101000010000001110000011011110111001101101001011101000110100101101111011011100010000000110000 9
b11111111111111111111111110011000 6
b0 5
b11111110110111001011101010011000 8
b100 ,
#15000
b11111111111111111111111110111010 !
b11111111111111111111111110111010 1
b10111010 2
b1 (
b1 .
b110 -
b1001100010000100011101000100000010011100110010101100111011000010111010001101001011101100110010100100000011000100111100101110100011001010010000001100001011101000010000001110000011011110111001101101001011101000110100101101111011011100010000000110001 9
b11111111111111111111111110111010 6
b1 5
b101 ,
#16000
b11111111111111111111111111011100 !
b11111111111111111111111111011100 1
b11011100 2
b1111111011011100 3
b10 (
b10 .
b111 -
b1001100010000100011101000100000010011100110010101100111011000010111010001101001011101100110010100100000011000100111100101110100011001010010000001100001011101000010000001110000011011110111001101101001011101000110100101101111011011100010000000110010 9
b11111111111111111111111111011100 6
b10 5
b110 ,
#17000
b11111111111111111111111111111110 !
b11111111111111111111111111111110 1
b11111110 2
b11 (
b11 .
b1000 -
b1001100010000100011101000100000010011100110010101100111011000010111010001101001011101100110010100100000011000100111100101110100011001010010000001100001011101000010000001110000011011110111001101101001011101000110100101101111011011100010000000110011 9
b11111111111111111111111111111110 6
b11 5
b111 ,
#18000
b0 !
b0 1
b0 2
b0 3
b0 (
b0 .
b0 *
b0 0
b1001 -
b1001100010000100011101000100000010110100110010101110010011011110010000001100010011110010111010001100101 9
b0 6
b0 5
b0 8
b1000 ,
#19000
b1111111 !
b1111111 1
b111111101111111 3
b1111111 2
b1111111011111110111111101111111 *
b1111111011111110111111101111111 0
b1010 -
b1001100010000100011101000100000010011010110000101111000011010010110110101110101011011010010000001110000011011110111001101101001011101000110100101110110011001010010000001100010011110010111010001100101 9
b1111111 6
b1111111011111110111111101111111 8
b1001 ,
#20000
b11111111111111111111111110000000 !
b11111111111111111111111110000000 1
b10000000 2
b1000000010000000 3
b10000000100000001000000010000000 *
b10000000100000001000000010000000 0
b1011 -
b1001100010000100011101000100000010011010110100101101110011010010110110101110101011011010010000001101110011001010110011101100001011101000110100101110110011001010010000001100010011110010111010001100101 9
b11111111111111111111111110000000 6
b10000000100000001000000010000000 8
b1010 ,
#21000
b11111111111111111111111111111111 !
b11111111111111111111111111111111 1
b1111111111111111 3
b11111111 2
b11111111111111111111111111111111 *
b11111111111111111111111111111111 0
b1100 -
b1001100010000100011101000100000010000010110110001101100001000000011000101110011 9
b11111111111111111111111111111111 6
b11111111111111111111111111111111 8
b1011 ,
#22000
b100001100100001 !
b100001100100001 1
b100001 2
b100001100100001 3
b1 )
b1 /
b10000111011001010100001100100001 *
b10000111011001010100001100100001 0
b1101 -
b100110001001000001110100010000001001100011011110111011101100101011100100010000001101000011000010110110001100110011101110110111101110010011001000010000000101101001000000111000001101111011100110110100101110100011010010111011001100101 9
b100001100100001 6
b1 7
b10000111011001010100001100100001 8
b1100 ,
#23000
b1000011 2
b1 (
b1 .
b1110 -
b1001100010010000011101000100000010011000110111101110111011001010111001000100000011010000110000101101100011001100111011101101111011100100110010000100000001011010010000001100010011110010111010001100101010111110111001101100101011011000110010101100011011101000101101100110000010111010010000001101001011001110110111001101111011100100110010101100100 9
b1 5
b1101 ,
#24000
b11111111111111111000011101100101 !
b11111111111111111000011101100101 1
b1100101 2
b1000011101100101 3
b10 (
b10 .
b1111 -
b100110001001000001110100010000001010101011100000111000001100101011100100010000001101000011000010110110001100110011101110110111101110010011001000010000000101101001000000110111001100101011001110110000101110100011010010111011001100101 9
b11111111111111111000011101100101 6
b10 5
b1110 ,
#25000
b10000111 2
b11 (
b11 .
b10000 -
b1001100010010000011101000100000010101010111000001110000011001010111001000100000011010000110000101101100011001100111011101101111011100100110010000100000001011010010000001100010011110010111010001100101010111110111001101100101011011000110010101100011011101000101101100110000010111010010000001101001011001110110111001101111011100100110010101100100 9
b11 5
b1111 ,
#26000
b11111111111111111001100001110110 !
b11111111111111111001100001110110 1
b1110110 2
b1001100001110110 3
b0 (
b0 .
b10010001101001001100001110110 *
b10010001101001001100001110110 0
b10001 -
b10011000100100000111010001000000100111001100101011001110110000101110100011010010111011001100101001000000110110001101111011101110110010101110010001000000110100001100001011011000110011001110111011011110111001001100100 9
b11111111111111111001100001110110 6
b0 5
b10010001101001001100001110110 8
b10000 ,
#27000
b1001000110100 !
b1001000110100 1
b1001000110100 3
b110100 2
b10 (
b10 .
b10010 -
b10011000100100000111010001000000101000001101111011100110110100101110100011010010111011001100101001000000111010101110000011100000110010101110010001000000110100001100001011011000110011001110111011011110111001001100100 9
b1001000110100 6
b10 5
b10001 ,
#28000
b0 !
b0 1
b0 2
b0 3
b0 (
b0 .
b0 *
b0 0
b10011 -
b100110001001000001110100010000001011010011001010111001001101111001000000110100001100001011011000110011001110111011011110111001001100100 9
b0 6
b0 5
b0 8
b10010 ,
#29000
b111111111111111 !
b111111111111111 1
b111111111111111 3
b11111111 2
b1111111111111110111111111111111 *
b1111111111111110111111111111111 0
b10100 -
b100110001001000001110100010000001001101011000010111100001101001011011010111010101101101001000000111000001101111011100110110100101110100011010010111011001100101001000000110100001100001011011000110011001110111011011110111001001100100 9
b111111111111111 6
b1111111111111110111111111111111 8
b10011 ,
#30000
b11111111111111111000000000000000 !
b11111111111111111000000000000000 1
b0 2
b1000000000000000 3
b10000000000000001000000000000000 *
b10000000000000001000000000000000 0
b10101 -
b100110001001000001110100010000001001101011010010110111001101001011011010111010101101101001000000110111001100101011001110110000101110100011010010111011001100101001000000110100001100001011011000110011001110111011011110111001001100100 9
b11111111111111111000000000000000 6
b10000000000000001000000000000000 8
b10100 ,
#31000
b11111111111111111111111111111111 !
b11111111111111111111111111111111 1
b1111111111111111 3
b11111111 2
b11111111111111111111111111111111 *
b11111111111111111111111111111111 0
b10110 -
b1001100010010000011101000100000010000010110110001101100001000000011000101110011 9
b11111111111111111111111111111111 6
b11111111111111111111111111111111 8
b10101 ,
#32000
b10000111011001010100001100100001 !
b10000111011001010100001100100001 1
b100001 2
b100001100100001 3
b10 )
b10 /
b10000111011001010100001100100001 *
b10000111011001010100001100100001 0
b10111 -
b10011000101011100111010001000000100011001110101011011000110110000100000011101110110111101110010011001000010000000101101001000000110001001111001011101000110010101011111011100110110010101101100011001010110001101110100001000000011000000110000 9
b10000111011001010100001100100001 6
b10 7
b10000111011001010100001100100001 8
b10110 ,
#33000
b1000011 2
b1 (
b1 .
b11000 -
b10011000101011100111010001000000100011001110101011011000110110000100000011101110110111101110010011001000010000000101101001000000110001001111001011101000110010101011111011100110110010101101100011001010110001101110100001000000011000000110001 9
b1 5
b10111 ,
#34000
b1100101 2
b1000011101100101 3
b10 (
b10 .
b11001 -
b10011000101011100111010001000000100011001110101011011000110110000100000011101110110111101110010011001000010000000101101001000000110001001111001011101000110010101011111011100110110010101101100011001010110001101110100001000000011000100110000 9
b10 5
b11000 ,
#35000
b10000111 2
b11 (
b11 .
b11010 -
b10011000101011100111010001000000100011001110101011011000110110000100000011101110110111101110010011001000010000000101101001000000110001001111001011101000110010101011111011100110110010101101100011001010110001101110100001000000011000100110001 9
b11 5
b11001 ,
#36000
b0 !
b0 1
b0 2
b0 3
b0 (
b0 .
b0 *
b0 0
b11011 -
b1001100010101110011101000100000010110100110010101110010011011110010000001110111011011110111001001100100 9
b0 6
b0 5
b0 8
b11010 ,
#37000
b11111111111111111111111111111111 !
b11111111111111111111111111111111 1
b1111111111111111 3
b11111111 2
b11111111111111111111111111111111 *
b11111111111111111111111111111111 0
b11100 -
b10011000101011100111010001000000100000101101100011011000010000000110001011100110010000001110111011011110111001001100100 9
b11111111111111111111111111111111 6
b11111111111111111111111111111111 8
b11011 ,
#38000
b1111111111111111111111111111111 !
b1111111111111111111111111111111 1
b1111111111111111111111111111111 *
b1111111111111111111111111111111 0
b11101 -
b1001100010101110011101000100000010011010110000101111000011010010110110101110101011011010010000001110000011011110111001101101001011101000110100101110110011001010010000001110111011011110111001001100100 9
b1111111111111111111111111111111 6
b1111111111111111111111111111111 8
b11100 ,
#39000
b10000000000000000000000000000000 !
b10000000000000000000000000000000 1
b0 3
b0 2
b10000000000000000000000000000000 *
b10000000000000000000000000000000 0
b11110 -
b1001100010101110011101000100000010011010110100101101110011010010110110101110101011011010010000001101110011001010110011101100001011101000110100101110110011001010010000001110111011011110111001001100100 9
b10000000000000000000000000000000 6
b10000000000000000000000000000000 8
b11101 ,
#40000
b10101010101010100101010101010101 !
b10101010101010100101010101010101 1
b1010101 2
b101010101010101 3
b10101010101010100101010101010101 *
b10101010101010100101010101010101 0
b11111 -
b100110001010111001110100010000001000001011011000111010001100101011100100110111001100001011101000110100101101110011001110010000001110000011000010111010001110100011001010111001001101110 9
b10101010101010100101010101010101 6
b10101010101010100101010101010101 8
b11110 ,
#41000
b100001 !
b100001 1
b100001100100001 3
b100001 2
b100 )
b100 /
b10000111011001010100001100100001 *
b10000111011001010100001100100001 0
b100000 -
b10011000100001001010101001110100010000001000010011110010111010001100101001000000011000000100000001011010010000001111010011001010111001001101111001000000110010101111000011101000110010101101110011001000110010101100100 9
b100001 6
b100 7
b10000111011001010100001100100001 8
b11111 ,
#42000
b1000011 !
b1000011 1
b1000011 2
b1 (
b1 .
b100001 -
b10011000100001001010101001110100010000001000010011110010111010001100101001000000011000100100000001011010010000001111010011001010111001001101111001000000110010101111000011101000110010101101110011001000110010101100100 9
b1000011 6
b1 5
b100000 ,
#43000
b1100101 !
b1100101 1
b1000011101100101 3
b1100101 2
b10 (
b10 .
b100010 -
b10011000100001001010101001110100010000001000010011110010111010001100101001000000011001000100000001011010010000001111010011001010111001001101111001000000110010101111000011101000110010101101110011001000110010101100100 9
b1100101 6
b10 5
b100001 ,
#44000
b10000111 !
b10000111 1
b10000111 2
b11 (
b11 .
b100011 -
b10011000100001001010101001110100010000001000010011110010111010001100101001000000011001100100000001011010010000001111010011001010111001001101111001000000110010101111000011101000110010101101110011001000110010101100100001000000010100001110111011000010111001100100000011011100110010101100111011000010111010001101001011101100110010100100000011010010110111000100000010011000100001000101001 9
b10000111 6
b11 5
b100010 ,
#45000
b10011000 !
b10011000 1
b1011101010011000 3
b10011000 2
b0 (
b0 .
b11111110110111001011101010011000 *
b11111110110111001011101010011000 0
b100100 -
b1001100010000100101010100111010001000000101001101101001011001110110111000100000011000100110100101110100001000000110001001111001011101000110010100100000001011010010000001111010011001010111001001101111001000000110010101111000011101000110010101101110011001000110010101100100 9
b10011000 6
b0 5
b11111110110111001011101010011000 8
b100011 ,
#46000
b10111010 !
b10111010 1
b10111010 2
b1 (
b1 .
b100101 -
b10111010 6
b1 5
b100100 ,
#47000
b11011100 !
b11011100 1
b1111111011011100 3
b11011100 2
b10 (
b10 .
b100110 -
b11011100 6
b10 5
b100101 ,
