src/immediate_generator.v
// Immediate Generator Module
// Generates 32-bit sign-extended immediates for different instruction types
// Based on Blog.md section 2.1 item 4)

// =============================================================================
// Local Constants (moved from riscv_constants.vh)
// =============================================================================
`define DATA_WIDTH          32          // 32-bit data bus

// Immediate Type Constants (3-bit encoding)
`define IMM_TYPE_I          3'b000          // I-type immediate (12-bit)
`define IMM_TYPE_S          3'b001          // S-type immediate (12-bit)
`define IMM_TYPE_B          3'b010          // B-type immediate (12-bit)
`define IMM_TYPE_U          3'b011          // U-type immediate (20-bit)
`define IMM_TYPE_J          3'b100          // J-type immediate (20-bit)

module immediate_generator (
    // Instruction bits (excluding opcode)
    input  wire [`DATA_WIDTH-1:0]  instruction,
    
    // Immediate type selection
    input  wire [2:0]               imm_type,
    
    // Generated 32-bit immediate
    output reg  [`DATA_WIDTH-1:0]  immediate
);

    always @(*) begin
        case (imm_type)
            `IMM_TYPE_I: begin
                // I-type: bits [31:20]
                // Used for: ADDI, SLTI, XORI, ORI, ANDI, SLLI, SRLI, SRAI, LB, LH, LW, LBU, LHU, JALR
                immediate = {{20{instruction[31]}}, instruction[31:20]};
            end
            
            `IMM_TYPE_S: begin
                // S-type: bits [31:25][11:7]  
                // Used for: SB, SH, SW
                immediate = {{20{instruction[31]}}, instruction[31:25], instruction[11:7]};
            end
            
            `IMM_TYPE_B: begin
                // B-type: bits [31][7][30:25][11:8]
                // Used for: BEQ, BNE, BLT, BGE, BLTU, BGEU
                immediate = {{19{instruction[31]}}, instruction[31], instruction[7], 
                           instruction[30:25], instruction[11:8], 1'b0};
            end
            
            `IMM_TYPE_U: begin
                // U-type: bits [31:12]
                // Used for: LUI, AUIPC
                immediate = {instruction[31:12], 12'b000000000000};
            end
            
            `IMM_TYPE_J: begin
                // J-type: bits [31][19:12][20][30:21]
                // Used for: JAL
                immediate = {{11{instruction[31]}}, instruction[31], instruction[19:12],
                           instruction[20], instruction[30:21], 1'b0};
            end
            
            default: begin
                immediate = 32'h00000000;
            end
        endcase
    end

endmodule

verify/testbench/immediate_generator_tb.v
// =============================================================================
// Immediate Generator Testbench - Comprehensive Verification  
// =============================================================================
// Description: Tests immediate generation for all RISC-V instruction types
// Author: Auto-generated testbench
// Date: September 23, 2025
// Features: - All immediate types testing (I, S, B, U, J)
//          - Sign extension verification
//          - Corner cases and boundary testing
// =============================================================================

`timescale 1ns / 1ps

module immediate_generator_tb;

    // =================================================================
    // Testbench Parameters
    // =================================================================
    parameter VERBOSE_MODE = 1;
    
    // =================================================================
    // Test Signal Declarations  
    // =================================================================
    reg [31:0]  instruction;
    reg [2:0]   imm_type;
    wire [31:0] immediate;
    
    // Test control
    integer test_count;
    integer pass_count; 
    integer fail_count;
    
    // =================================================================
    // Constants (matching immediate_generator.v)
    // =================================================================
    localparam IMM_TYPE_I = 3'b000;
    localparam IMM_TYPE_S = 3'b001;
    localparam IMM_TYPE_B = 3'b010;
    localparam IMM_TYPE_U = 3'b011;
    localparam IMM_TYPE_J = 3'b100;
    
    // =================================================================
    // Device Under Test (DUT)
    // =================================================================
    immediate_generator dut (
        .instruction(instruction),
        .imm_type(imm_type),
        .immediate(immediate)
    );
    
    // =================================================================
    // Test Execution Control
    // =================================================================
    initial begin
        // Initialize counters
        test_count = 0;
        pass_count = 0;
        fail_count = 0;
        
        // Initialize inputs
        instruction = 32'h0;
        imm_type = 3'h0;
        
        $display("========================================");
        $display("IMMEDIATE GENERATOR TESTBENCH STARTING");
        $display("========================================");
        $display("Time: %0t", $time);
        
        // Run test suites
        #10;
        run_i_type_tests();
        run_s_type_tests();
        run_b_type_tests();
        run_u_type_tests();
        run_j_type_tests();
        run_corner_case_tests();
        
        // Display results
        display_test_summary();
        
        #100;
        $finish;
    end
    
    // =================================================================
    // Test Suite: I-Type Immediates
    // =================================================================
    task run_i_type_tests();
        begin
            $display("\n[%0t] Running I-Type Immediate Tests...", $time);
            
            // Positive immediate
            test_immediate_generation(
                32'h00000FFF,  // instruction[31:20] = 0x0FF (positive)
                IMM_TYPE_I,
                32'h00000FFF,
                "I-Type: Positive immediate 0x0FF"
            );
            
            // Negative immediate (sign bit set)
            test_immediate_generation(
                32'h800007FF,  // instruction[31:20] = 0x800 (negative)
                IMM_TYPE_I,
                32'hFFFFF800,
                "I-Type: Negative immediate 0x800"
            );
            
            // Zero immediate
            test_immediate_generation(
                32'h00000000,
                IMM_TYPE_I,
                32'h00000000,
                "I-Type: Zero immediate"
            );
            
            // Maximum positive immediate (0x7FF)
            test_immediate_generation(
                32'h7FF00000,
                IMM_TYPE_I,
                32'h000007FF,
                "I-Type: Maximum positive (0x7FF)"
            );
            
            // Minimum negative immediate (0x800)
            test_immediate_generation(
                32'h80000000,
                IMM_TYPE_I,
                32'hFFFFF800,
                "I-Type: Minimum negative (0x800)"
            );
            
            $display("I-Type Tests Completed");
        end
    endtask
    
    // =================================================================
    // Test Suite: S-Type Immediates
    // =================================================================
    task run_s_type_tests();
        begin
            $display("\n[%0t] Running S-Type Immediate Tests...", $time);
            
            // Positive immediate: [31:25] = 0x00, [11:7] = 0x0F
            test_immediate_generation(
                32'h000000F0,  // [11:7] = 0x0F
                IMM_TYPE_S,
                32'h0000000F,
                "S-Type: Positive immediate"
            );
            
            // Negative immediate: [31:25] = 0x7F, [11:7] = 0x1F
            test_immediate_generation(
                32'hFE0000F0,  // [31:25] = 0x7F, [11:7] = 0x0F  
                IMM_TYPE_S,
                32'hFFFFFFEF,
                "S-Type: Negative immediate"
            );
            
            // Mixed bits: [31:25] = 0x2A, [11:7] = 0x15
            test_immediate_generation(
                32'h540000A0,  // [31:25] = 0x2A, [11:7] = 0x15
                IMM_TYPE_S,
                32'h00000555,
                "S-Type: Mixed pattern"
            );
            
            // Zero immediate
            test_immediate_generation(
                32'h00000000,
                IMM_TYPE_S,
                32'h00000000,
                "S-Type: Zero immediate"
            );
            
            $display("S-Type Tests Completed");
        end
    endtask
    
    // =================================================================
    // Test Suite: B-Type Immediates
    // =================================================================
    task run_b_type_tests();
        begin
            $display("\n[%0t] Running B-Type Immediate Tests...", $time);
            
            // Positive branch offset
            // [31]=0, [7]=0, [30:25]=0x10, [11:8]=0x8
            test_immediate_generation(
                32'h20000880,
                IMM_TYPE_B,
                32'h00000410,  // Expected: 0000 0100 0001 0000 (0x410)
                "B-Type: Positive branch offset"
            );
            
            // Negative branch offset
            // [31]=1, [7]=1, [30:25]=0x3F, [11:8]=0xF  
            test_immediate_generation(
                32'hFE000F80,
                IMM_TYPE_B,
                32'hFFFFFFFE,  // All 1s with LSB=0 
                "B-Type: Negative branch offset"
            );
            
            // Zero branch offset
            test_immediate_generation(
                32'h00000000,
                IMM_TYPE_B,
                32'h00000000,
                "B-Type: Zero branch offset"
            );
            
            // Maximum positive branch offset
            // [31]=0, [7]=0, [30:25]=0x3F, [11:8]=0xF
            test_immediate_generation(
                32'h7E000F00,
                IMM_TYPE_B,
                32'h00000FFE,
                "B-Type: Maximum positive offset"
            );
            
            $display("B-Type Tests Completed");
        end
    endtask
    
    // =================================================================
    // Test Suite: U-Type Immediates
    // =================================================================
    task run_u_type_tests();
        begin
            $display("\n[%0t] Running U-Type Immediate Tests...", $time);
            
            // Positive upper immediate
            test_immediate_generation(
                32'h12345678,  // [31:12] = 0x12345
                IMM_TYPE_U,
                32'h12345000,
                "U-Type: Positive upper immediate"
            );
            
            // Negative upper immediate
            test_immediate_generation(
                32'h87654321,  // [31:12] = 0x87654
                IMM_TYPE_U,
                32'h87654000,
                "U-Type: Negative upper immediate"
            );
            
            // Zero upper immediate
            test_immediate_generation(
                32'h00000FFF,  // [31:12] = 0x00000 (lower bits ignored)
                IMM_TYPE_U,
                32'h00000000,
                "U-Type: Zero upper immediate"
            );
            
            // Maximum upper immediate
            test_immediate_generation(
                32'hFFFFF000,  // [31:12] = 0xFFFFF
                IMM_TYPE_U,
                32'hFFFFF000,
                "U-Type: Maximum upper immediate"
            );
            
            $display("U-Type Tests Completed");
        end
    endtask
    
    // =================================================================
    // Test Suite: J-Type Immediates
    // =================================================================
    task run_j_type_tests();
        begin
            $display("\n[%0t] Running J-Type Immediate Tests...", $time);
            
            // Positive jump offset
            // [31]=0, [19:12]=0x12, [20]=0, [30:21]=0x345
            test_immediate_generation(
                32'h6AC12000,  // Constructed carefully
                IMM_TYPE_J,
                32'h00356240,  // Expected value
                "J-Type: Positive jump offset"
            );
            
            // Negative jump offset
            // [31]=1, [19:12]=0xFF, [20]=1, [30:21]=0x3FF
            test_immediate_generation(
                32'hFFEFF000,
                IMM_TYPE_J,
                32'hFFFFFFE0,  // Sign extended
                "J-Type: Negative jump offset"  
            );
            
            // Zero jump offset
            test_immediate_generation(
                32'h00000000,
                IMM_TYPE_J,
                32'h00000000,
                "J-Type: Zero jump offset"
            );
            
            // Large positive jump
            test_immediate_generation(
                32'h7FE00000,  // Positive with large offset
                IMM_TYPE_J,
                32'h0003FFE0,
                "J-Type: Large positive jump"
            );
            
            $display("J-Type Tests Completed");
        end
    endtask
    
    // =================================================================
    // Test Suite: Corner Cases
    // =================================================================
    task run_corner_case_tests();
        begin
            $display("\n[%0t] Running Corner Case Tests...", $time);
            
            // Invalid immediate type
            test_immediate_generation(
                32'hDEADBEEF,
                3'b111,  // Invalid type
                32'h00000000,
                "Corner: Invalid immediate type should return zero"
            );
            
            // All 1s instruction
            test_immediate_generation(
                32'hFFFFFFFF,
                IMM_TYPE_I,
                32'hFFFFFFFF,
                "Corner: All 1s instruction (I-type)"
            );
            
            test_immediate_generation(
                32'hFFFFFFFF,
                IMM_TYPE_U,
                32'hFFFFF000,
                "Corner: All 1s instruction (U-type)"
            );
            
            // Sign bit boundary cases
            test_immediate_generation(
                32'h7FFFFFFF,  // Positive with MSB=0
                IMM_TYPE_I,
                32'h000007FF,
                "Corner: I-type sign bit boundary (positive)"
            );
            
            test_immediate_generation(
                32'h80000000,  // Negative with MSB=1
                IMM_TYPE_I,
                32'hFFFFF800,
                "Corner: I-type sign bit boundary (negative)"
            );
            
            $display("Corner Case Tests Completed");
        end
    endtask
    
    // =================================================================
    // Helper Task: Test Immediate Generation
    // =================================================================
    task test_immediate_generation(
        input [31:0] test_instruction,
        input [2:0]  test_imm_type,
        input [31:0] expected_immediate,
        input [200*8:1] test_name
    );
        begin
            test_count = test_count + 1;
            
            // Apply inputs
            instruction = test_instruction;
            imm_type = test_imm_type;
            
            // Wait for propagation
            #1;
            
            // Check result
            if (immediate === expected_immediate) begin
                pass_count = pass_count + 1;
                if (VERBOSE_MODE) begin
                    $display("  ✅ PASS: %0s", test_name);
                    $display("      Instruction: 0x%08h, Type: %0d, Immediate: 0x%08h", 
                             test_instruction, test_imm_type, immediate);
                end
            end else begin
                fail_count = fail_count + 1;
                $display("  ❌ FAIL: %0s", test_name);
                $display("      Instruction: 0x%08h, Type: %0d", test_instruction, test_imm_type);
                $display("      Expected: 0x%08h, Got: 0x%08h", expected_immediate, immediate);
            end
        end
    endtask
    
    // =================================================================
    // Test Summary Display
    // =================================================================
    task display_test_summary();
        real pass_rate;
        begin
            $display("\n========================================");
            $display("IMMEDIATE GENERATOR TESTBENCH SUMMARY");
            $display("========================================");
            $display("Total Tests:  %0d", test_count);
            $display("Passed:       %0d", pass_count);
            $display("Failed:       %0d", fail_count);
            
            if (test_count > 0) begin
                pass_rate = ($itor(pass_count) / $itor(test_count)) * 100.0;
                $display("Pass Rate:    %0.1f%%", pass_rate);
                
                if (fail_count == 0) begin
                    $display("🎉 ALL TESTS PASSED! Immediate Generator implementation is correct.");
                end else begin
                    $display("⚠️  Some tests failed. Review Immediate Generator implementation.");
                end
            end
            
            $display("========================================");
            $display("Simulation completed at time: %0t", $time);
        end
    endtask
    
    // =================================================================
    // Waveform Dumping
    // =================================================================
    initial begin
        $dumpfile("immediate_generator_tb.vcd");
        $dumpvars(0, immediate_generator_tb);
    end

endmodule

verify/results/immediate_generator_tb.vcd
$date
	Thu Sep 25 18:32:21 2025
$end
$version
	Icarus Verilog
$end
$timescale
	1ps
$end
$scope module immediate_generator_tb $end
$var wire 32 ! immediate [31:0] $end
$var parameter 3 " IMM_TYPE_B $end
$var parameter 3 # IMM_TYPE_I $end
$var parameter 3 $ IMM_TYPE_J $end
$var parameter 3 % IMM_TYPE_S $end
$var parameter 3 & IMM_TYPE_U $end
$var parameter 32 ' VERBOSE_MODE $end
$var reg 3 ( imm_type [2:0] $end
$var reg 32 ) instruction [31:0] $end
$var integer 32 * fail_count [31:0] $end
$var integer 32 + pass_count [31:0] $end
$var integer 32 , test_count [31:0] $end
$scope module dut $end
$var wire 3 - imm_type [2:0] $end
$var wire 32 . instruction [31:0] $end
$var reg 32 / immediate [31:0] $end
$upscope $end
$scope task display_test_summary $end
$var real 1 0 pass_rate $end
$upscope $end
$scope task run_b_type_tests $end
$upscope $end
$scope task run_corner_case_tests $end
$upscope $end
$scope task run_i_type_tests $end
$upscope $end
$scope task run_j_type_tests $end
$upscope $end
$scope task run_s_type_tests $end
$upscope $end
$scope task run_u_type_tests $end
$upscope $end
$scope task test_immediate_generation $end
$var reg 32 1 expected_immediate [31:0] $end
$var reg 3 2 test_imm_type [2:0] $end
$var reg 32 3 test_instruction [31:0] $end
$var reg 1600 4 test_name [1600:1] $end
$upscope $end
$upscope $end
$enddefinitions $end
$comment Show the parameter values. $end
$dumpall
b1 '
b11 &
b1 %
b100 $
b0 #
b10 "
$end
#0
$dumpvars
bx 4
bx 3
bx 2
bx 1
r0 0
b0 /
b0 .
b0 -
b0 ,
b0 +
b0 *
b0 )
b0 (
b0 !
$end
#10000
b111111111111 )
b111111111111 .
b1 ,
b100100100101101010101000111100101110000011001010011101000100000010100000110111101110011011010010111010001101001011101100110010100100000011010010110110101101101011001010110010001101001011000010111010001100101001000000011000001111000001100000100011001000110 4
b111111111111 1
b0 2
b111111111111 3
#11000
b11111111111111111111100000000000 !
b11111111111111111111100000000000 /
b10000000000000000000011111111111 )
b10000000000000000000011111111111 .
b10 ,
b100100100101101010101000111100101110000011001010011101000100000010011100110010101100111011000010111010001101001011101100110010100100000011010010110110101101101011001010110010001101001011000010111010001100101001000000011000001111000001110000011000000110000 4
b11111111111111111111100000000000 1
b10000000000000000000011111111111 3
b1 *
#12000
b0 !
b0 /
b0 )
b0 .
b11 ,
b1001001001011010101010001111001011100000110010100111010001000000101101001100101011100100110111100100000011010010110110101101101011001010110010001101001011000010111010001100101 4
b0 1
b0 3
b1 +
#13000
b11111111111 !
b11111111111 /
b1111111111100000000000000000000 )
b1111111111100000000000000000000 .
b100 ,
b100100100101101010101000111100101110000011001010011101000100000010011010110000101111000011010010110110101110101011011010010000001110000011011110111001101101001011101000110100101110110011001010010000000101000001100000111100000110111010001100100011000101001 4
b11111111111 1
b1111111111100000000000000000000 3
b10 +
#14000
b11111111111111111111100000000000 !
b11111111111111111111100000000000 /
b10000000000000000000000000000000 )
b10000000000000000000000000000000 .
b101 ,
b100100100101101010101000111100101110000011001010011101000100000010011010110100101101110011010010110110101110101011011010010000001101110011001010110011101100001011101000110100101110110011001010010000000101000001100000111100000111000001100000011000000101001 4
b11111111111111111111100000000000 1
b10000000000000000000000000000000 3
b11 +
#15000
b1 !
b1 /
b1 (
b1 -
b11110000 )
b11110000 .
b110 ,
b101001100101101010101000111100101110000011001010011101000100000010100000110111101110011011010010111010001101001011101100110010100100000011010010110110101101101011001010110010001101001011000010111010001100101 4
b1111 1
b1 2
b11110000 3
b100 +
#16000
b11111111111111111111111111100001 !
b11111111111111111111111111100001 /
b11111110000000000000000011110000 )
b11111110000000000000000011110000 .
b111 ,
b101001100101101010101000111100101110000011001010011101000100000010011100110010101100111011000010111010001101001011101100110010100100000011010010110110101101101011001010110010001101001011000010111010001100101 4
b11111111111111111111111111101111 1
b11111110000000000000000011110000 3
b10 *
#17000
b10101000001 !
b10101000001 /
b1010100000000000000000010100000 )
b1010100000000000000000010100000 .
b1000 ,
b10100110010110101010100011110010111000001100101001110100010000001001101011010010111100001100101011001000010000001110000011000010111010001110100011001010111001001101110 4
b10101010101 1
b1010100000000000000000010100000 3
b11 *
#18000
b0 !
b0 /
b0 )
b0 .
b1001 ,
b1010011001011010101010001111001011100000110010100111010001000000101101001100101011100100110111100100000011010010110110101101101011001010110010001101001011000010111010001100101 4
b0 1
b0 3
b100 *
#19000
b101000010000 !
b101000010000 /
b10 (
b10 -
b100000000000000000100010000000 )
b100000000000000000100010000000 .
b1010 ,
b10000100010110101010100011110010111000001100101001110100010000001010000011011110111001101101001011101000110100101110110011001010010000001100010011100100110000101101110011000110110100000100000011011110110011001100110011100110110010101110100 4
b10000010000 1
b10 2
b100000000000000000100010000000 3
b101 +
#20000
b11111111111111111111111111111110 !
b11111111111111111111111111111110 /
b11111110000000000000111110000000 )
b11111110000000000000111110000000 .
b1011 ,
b10000100010110101010100011110010111000001100101001110100010000001001110011001010110011101100001011101000110100101110110011001010010000001100010011100100110000101101110011000110110100000100000011011110110011001100110011100110110010101110100 4
b11111111111111111111111111111110 1
b11111110000000000000111110000000 3
b101 *
#21000
b0 !
b0 /
b0 )
b0 .
b1100 ,
b100001000101101010101000111100101110000011001010011101000100000010110100110010101110010011011110010000001100010011100100110000101101110011000110110100000100000011011110110011001100110011100110110010101110100 4
b0 1
b0 3
b110 +
#22000
b11111111110 !
b11111111110 /
b1111110000000000000111100000000 )
b1111110000000000000111100000000 .
b1101 ,
b1000010001011010101010001111001011100000110010100111010001000000100110101100001011110000110100101101101011101010110110100100000011100000110111101110011011010010111010001101001011101100110010100100000011011110110011001100110011100110110010101110100 4
b111111111110 1
b1111110000000000000111100000000 3
b111 +
#23000
b10010001101000101000000000000 !
b10010001101000101000000000000 /
b11 (
b11 -
b10010001101000101011001111000 )
b10010001101000101011001111000 .
b1110 ,
b101010100101101010101000111100101110000011001010011101000100000010100000110111101110011011010010111010001101001011101100110010100100000011101010111000001110000011001010111001000100000011010010110110101101101011001010110010001101001011000010111010001100101 4
b10010001101000101000000000000 1
b11 2
b10010001101000101011001111000 3
b110 *
#24000
b10000111011001010100000000000000 !
b10000111011001010100000000000000 /
b10000111011001010100001100100001 )
b10000111011001010100001100100001 .
b1111 ,
b101010100101101010101000111100101110000011001010011101000100000010011100110010101100111011000010111010001101001011101100110010100100000011101010111000001110000011001010111001000100000011010010110110101101101011001010110010001101001011000010111010001100101 4
b10000111011001010100000000000000 1
b10000111011001010100001100100001 3
b1000 +
#25000
b0 !
b0 /
b111111111111 )
b111111111111 .
b10000 ,
b1010101001011010101010001111001011100000110010100111010001000000101101001100101011100100110111100100000011101010111000001110000011001010111001000100000011010010110110101101101011001010110010001101001011000010111010001100101 4
b0 1
b111111111111 3
b1001 +
#26000
b11111111111111111111000000000000 !
b11111111111111111111000000000000 /
b11111111111111111111000000000000 )
b11111111111111111111000000000000 .
b10001 ,
b1010101001011010101010001111001011100000110010100111010001000000100110101100001011110000110100101101101011101010110110100100000011101010111000001110000011001010111001000100000011010010110110101101101011001010110010001101001011000010111010001100101 4
b11111111111111111111000000000000 1
b11111111111111111111000000000000 3
b1010 +
#27000
b10010011010101100 !
b10010011010101100 /
b100 (
b100 -
b1101010110000010010000000000000 )
b1101010110000010010000000000000 .
b10010 ,
b1001010001011010101010001111001011100000110010100111010001000000101000001101111011100110110100101110100011010010111011001100101001000000110101001110101011011010111000000100000011011110110011001100110011100110110010101110100 4
b1101010110001001000000 1
b100 2
b1101010110000010010000000000000 3
b1011 +
#28000
b11111111111111111111011111111110 !
b11111111111111111111011111111110 /
b11111111111011111111000000000000 )
b11111111111011111111000000000000 .
b10011 ,
b1001010001011010101010001111001011100000110010100111010001000000100111001100101011001110110000101110100011010010111011001100101001000000110101001110101011011010111000000100000011011110110011001100110011100110110010101110100 4
b11111111111111111111111111100000 1
b11111111111011111111000000000000 3
b111 *
#29000
b0 !
b0 /
b0 )
b0 .
b10100 ,
b10010100010110101010100011110010111000001100101001110100010000001011010011001010111001001101111001000000110101001110101011011010111000000100000011011110110011001100110011100110110010101110100 4
b0 1
b0 3
b1000 *
#30000
b11111111110 !
b11111111110 /
b1111111111000000000000000000000 )
b1111111111000000000000000000000 .
b10101 ,
b10010100010110101010100011110010111000001100101001110100010000001001100011000010111001001100111011001010010000001110000011011110111001101101001011101000110100101110110011001010010000001101010011101010110110101110000 4
b111111111111100000 1
b1111111111000000000000000000000 3
b1100 +
#31000
b0 !
b0 /
b111 (
b111 -
b11011110101011011011111011101111 )
b11011110101011011011111011101111 .
b10110 ,
b1000011011011110111001001101110011001010111001000111010001000000100100101101110011101100110000101101100011010010110010000100000011010010110110101101101011001010110010001101001011000010111010001100101001000000111010001111001011100000110010100100000011100110110100001101111011101010110110001100100001000000111001001100101011101000111010101110010011011100010000001111010011001010111001001101111 4
b0 1
b111 2
b11011110101011011011111011101111 3
b1001 *
#32000
b11111111111111111111111111111111 !
b11111111111111111111111111111111 /
b0 (
b0 -
b11111111111111111111111111111111 )
b11111111111111111111111111111111 .
b10111 ,
b100001101101111011100100110111001100101011100100011101000100000010000010110110001101100001000000011000101110011001000000110100101101110011100110111010001110010011101010110001101110100011010010110111101101110001000000010100001001001001011010111010001111001011100000110010100101001 4
b11111111111111111111111111111111 1
b0 2
b11111111111111111111111111111111 3
b1101 +
#33000
b11111111111111111111000000000000 !
b11111111111111111111000000000000 /
b11 (
b11 -
b11000 ,
b100001101101111011100100110111001100101011100100011101000100000010000010110110001101100001000000011000101110011001000000110100101101110011100110111010001110010011101010110001101110100011010010110111101101110001000000010100001010101001011010111010001111001011100000110010100101001 4
b11111111111111111111000000000000 1
b11 2
b1110 +
#34000
b11111111111 !
b11111111111 /
b0 (
b0 -
b1111111111111111111111111111111 )
b1111111111111111111111111111111 .
b11001 ,
b1000011011011110111001001101110011001010111001000111010001000000100100100101101011101000111100101110000011001010010000001110011011010010110011101101110001000000110001001101001011101000010000001100010011011110111010101101110011001000110000101110010011110010010000000101000011100000110111101110011011010010111010001101001011101100110010100101001 4
b11111111111 1
b0 2
b1111111111111111111111111111111 3
b1111 +
#35000
b11111111111111111111100000000000 !
b11111111111111111111100000000000 /
b10000000000000000000000000000000 )
b10000000000000000000000000000000 .
b11010 ,
b1000011011011110111001001101110011001010111001000111010001000000100100100101101011101000111100101110000011001010010000001110011011010010110011101101110001000000110001001101001011101000010000001100010011011110111010101101110011001000110000101110010011110010010000000101000011011100110010101100111011000010111010001101001011101100110010100101001 4
b11111111111111111111100000000000 1
b10000000000000000000000000000000 3
b10000 +
#36000
r65.38461538461539 0
b10001 +
