src/instruction_memory.v
// =============================================================================
// Instruction Memory Module - ASIC Synthesis Optimized
// =============================================================================
// Description: Simple instruction memory with clean single-cycle access
//              100% synthesis compatible with no clock domain conflicts
// Author: Auto-generated for OpenLane flow
// Date: September 15, 2025
// =============================================================================

// =============================================================================
// Local Constants (moved from riscv_constants.vh)
// =============================================================================
// Data Width Constants (minimal needed for this module)
`define DATA_WIDTH          32          // 32-bit data bus

module instruction_memory #(
    // =================================================================
    // Parameters
    // =================================================================
    parameter DATA_WIDTH = 32,              // Data width
    parameter ADDR_WIDTH = 12,              // Address width (4KB default)
    parameter MEMORY_STYLE = "block",       // "block", "distributed", "ultra" - unused
    parameter INIT_FILE = "",               // Memory initialization file - unused
    parameter ENABLE_DEBUG = 1              // Enable debug features - unused
)(
    // =================================================================
    // Clock and Reset Interface  
    // =================================================================
    input  wire                     clk,
    input  wire                     rst_n,      // Synchronized reset
    
    // =================================================================
    // Memory Interface
    // =================================================================
    input  wire [DATA_WIDTH-1:0]    pc_f,          // Program counter
    output wire [DATA_WIDTH-1:0]    instruction_f, // Fetched instruction
    
    // =================================================================
    // Debug Interface (Optional)
    // =================================================================
    input  wire                     debug_enable,
    input  wire [ADDR_WIDTH-1:0]    debug_addr,
    output wire [DATA_WIDTH-1:0]    debug_data
);

    // =================================================================
    // Local Parameters and Memory Declaration
    // =================================================================
    localparam MEMORY_DEPTH = 1 << (ADDR_WIDTH-2);  // Word-addressable
    
    // Memory array - word addressable
    (* ram_style = MEMORY_STYLE *)
    reg [DATA_WIDTH-1:0] imem [0:MEMORY_DEPTH-1];
    
    // Address decoding
    wire [ADDR_WIDTH-3:0] word_addr;
    wire addr_valid;
    
    assign word_addr = pc_f[ADDR_WIDTH-1:2];  // Word address only
    assign addr_valid = (word_addr < MEMORY_DEPTH);
    
    // =================================================================
    // Memory Logic - Single Process Only
    // =================================================================
    // For ASIC: instructions are loaded externally, no internal initialization
    // This prevents multiple clock domain conflicts
    
    // Combinational read - no clock conflicts
    assign instruction_f = (addr_valid && rst_n) ? imem[word_addr] : 32'h00000013;
    
    // =================================================================
    // Debug Interface
    // =================================================================
    wire [ADDR_WIDTH-3:0] debug_word_addr = debug_addr[ADDR_WIDTH-1:2];
    assign debug_data = (debug_enable && debug_word_addr < MEMORY_DEPTH) ? 
                       imem[debug_word_addr] : {DATA_WIDTH{1'b0}};

endmodule

verify/testbench/instruction_memory_tb.v
// =============================================================================
// Instruction Memory Testbench - Comprehensive Verification
// =============================================================================
// Description: Tests instruction memory functionality with various access patterns
// Author: Auto-generated testbench
// Date: September 23, 2025
// Features: - Address range testing
//          - Memory initialization testing  
//          - Debug interface testing
//          - Reset behavior verification
// =============================================================================

`timescale 1ns / 1ps

module instruction_memory_tb;

    // =================================================================
    // Testbench Parameters
    // =================================================================
    parameter CLOCK_PERIOD = 10;
    parameter VERBOSE_MODE = 1;
    parameter DATA_WIDTH = 32;
    parameter ADDR_WIDTH = 12;
    parameter MEMORY_DEPTH = 1 << (ADDR_WIDTH-2); // 1K words
    
    // =================================================================
    // Test Signal Declarations
    // =================================================================
    reg                     clk;
    reg                     rst_n;
    reg [DATA_WIDTH-1:0]    pc_f;
    wire [DATA_WIDTH-1:0]   instruction_f;
    reg                     debug_enable;
    reg [ADDR_WIDTH-1:0]    debug_addr;
    wire [DATA_WIDTH-1:0]   debug_data;
    
    // Test control
    integer test_count;
    integer pass_count;
    integer fail_count;
    
    // =================================================================
    // Device Under Test (DUT)
    // =================================================================
    instruction_memory #(
        .DATA_WIDTH(DATA_WIDTH),
        .ADDR_WIDTH(ADDR_WIDTH),
        .MEMORY_STYLE("distributed"),
        .ENABLE_DEBUG(1)
    ) dut (
        .clk(clk),
        .rst_n(rst_n),
        .pc_f(pc_f),
        .instruction_f(instruction_f),
        .debug_enable(debug_enable),
        .debug_addr(debug_addr),
        .debug_data(debug_data)
    );
    
    // =================================================================
    // Clock Generation
    // =================================================================
    initial begin
        clk = 0;
        forever #(CLOCK_PERIOD/2) clk = ~clk;
    end
    
    // =================================================================
    // Test Execution Control
    // =================================================================
    initial begin
        // Initialize counters
        test_count = 0;
        pass_count = 0;
        fail_count = 0;
        
        // Initialize inputs
        rst_n = 1'b0;
        pc_f = 32'h0;
        debug_enable = 1'b0;
        debug_addr = 12'h0;
        
        $display("========================================");
        $display("INSTRUCTION MEMORY TESTBENCH STARTING");
        $display("========================================");
        $display("Time: %0t", $time);
        
        // Reset sequence
        #(CLOCK_PERIOD * 2);
        rst_n = 1'b1;
        #(CLOCK_PERIOD);
        
        // Initialize memory with test patterns
        initialize_test_memory();
        
        // Run test suites
        run_basic_read_tests();
        run_address_range_tests();
        run_debug_interface_tests();
        run_reset_behavior_tests();
        run_boundary_tests();
        
        // Display results
        display_test_summary();
        
        #100;
        $finish;
    end
    
    // =================================================================
    // Initialize Memory with Test Patterns
    // =================================================================
    task initialize_test_memory();
        integer i;
        begin
            $display("\n[%0t] Initializing test memory...", $time);
            
            // Load test instructions into memory
            for (i = 0; i < 64; i = i + 1) begin
                dut.imem[i] = 32'h00000000 + i; // Simple pattern: addr as instruction
            end
            
            // Special test patterns
            dut.imem[0] = 32'h00000013;   // ADDI x0, x0, 0 (NOP)
            dut.imem[1] = 32'h00100093;   // ADDI x1, x0, 1
            dut.imem[2] = 32'h00200113;   // ADDI x2, x0, 2  
            dut.imem[3] = 32'h00300193;   // ADDI x3, x0, 3
            dut.imem[4] = 32'hFE000EE3;   // BEQ loop instruction
            dut.imem[5] = 32'h00100073;   // EBREAK
            
            $display("  Memory initialized with test patterns");
        end
    endtask
    
    // =================================================================
    // Test Suite: Basic Read Operations
    // =================================================================
    task run_basic_read_tests();
        begin
            $display("\n[%0t] Running Basic Read Tests...", $time);
            
            // Test reading from address 0
            test_instruction_read(32'h00000000, 32'h00000013, "Read from address 0 (NOP)");
            
            // Test reading from address 4 (word 1)
            test_instruction_read(32'h00000004, 32'h00100093, "Read from address 4");
            
            // Test reading from address 8 (word 2)
            test_instruction_read(32'h00000008, 32'h00200113, "Read from address 8");
            
            // Test reading from address 12 (word 3)  
            test_instruction_read(32'h0000000C, 32'h00300193, "Read from address 12");
            
            // Test reading from address 16 (word 4)
            test_instruction_read(32'h00000010, 32'hFE000EE3, "Read from address 16");
            
            // Test reading from address 20 (word 5)
            test_instruction_read(32'h00000014, 32'h00100073, "Read from address 20");
            
            $display("Basic Read Tests Completed");
        end
    endtask
    
    // =================================================================
    // Test Suite: Address Range Testing
    // =================================================================
    task run_address_range_tests();
        integer i;
        reg [31:0] expected_data;
        begin
            $display("\n[%0t] Running Address Range Tests...", $time);
            
            // Test sequential addresses
            for (i = 24; i < 64; i = i + 4) begin
                expected_data = 32'h00000000 + (i/4);
                test_instruction_read(i, expected_data, "Sequential read at address");
            end
            
            // Test word alignment - addresses must be word-aligned
            test_instruction_read(32'h00000100, 32'h00000040, "Read from address 0x100");
            test_instruction_read(32'h00000200, 32'h00000080, "Read from address 0x200");
            
            // Test unaligned address behavior (should use word address)
            test_instruction_read(32'h00000001, 32'h00000013, "Unaligned address 1 (should read word 0)");
            test_instruction_read(32'h00000002, 32'h00000013, "Unaligned address 2 (should read word 0)");
            test_instruction_read(32'h00000003, 32'h00000013, "Unaligned address 3 (should read word 0)");
            
            $display("Address Range Tests Completed");
        end
    endtask
    
    // =================================================================
    // Test Suite: Debug Interface Testing
    // =================================================================
    task run_debug_interface_tests();
        begin
            $display("\n[%0t] Running Debug Interface Tests...", $time);
            
            // Enable debug interface
            debug_enable = 1'b1;
            
            // Test debug reads
            test_debug_read(12'h000, 32'h00000013, "Debug read address 0");
            test_debug_read(12'h004, 32'h00100093, "Debug read address 4");
            test_debug_read(12'h008, 32'h00200113, "Debug read address 8");
            test_debug_read(12'h00C, 32'h00300193, "Debug read address 12");
            
            // Test debug interface disabled
            debug_enable = 1'b0;
            debug_addr = 12'h004;
            #1;
            test_single_signal(debug_data, 32'h00000000, "Debug disabled should return zero");
            
            // Re-enable for cleanup
            debug_enable = 1'b1;
            
            $display("Debug Interface Tests Completed");
        end
    endtask
    
    // =================================================================
    // Test Suite: Reset Behavior Testing  
    // =================================================================
    task run_reset_behavior_tests();
        begin
            $display("\n[%0t] Running Reset Behavior Tests...", $time);
            
            // Test normal operation
            pc_f = 32'h00000000;
            #1;
            test_single_signal(instruction_f, 32'h00000013, "Normal operation before reset");
            
            // Apply reset
            rst_n = 1'b0;
            #1;
            test_single_signal(instruction_f, 32'h00000013, "During reset should return NOP");
            
            // Release reset
            rst_n = 1'b1;
            #1;
            test_single_signal(instruction_f, 32'h00000013, "After reset normal operation");
            
            $display("Reset Behavior Tests Completed");
        end
    endtask
    
    // =================================================================
    // Test Suite: Boundary Testing
    // =================================================================
    task run_boundary_tests();
        begin
            $display("\n[%0t] Running Boundary Tests...", $time);
            
            // Test valid address at boundary
            test_instruction_read(32'h00000FFC, 32'h000003FF, "Last valid address");
            
            // Test out-of-range addresses (should return NOP)
            test_instruction_read(32'h00001000, 32'h00000013, "Out of range address (should return NOP)");
            test_instruction_read(32'h0000FFFF, 32'h00000013, "Large out of range address");
            
            // Test maximum PC values
            test_instruction_read(32'hFFFFFFFC, 32'h00000013, "Maximum PC value");
            
            $display("Boundary Tests Completed");
        end
    endtask
    
    // =================================================================
    // Helper Task: Test Instruction Read
    // =================================================================
    task test_instruction_read(
        input [31:0] address,
        input [31:0] expected_instruction,
        input [200*8:1] test_name
    );
        begin
            test_count = test_count + 1;
            
            // Set PC and wait for propagation
            pc_f = address;
            #1;
            
            if (instruction_f === expected_instruction) begin
                pass_count = pass_count + 1;
                if (VERBOSE_MODE) begin
                    $display("  ✅ PASS: %0s", test_name);
                    $display("      Address: 0x%08h, Instruction: 0x%08h", address, instruction_f);
                end
            end else begin
                fail_count = fail_count + 1;
                $display("  ❌ FAIL: %0s", test_name);
                $display("      Address: 0x%08h", address);
                $display("      Expected: 0x%08h, Got: 0x%08h", expected_instruction, instruction_f);
            end
        end
    endtask
    
    // =================================================================
    // Helper Task: Test Debug Read
    // =================================================================
    task test_debug_read(
        input [11:0] address,
        input [31:0] expected_data,
        input [200*8:1] test_name
    );
        begin
            test_count = test_count + 1;
            
            debug_addr = address;
            #1;
            
            if (debug_data === expected_data) begin
                pass_count = pass_count + 1;
                if (VERBOSE_MODE) begin
                    $display("  ✅ PASS: %0s", test_name);
                    $display("      Debug Address: 0x%03h, Data: 0x%08h", address, debug_data);
                end
            end else begin
                fail_count = fail_count + 1;
                $display("  ❌ FAIL: %0s", test_name);
                $display("      Debug Address: 0x%03h", address);
                $display("      Expected: 0x%08h, Got: 0x%08h", expected_data, debug_data);
            end
        end
    endtask
    
    // =================================================================
    // Helper Task: Test Single Signal
    // =================================================================
    task test_single_signal(
        input [31:0] actual_value,
        input [31:0] expected_value,
        input [200*8:1] test_name
    );
        begin
            test_count = test_count + 1;
            
            if (actual_value === expected_value) begin
                pass_count = pass_count + 1;
                if (VERBOSE_MODE) begin
                    $display("  ✅ PASS: %0s", test_name);
                    $display("      Value: 0x%08h", actual_value);
                end
            end else begin
                fail_count = fail_count + 1;
                $display("  ❌ FAIL: %0s", test_name);
                $display("      Expected: 0x%08h, Got: 0x%08h", expected_value, actual_value);
            end
        end
    endtask
    
    // =================================================================
    // Test Summary Display
    // =================================================================
    task display_test_summary();
        real pass_rate;
        begin
            $display("\n========================================");
            $display("INSTRUCTION MEMORY TESTBENCH SUMMARY");
            $display("========================================");
            $display("Total Tests:  %0d", test_count);
            $display("Passed:       %0d", pass_count);
            $display("Failed:       %0d", fail_count);
            
            if (test_count > 0) begin
                pass_rate = ($itor(pass_count) / $itor(test_count)) * 100.0;
                $display("Pass Rate:    %0.1f%%", pass_rate);
                
                if (fail_count == 0) begin
                    $display("🎉 ALL TESTS PASSED! Instruction Memory implementation is correct.");
                end else begin
                    $display("⚠️  Some tests failed. Review Instruction Memory implementation.");
                end
            end
            
            $display("========================================");
            $display("Simulation completed at time: %0t", $time);
        end
    endtask
    
    // =================================================================
    // Waveform Dumping
    // =================================================================
    initial begin
        $dumpfile("instruction_memory_tb.vcd");
        $dumpvars(0, instruction_memory_tb);
    end

endmodule

verify/results/instruction_memory_tb.vcd
$date
	Thu Sep 25 18:34:33 2025
$end
$version
	Icarus Verilog
$end
$timescale
	1ps
$end
$scope module instruction_memory_tb $end
$var wire 32 ! instruction_f [31:0] $end
$var wire 32 " debug_data [31:0] $end
$var parameter 32 # ADDR_WIDTH $end
$var parameter 32 $ CLOCK_PERIOD $end
$var parameter 32 % DATA_WIDTH $end
$var parameter 42 & MEMORY_DEPTH $end
$var parameter 32 ' VERBOSE_MODE $end
$var reg 1 ( clk $end
$var reg 12 ) debug_addr [11:0] $end
$var reg 1 * debug_enable $end
$var reg 32 + pc_f [31:0] $end
$var reg 1 , rst_n $end
$var integer 32 - fail_count [31:0] $end
$var integer 32 . pass_count [31:0] $end
$var integer 32 / test_count [31:0] $end
$scope module dut $end
$var wire 1 ( clk $end
$var wire 12 0 debug_addr [11:0] $end
$var wire 1 * debug_enable $end
$var wire 32 1 pc_f [31:0] $end
$var wire 1 , rst_n $end
$var wire 10 2 word_addr [9:0] $end
$var wire 32 3 instruction_f [31:0] $end
$var wire 10 4 debug_word_addr [9:0] $end
$var wire 32 5 debug_data [31:0] $end
$var wire 1 6 addr_valid $end
$var parameter 32 7 ADDR_WIDTH $end
$var parameter 32 8 DATA_WIDTH $end
$var parameter 32 9 ENABLE_DEBUG $end
$var parameter 8 : INIT_FILE $end
$var parameter 42 ; MEMORY_DEPTH $end
$var parameter 88 < MEMORY_STYLE $end
$upscope $end
$scope task display_test_summary $end
$var real 1 = pass_rate $end
$upscope $end
$scope task initialize_test_memory $end
$var integer 32 > i [31:0] $end
$upscope $end
$scope task run_address_range_tests $end
$var reg 32 ? expected_data [31:0] $end
$var integer 32 @ i [31:0] $end
$upscope $end
$scope task run_basic_read_tests $end
$upscope $end
$scope task run_boundary_tests $end
$upscope $end
$scope task run_debug_interface_tests $end
$upscope $end
$scope task run_reset_behavior_tests $end
$upscope $end
$scope task test_debug_read $end
$var reg 12 A address [11:0] $end
$var reg 32 B expected_data [31:0] $end
$var reg 1600 C test_name [1600:1] $end
$upscope $end
$scope task test_instruction_read $end
$var reg 32 D address [31:0] $end
$var reg 32 E expected_instruction [31:0] $end
$var reg 1600 F test_name [1600:1] $end
$upscope $end
$scope task test_single_signal $end
$var reg 32 G actual_value [31:0] $end
$var reg 32 H expected_value [31:0] $end
$var reg 1600 I test_name [1600:1] $end
$upscope $end
$upscope $end
$enddefinitions $end
$comment Show the parameter values. $end
$dumpall
b110010001101001011100110111010001110010011010010110001001110101011101000110010101100100 <
b10000000000 ;
b0 :
b1 9
b100000 8
b1100 7
b1 '
b10000000000 &
b100000 %
b1010 $
b1100 #
$end
#0
$dumpvars
bx I
bx H
bx G
bx F
bx E
bx D
bx C
bx B
bx A
bx @
bx ?
bx >
r0 =
16
b0 5
b0 4
b10011 3
b0 2
b0 1
b0 0
b0 /
b0 .
b0 -
0,
b0 +
0*
b0 )
0(
b0 "
b10011 !
$end
#5000
1(
#10000
0(
#15000
1(
#20000
bx !
bx 3
0(
1,
#25000
1(
#30000
b10011 !
b10011 3
0(
b1 /
b1010010011001010110000101100100001000000110011001110010011011110110110100100000011000010110010001100100011100100110010101110011011100110010000000110000001000000010100001001110010011110101000000101001 F
b10011 E
b0 D
b1000000 >
#31000
b100000000000010010011 !
b100000000000010010011 3
b1 2
b100 +
b100 1
b10 /
b1010010011001010110000101100100001000000110011001110010011011110110110100100000011000010110010001100100011100100110010101110011011100110010000000110100 F
b100000000000010010011 E
b100 D
b1 .
#32000
b1000000000000100010011 !
b1000000000000100010011 3
b10 2
b1000 +
b1000 1
b11 /
b1010010011001010110000101100100001000000110011001110010011011110110110100100000011000010110010001100100011100100110010101110011011100110010000000111000 F
b1000000000000100010011 E
b1000 D
b10 .
#33000
b1100000000000110010011 !
b1100000000000110010011 3
b11 2
b1100 +
b1100 1
b100 /
b101001001100101011000010110010000100000011001100111001001101111011011010010000001100001011001000110010001110010011001010111001101110011001000000011000100110010 F
b1100000000000110010011 E
b1100 D
b11 .
#34000
b11111110000000000000111011100011 !
b11111110000000000000111011100011 3
b100 2
b10000 +
b10000 1
b101 /
b101001001100101011000010110010000100000011001100111001001101111011011010010000001100001011001000110010001110010011001010111001101110011001000000011000100110110 F
b11111110000000000000111011100011 E
b10000 D
b100 .
#35000
b100000000000001110011 !
b100000000000001110011 3
b101 2
b10100 +
b10100 1
b110 /
b101001001100101011000010110010000100000011001100111001001101111011011010010000001100001011001000110010001110010011001010111001101110011001000000011001000110000 F
b100000000000001110011 E
b10100 D
b101 .
1(
#36000
b110 !
b110 3
b110 2
b11000 +
b11000 1
b111 /
b101001101100101011100010111010101100101011011100111010001101001011000010110110000100000011100100110010101100001011001000010000001100001011101000010000001100001011001000110010001110010011001010111001101110011 F
b110 E
b11000 D
b110 ?
b11000 @
b110 .
#37000
b111 !
b111 3
b111 2
b11100 +
b11100 1
b1000 /
b111 E
b11100 D
b111 ?
b11100 @
b111 .
#38000
b1000 !
b1000 3
b1000 2
b100000 +
b100000 1
b1001 /
b1000 E
b100000 D
b1000 ?
b100000 @
b1000 .
#39000
b1001 !
b1001 3
b1001 2
b100100 +
b100100 1
b1010 /
b1001 E
b100100 D
b1001 ?
b100100 @
b1001 .
#40000
b1010 !
b1010 3
b1010 2
b101000 +
b101000 1
b1011 /
b1010 E
b101000 D
b1010 ?
b101000 @
b1010 .
0(
#41000
b1011 !
b1011 3
b1011 2
b101100 +
b101100 1
b1100 /
b1011 E
b101100 D
b1011 ?
b101100 @
b1011 .
#42000
b1100 !
b1100 3
b1100 2
b110000 +
b110000 1
b1101 /
b1100 E
b110000 D
b1100 ?
b110000 @
b1100 .
#43000
b1101 !
b1101 3
b1101 2
b110100 +
b110100 1
b1110 /
b1101 E
b110100 D
b1101 ?
b110100 @
b1101 .
#44000
b1110 !
b1110 3
b1110 2
b111000 +
b111000 1
b1111 /
b1110 E
b111000 D
b1110 ?
b111000 @
b1110 .
#45000
b1111 !
b1111 3
b1111 2
b111100 +
b111100 1
b10000 /
b1111 E
b111100 D
b1111 ?
b111100 @
b1111 .
1(
#46000
bx !
bx 3
b1000000 2
b100000000 +
b100000000 1
b10001 /
b101001001100101011000010110010000100000011001100111001001101111011011010010000001100001011001000110010001110010011001010111001101110011001000000011000001111000001100010011000000110000 F
b1000000 E
b100000000 D
b1000000 @
b10000 .
#47000
b10000000 2
b1000000000 +
b1000000000 1
b10010 /
b101001001100101011000010110010000100000011001100111001001101111011011010010000001100001011001000110010001110010011001010111001101110011001000000011000001111000001100100011000000110000 F
b10000000 E
b1000000000 D
b1 -
#48000
b10011 !
b10011 3
b0 2
b1 +
b1 1
b10011 /
b1010101011011100110000101101100011010010110011101101110011001010110010000100000011000010110010001100100011100100110010101110011011100110010000000110001001000000010100001110011011010000110111101110101011011000110010000100000011100100110010101100001011001000010000001110111011011110111001001100100001000000011000000101001 F
b10011 E
b1 D
b10 -
#49000
b10 +
b10 1
b10100 /
b1010101011011100110000101101100011010010110011101101110011001010110010000100000011000010110010001100100011100100110010101110011011100110010000000110010001000000010100001110011011010000110111101110101011011000110010000100000011100100110010101100001011001000010000001110111011011110111001001100100001000000011000000101001 F
b10 D
b10001 .
#50000
b11 +
b11 1
b10101 /
b1010101011011100110000101101100011010010110011101101110011001010110010000100000011000010110010001100100011100100110010101110011011100110010000000110011001000000010100001110011011010000110111101110101011011000110010000100000011100100110010101100001011001000010000001110111011011110111001001100100001000000011000000101001 F
b11 D
b10010 .
0(
#51000
b10011 "
b10011 5
b10110 /
b100010001100101011000100111010101100111001000000111001001100101011000010110010000100000011000010110010001100100011100100110010101110011011100110010000000110000 C
b10011 B
b0 A
1*
b10011 .
#52000
b100000000000010010011 "
b100000000000010010011 5
b1 4
b100 )
b100 0
b10111 /
b100010001100101011000100111010101100111001000000111001001100101011000010110010000100000011000010110010001100100011100100110010101110011011100110010000000110100 C
b100000000000010010011 B
b100 A
b10100 .
#53000
b1000000000000100010011 "
b1000000000000100010011 5
b10 4
b1000 )
b1000 0
b11000 /
b100010001100101011000100111010101100111001000000111001001100101011000010110010000100000011000010110010001100100011100100110010101110011011100110010000000111000 C
b1000000000000100010011 B
b1000 A
b10101 .
#54000
b1100000000000110010011 "
b1100000000000110010011 5
b11 4
b1100 )
b1100 0
b11001 /
b10001000110010101100010011101010110011100100000011100100110010101100001011001000010000001100001011001000110010001110010011001010111001101110011001000000011000100110010 C
b1100000000000110010011 B
b1100 A
b10110 .
#55000
b0 "
b0 5
b1 4
b100 )
b100 0
0*
b10111 .
1(
#56000
b100000000000010010011 "
b100000000000010010011 5
b0 +
b0 1
1*
b11000 .
b11010 /
b10001000110010101100010011101010110011100100000011001000110100101110011011000010110001001101100011001010110010000100000011100110110100001101111011101010110110001100100001000000111001001100101011101000111010101110010011011100010000001111010011001010111001001101111 I
b0 H
b0 G
#57000
0,
b11001 .
b11011 /
b100111001101111011100100110110101100001011011000010000001101111011100000110010101110010011000010111010001101001011011110110111000100000011000100110010101100110011011110111001001100101001000000111001001100101011100110110010101110100 I
b10011 H
b10011 G
#58000
1,
b11010 .
b11100 /
b10001000111010101110010011010010110111001100111001000000111001001100101011100110110010101110100001000000111001101101000011011110111010101101100011001000010000001110010011001010111010001110101011100100110111000100000010011100100111101010000 I
#59000
bx !
bx 3
b1111111111 2
b111111111100 +
b111111111100 1
b10011000110000101110011011101000010000001110110011000010110110001101001011001000010000001100001011001000110010001110010011001010111001101110011 F
b1111111111 E
b111111111100 D
b11011 .
b11110 /
b1000001011001100111010001100101011100100010000001110010011001010111001101100101011101000010000001101110011011110111001001101101011000010110110000100000011011110111000001100101011100100110000101110100011010010110111101101110 I
#60000
b10011 !
b10011 3
b0 2
b1000000000000 +
b1000000000000 1
b11111 /
b1001111011101010111010000100000011011110110011000100000011100100110000101101110011001110110010100100000011000010110010001100100011100100110010101110011011100110010000000101000011100110110100001101111011101010110110001100100001000000111001001100101011101000111010101110010011011100010000001001110010011110101000000101001 F
b10011 E
b1000000000000 D
b11 -
0(
#61000
bx !
bx 3
b1111111111 2
b1111111111111111 +
b1111111111111111 1
b100000 /
b100110001100001011100100110011101100101001000000110111101110101011101000010000001101111011001100010000001110010011000010110111001100111011001010010000001100001011001000110010001110010011001010111001101110011 F
b1111111111111111 D
b11100 .
#62000
b11111111111111111111111111111100 +
b11111111111111111111111111111100 1
b100001 /
b1001101011000010111100001101001011011010111010101101101001000000101000001000011001000000111011001100001011011000111010101100101 F
b11111111111111111111111111111100 D
b100 -
#63000
r84.84848484848484 =
b101 -
