src/npc_generator.v
// Next PC Generator Module
// Implements priority selection for next PC: JalrE/BranchE > JalD > PC+4
// Based on Blog.md section 2.1 item 1)

// =============================================================================
// Local Constants (moved from riscv_constants.vh)
// =============================================================================
`define DATA_WIDTH          32          // 32-bit data bus
`define RESET_PC            32'h00000000    // Reset PC address

module npc_generator (
    input  wire                     clk,    // unused but kept for interface consistency
    input  wire                     rst_n,
    
    // Current PC
    input  wire [`DATA_WIDTH-1:0]  pc_f,
    
    // Control signals from different stages
    input  wire                     branch_e,       // Branch decision from EX stage
    input  wire                     jalr_e,         // JALR from EX stage  
    input  wire                     jal_d,          // JAL from ID stage
    
    // Target addresses
    input  wire [`DATA_WIDTH-1:0]  branch_target,  // Branch target (BrT)
    input  wire [`DATA_WIDTH-1:0]  jalr_target,    // JALR target (JalrT) 
    input  wire [`DATA_WIDTH-1:0]  jal_target,     // JAL target (JalT)
    
    // Stall signal from hazard unit
    input  wire                     stall_f,
    
    // Output next PC
    output reg  [`DATA_WIDTH-1:0]  pc_next
);

    always @(*) begin
        if (!rst_n) begin
            pc_next = `RESET_PC;
        end else if (stall_f) begin
            // Hold current PC when stalled
            pc_next = pc_f;
        end else begin
            // Priority selection based on Blog.md analysis:
            // EX stage signals (JalrE, BranchE) have higher priority than ID stage (JalD)
            if (jalr_e) begin
                pc_next = jalr_target;
            end else if (branch_e) begin
                pc_next = branch_target;
            end else if (jal_d) begin
                pc_next = jal_target;
            end else begin
                // Default: sequential execution (PC + 4)
                pc_next = pc_f + 32'd4;
            end
        end
    end

endmodule

verify/testbench/npc_generator_tb.v
// =============================================================================
// NPC Generator Testbench - Comprehensive Verification
// =============================================================================
// Description: Tests Next PC generation logic with priority selection
// Author: Auto-generated testbench
// Date: September 23, 2025
// Features: - Priority testing (JALR > Branch > JAL > PC+4)
//          - Stall behavior testing
//          - Reset behavior verification
//          - Edge cases and corner testing
// =============================================================================

`timescale 1ns / 1ps

module npc_generator_tb;

    // =================================================================
    // Testbench Parameters
    // =================================================================
    parameter CLOCK_PERIOD = 10;
    parameter VERBOSE_MODE = 1;
    parameter DATA_WIDTH = 32;
    
    // =================================================================
    // Test Signal Declarations
    // =================================================================
    reg                     clk;
    reg                     rst_n;
    reg [DATA_WIDTH-1:0]    pc_f;
    reg                     branch_e;
    reg                     jalr_e;
    reg                     jal_d;
    reg [DATA_WIDTH-1:0]    branch_target;
    reg [DATA_WIDTH-1:0]    jalr_target;
    reg [DATA_WIDTH-1:0]    jal_target;
    reg                     stall_f;
    wire [DATA_WIDTH-1:0]   pc_next;
    
    // Test control
    integer test_count;
    integer pass_count;
    integer fail_count;
    
    // =================================================================
    // Device Under Test (DUT)
    // =================================================================
    npc_generator dut (
        .clk(clk),
        .rst_n(rst_n),
        .pc_f(pc_f),
        .branch_e(branch_e),
        .jalr_e(jalr_e),
        .jal_d(jal_d),
        .branch_target(branch_target),
        .jalr_target(jalr_target),
        .jal_target(jal_target),
        .stall_f(stall_f),
        .pc_next(pc_next)
    );
    
    // =================================================================
    // Clock Generation
    // =================================================================
    initial begin
        clk = 0;
        forever #(CLOCK_PERIOD/2) clk = ~clk;
    end
    
    // =================================================================
    // Test Execution Control
    // =================================================================
    initial begin
        // Initialize counters
        test_count = 0;
        pass_count = 0;
        fail_count = 0;
        
        // Initialize inputs
        initialize_inputs();
        
        $display("========================================");
        $display("NPC GENERATOR TESTBENCH STARTING");
        $display("========================================");
        $display("Time: %0t", $time);
        
        // Reset sequence
        rst_n = 1'b0;
        #(CLOCK_PERIOD * 2);
        rst_n = 1'b1;
        #(CLOCK_PERIOD);
        
        // Run test suites
        run_reset_tests();
        run_sequential_pc_tests();
        run_jal_tests();
        run_branch_tests();
        run_jalr_tests();
        run_priority_tests();
        run_stall_tests();
        run_corner_case_tests();
        
        // Display results
        display_test_summary();
        
        #100;
        $finish;
    end
    
    // =================================================================
    // Initialize Inputs Task
    // =================================================================
    task initialize_inputs();
        begin
            clk = 1'b0;
            rst_n = 1'b0;
            pc_f = 32'h00000000;
            branch_e = 1'b0;
            jalr_e = 1'b0;
            jal_d = 1'b0;
            branch_target = 32'h00000000;
            jalr_target = 32'h00000000;
            jal_target = 32'h00000000;
            stall_f = 1'b0;
        end
    endtask
    
    // =================================================================
    // Test Suite: Reset Behavior
    // =================================================================
    task run_reset_tests();
        begin
            $display("\n[%0t] Running Reset Tests...", $time);
            
            // During reset, PC should go to reset address
            pc_f = 32'h12345678;  // Non-zero current PC
            rst_n = 1'b0;
            #1;
            test_pc_generation(32'h00000000, "Reset state - PC should be 0x00000000");
            
            // After reset release
            rst_n = 1'b1;
            #1;
            test_pc_generation(32'h1234567C, "After reset - sequential PC+4");
            
            $display("Reset Tests Completed");
        end
    endtask
    
    // =================================================================
    // Test Suite: Sequential PC Tests
    // =================================================================
    task run_sequential_pc_tests();
        begin
            $display("\n[%0t] Running Sequential PC Tests...", $time);
            
            initialize_inputs();
            rst_n = 1'b1;
            
            // Test basic PC+4 increment
            pc_f = 32'h00000000;
            #1;
            test_pc_generation(32'h00000004, "Sequential: PC=0 -> PC+4=4");
            
            pc_f = 32'h00000100;
            #1;
            test_pc_generation(32'h00000104, "Sequential: PC=0x100 -> PC+4=0x104");
            
            pc_f = 32'h12345678;
            #1;
            test_pc_generation(32'h1234567C, "Sequential: PC=0x12345678 -> PC+4");
            
            // Test various address alignments
            pc_f = 32'h00001000;
            #1;
            test_pc_generation(32'h00001004, "Sequential: Aligned address");
            
            pc_f = 32'hFFFFFFF8;
            #1;
            test_pc_generation(32'hFFFFFFFC, "Sequential: Near maximum address");
            
            $display("Sequential PC Tests Completed");
        end
    endtask
    
    // =================================================================
    // Test Suite: JAL Instruction Tests
    // =================================================================
    task run_jal_tests();
        begin
            $display("\n[%0t] Running JAL Tests...", $time);
            
            initialize_inputs();
            rst_n = 1'b1;
            
            // Test JAL with positive offset
            pc_f = 32'h00000100;
            jal_d = 1'b1;
            jal_target = 32'h00001000;
            #1;
            test_pc_generation(32'h00001000, "JAL: Jump to positive target");
            
            // Test JAL with negative offset (backwards jump)
            pc_f = 32'h00001000;
            jal_target = 32'h00000200;
            #1;
            test_pc_generation(32'h00000200, "JAL: Jump to backwards target");
            
            // Test JAL disabled
            jal_d = 1'b0;
            #1;
            test_pc_generation(32'h00001004, "JAL disabled: Should be sequential");
            
            // Test JAL to address 0
            jal_d = 1'b1;
            jal_target = 32'h00000000;
            #1;
            test_pc_generation(32'h00000000, "JAL: Jump to address 0");
            
            $display("JAL Tests Completed");
        end
    endtask
    
    // =================================================================
    // Test Suite: Branch Instruction Tests
    // =================================================================
    task run_branch_tests();
        begin
            $display("\n[%0t] Running Branch Tests...", $time);
            
            initialize_inputs();
            rst_n = 1'b1;
            
            // Test branch taken
            pc_f = 32'h00000200;
            branch_e = 1'b1;
            branch_target = 32'h00000400;
            #1;
            test_pc_generation(32'h00000400, "Branch taken: Jump to target");
            
            // Test branch not taken
            branch_e = 1'b0;
            #1;
            test_pc_generation(32'h00000204, "Branch not taken: Sequential PC+4");
            
            // Test branch to backwards address
            branch_e = 1'b1;
            branch_target = 32'h00000100;
            #1;
            test_pc_generation(32'h00000100, "Branch taken: Backwards target");
            
            // Test branch priority over JAL
            jal_d = 1'b1;
            jal_target = 32'h00002000;
            branch_e = 1'b1;
            branch_target = 32'h00000800;
            #1;
            test_pc_generation(32'h00000800, "Branch priority: Branch beats JAL");
            
            $display("Branch Tests Completed");
        end
    endtask
    
    // =================================================================
    // Test Suite: JALR Instruction Tests
    // =================================================================
    task run_jalr_tests();
        begin
            $display("\n[%0t] Running JALR Tests...", $time);
            
            initialize_inputs();
            rst_n = 1'b1;
            
            // Test JALR
            pc_f = 32'h00000300;
            jalr_e = 1'b1;
            jalr_target = 32'h00005000;
            #1;
            test_pc_generation(32'h00005000, "JALR: Jump to register target");
            
            // Test JALR to address 0
            jalr_target = 32'h00000000;
            #1;
            test_pc_generation(32'h00000000, "JALR: Jump to address 0");
            
            // Test JALR disabled
            jalr_e = 1'b0;
            #1;
            test_pc_generation(32'h00000304, "JALR disabled: Sequential PC+4");
            
            $display("JALR Tests Completed");
        end
    endtask
    
    // =================================================================
    // Test Suite: Priority Testing
    // =================================================================
    task run_priority_tests();
        begin
            $display("\n[%0t] Running Priority Tests...", $time);
            
            initialize_inputs();
            rst_n = 1'b1;
            pc_f = 32'h00000400;
            
            // Test JALR highest priority
            jalr_e = 1'b1;
            jalr_target = 32'h00001000;
            branch_e = 1'b1;
            branch_target = 32'h00002000;
            jal_d = 1'b1;
            jal_target = 32'h00003000;
            #1;
            test_pc_generation(32'h00001000, "Priority: JALR beats Branch and JAL");
            
            // Test Branch over JAL
            jalr_e = 1'b0;
            branch_e = 1'b1;
            jal_d = 1'b1;
            #1;
            test_pc_generation(32'h00002000, "Priority: Branch beats JAL");
            
            // Test JAL over sequential
            branch_e = 1'b0;
            jal_d = 1'b1;
            #1;
            test_pc_generation(32'h00003000, "Priority: JAL beats sequential");
            
            // Test all disabled - sequential
            jal_d = 1'b0;
            #1;
            test_pc_generation(32'h00000404, "Priority: All disabled, sequential PC+4");
            
            $display("Priority Tests Completed");
        end
    endtask
    
    // =================================================================
    // Test Suite: Stall Behavior Tests
    // =================================================================
    task run_stall_tests();
        begin
            $display("\n[%0t] Running Stall Tests...", $time);
            
            initialize_inputs();
            rst_n = 1'b1;
            
            // Test stall with sequential PC
            pc_f = 32'h00000500;
            stall_f = 1'b1;
            #1;
            test_pc_generation(32'h00000500, "Stall: PC should not change");
            
            // Test stall with JAL
            jal_d = 1'b1;
            jal_target = 32'h00001000;
            stall_f = 1'b1;
            #1;
            test_pc_generation(32'h00000500, "Stall with JAL: PC should not change");
            
            // Test stall with Branch
            jal_d = 1'b0;
            branch_e = 1'b1;
            branch_target = 32'h00002000;
            stall_f = 1'b1;
            #1;
            test_pc_generation(32'h00000500, "Stall with Branch: PC should not change");
            
            // Test stall with JALR
            branch_e = 1'b0;
            jalr_e = 1'b1;
            jalr_target = 32'h00003000;
            stall_f = 1'b1;
            #1;
            test_pc_generation(32'h00000500, "Stall with JALR: PC should not change");
            
            // Test stall release
            stall_f = 1'b0;
            #1;
            test_pc_generation(32'h00003000, "Stall release: JALR should work");
            
            $display("Stall Tests Completed");
        end
    endtask
    
    // =================================================================
    // Test Suite: Corner Cases
    // =================================================================
    task run_corner_case_tests();
        begin
            $display("\n[%0t] Running Corner Case Tests...", $time);
            
            initialize_inputs();
            rst_n = 1'b1;
            
            // Test maximum address
            pc_f = 32'hFFFFFFFC;
            #1;
            test_pc_generation(32'h00000000, "Corner: Maximum PC wraps to 0");
            
            // Test all targets same
            pc_f = 32'h00000600;
            jalr_e = 1'b1;
            branch_e = 1'b1;
            jal_d = 1'b1;
            jalr_target = 32'h00001000;
            branch_target = 32'h00001000;
            jal_target = 32'h00001000;
            #1;
            test_pc_generation(32'h00001000, "Corner: All targets same, JALR priority");
            
            // Test target equals current PC
            pc_f = 32'h00000700;
            jalr_e = 1'b0;
            branch_e = 1'b1;
            jal_d = 1'b0;
            branch_target = 32'h00000700;
            #1;
            test_pc_generation(32'h00000700, "Corner: Branch to same address");
            
            // Test misaligned PC
            pc_f = 32'h00000701; // Unaligned
            branch_e = 1'b0;
            #1;
            test_pc_generation(32'h00000705, "Corner: Unaligned PC + 4");
            
            $display("Corner Case Tests Completed");
        end
    endtask
    
    // =================================================================
    // Helper Task: Test PC Generation
    // =================================================================
    task test_pc_generation(
        input [31:0] expected_pc,
        input [200*8:1] test_name
    );
        begin
            test_count = test_count + 1;
            
            if (pc_next === expected_pc) begin
                pass_count = pass_count + 1;
                if (VERBOSE_MODE) begin
                    $display("  ✅ PASS: %0s", test_name);
                    $display("      Current PC: 0x%08h, Next PC: 0x%08h", pc_f, pc_next);
                    $display("      Controls: JALR=%b Branch=%b JAL=%b Stall=%b", jalr_e, branch_e, jal_d, stall_f);
                end
            end else begin
                fail_count = fail_count + 1;
                $display("  ❌ FAIL: %0s", test_name);
                $display("      Current PC: 0x%08h", pc_f);
                $display("      Controls: JALR=%b Branch=%b JAL=%b Stall=%b", jalr_e, branch_e, jal_d, stall_f);
                $display("      Targets: JALR=0x%08h Branch=0x%08h JAL=0x%08h", jalr_target, branch_target, jal_target);
                $display("      Expected: 0x%08h, Got: 0x%08h", expected_pc, pc_next);
            end
        end
    endtask
    
    // =================================================================
    // Test Summary Display
    // =================================================================
    task display_test_summary();
        real pass_rate;
        begin
            $display("\n========================================");
            $display("NPC GENERATOR TESTBENCH SUMMARY");
            $display("========================================");
            $display("Total Tests:  %0d", test_count);
            $display("Passed:       %0d", pass_count);
            $display("Failed:       %0d", fail_count);
            
            if (test_count > 0) begin
                pass_rate = ($itor(pass_count) / $itor(test_count)) * 100.0;
                $display("Pass Rate:    %0.1f%%", pass_rate);
                
                if (fail_count == 0) begin
                    $display("🎉 ALL TESTS PASSED! NPC Generator implementation is correct.");
                end else begin
                    $display("⚠️  Some tests failed. Review NPC Generator implementation.");
                end
            end
            
            $display("========================================");
            $display("Simulation completed at time: %0t", $time);
        end
    endtask
    
    // =================================================================
    // Waveform Dumping
    // =================================================================
    initial begin
        $dumpfile("npc_generator_tb.vcd");
        $dumpvars(0, npc_generator_tb);
    end

endmodule

verify/results/npc_generator_tb.vcd
$date
	Fri Sep 26 13:48:37 2025
$end
$version
	Icarus Verilog
$end
$timescale
	1ps
$end
$scope module npc_generator_tb $end
$var wire 32 ! pc_next [31:0] $end
$var parameter 32 " CLOCK_PERIOD $end
$var parameter 32 # DATA_WIDTH $end
$var parameter 32 $ VERBOSE_MODE $end
$var reg 1 % branch_e $end
$var reg 32 & branch_target [31:0] $end
$var reg 1 ' clk $end
$var reg 1 ( jal_d $end
$var reg 32 ) jal_target [31:0] $end
$var reg 1 * jalr_e $end
$var reg 32 + jalr_target [31:0] $end
$var reg 32 , pc_f [31:0] $end
$var reg 1 - rst_n $end
$var reg 1 . stall_f $end
$var integer 32 / fail_count [31:0] $end
$var integer 32 0 pass_count [31:0] $end
$var integer 32 1 test_count [31:0] $end
$scope module dut $end
$var wire 1 % branch_e $end
$var wire 32 2 branch_target [31:0] $end
$var wire 1 ' clk $end
$var wire 1 ( jal_d $end
$var wire 32 3 jal_target [31:0] $end
$var wire 1 * jalr_e $end
$var wire 32 4 jalr_target [31:0] $end
$var wire 32 5 pc_f [31:0] $end
$var wire 1 - rst_n $end
$var wire 1 . stall_f $end
$var reg 32 6 pc_next [31:0] $end
$upscope $end
$scope task display_test_summary $end
$var real 1 7 pass_rate $end
$upscope $end
$scope task initialize_inputs $end
$upscope $end
$scope task run_branch_tests $end
$upscope $end
$scope task run_corner_case_tests $end
$upscope $end
$scope task run_jal_tests $end
$upscope $end
$scope task run_jalr_tests $end
$upscope $end
$scope task run_priority_tests $end
$upscope $end
$scope task run_reset_tests $end
$upscope $end
$scope task run_sequential_pc_tests $end
$upscope $end
$scope task run_stall_tests $end
$upscope $end
$scope task test_pc_generation $end
$var reg 32 8 expected_pc [31:0] $end
$var reg 1600 9 test_name [1600:1] $end
$upscope $end
$upscope $end
$enddefinitions $end
$comment Show the parameter values. $end
$dumpall
b1 $
b100000 #
b1010 "
$end
#0
$dumpvars
bx 9
bx 8
r0 7
b0 6
b0 5
b0 4
b0 3
b0 2
b0 1
b0 0
b0 /
0.
0-
b0 ,
b0 +
0*
b0 )
0(
0'
b0 &
0%
b0 !
$end
#5000
1'
#10000
0'
#15000
1'
#20000
b100 !
b100 6
0'
1-
#25000
1'
#30000
b0 !
b0 6
0'
0-
b10010001101000101011001111000 ,
b10010001101000101011001111000 5
#31000
b10010001101000101011001111100 !
b10010001101000101011001111100 6
1-
b1 0
b1 1
b1010010011001010111001101100101011101000010000001110011011101000110000101110100011001010010000000101101001000000101000001000011001000000111001101101000011011110111010101101100011001000010000001100010011001010010000000110000011110000011000000110000001100000011000000110000001100000011000000110000 9
b0 8
#32000
b100 !
b100 6
b0 ,
b0 5
1-
b10 0
b10 1
b100000101100110011101000110010101110010001000000111001001100101011100110110010101110100001000000010110100100000011100110110010101110001011101010110010101101110011101000110100101100001011011000010000001010000010000110010101100110100 9
b10010001101000101011001111100 8
#33000
b100000100 !
b100000100 6
b100000000 ,
b100000000 5
b11 0
b11 1
b101001101100101011100010111010101100101011011100111010001101001011000010110110000111010001000000101000001000011001111010011000000100000001011010011111000100000010100000100001100101011001101000011110100110100 9
b100 8
#34000
b10010001101000101011001111100 !
b10010001101000101011001111100 6
b10010001101000101011001111000 ,
b10010001101000101011001111000 5
b100 0
b100 1
b1010011011001010111000101110101011001010110111001110100011010010110000101101100001110100010000001010000010000110011110100110000011110000011000100110000001100000010000000101101001111100010000001010000010000110010101100110100001111010011000001111000001100010011000000110100 9
b100000100 8
#35000
b1000000000100 !
b1000000000100 6
b1000000000000 ,
b1000000000000 5
b101 0
b101 1
b10100110110010101110001011101010110010101101110011101000110100101100001011011000011101000100000010100000100001100111101001100000111100000110001001100100011001100110100001101010011011000110111001110000010000000101101001111100010000001010000010000110010101100110100 9
b10010001101000101011001111100 8
1'
#36000
b11111111111111111111111111111100 !
b11111111111111111111111111111100 6
b11111111111111111111111111111000 ,
b11111111111111111111111111111000 5
b110 0
b110 1
b10100110110010101110001011101010110010101101110011101000110100101100001011011000011101000100000010000010110110001101001011001110110111001100101011001000010000001100001011001000110010001110010011001010111001101110011 9
b1000000000100 8
#37000
b1000000000000 !
b1000000000000 6
b1000000000000 )
b1000000000000 3
1(
b100000000 ,
b100000000 5
1-
0'
b111 0
b111 1
b101001101100101011100010111010101100101011011100111010001101001011000010110110000111010001000000100111001100101011000010111001000100000011011010110000101111000011010010110110101110101011011010010000001100001011001000110010001110010011001010111001101110011 9
b11111111111111111111111111111100 8
#38000
b1000000000 !
b1000000000 6
b1000000000 )
b1000000000 3
b1000000000000 ,
b1000000000000 5
b1000 0
b1000 1
b1001010010000010100110000111010001000000100101001110101011011010111000000100000011101000110111100100000011100000110111101110011011010010111010001101001011101100110010100100000011101000110000101110010011001110110010101110100 9
b1000000000000 8
#39000
b1000000000100 !
b1000000000100 6
0(
b1001 0
b1001 1
b100101001000001010011000011101000100000010010100111010101101101011100000010000001110100011011110010000001100010011000010110001101101011011101110110000101110010011001000111001100100000011101000110000101110010011001110110010101110100 9
b1000000000 8
#40000
b0 !
b0 6
b0 )
b0 3
1(
b1010 0
b1010 1
b1001010010000010100110000100000011001000110100101110011011000010110001001101100011001010110010000111010001000000101001101101000011011110111010101101100011001000010000001100010011001010010000001110011011001010111000101110101011001010110111001110100011010010110000101101100 9
b1000000000100 8
1'
#41000
b10000000000 !
b10000000000 6
b10000000000 &
b10000000000 2
1%
0(
b1000000000 ,
b1000000000 5
1-
0'
b1011 0
b1011 1
b1001010010000010100110000111010001000000100101001110101011011010111000000100000011101000110111100100000011000010110010001100100011100100110010101110011011100110010000000110000 9
b0 8
#42000
b1000000100 !
b1000000100 6
0%
b1100 0
b1100 1
b1000010011100100110000101101110011000110110100000100000011101000110000101101011011001010110111000111010001000000100101001110101011011010111000000100000011101000110111100100000011101000110000101110010011001110110010101110100 9
b10000000000 8
#43000
b100000000 !
b100000000 6
b100000000 &
b100000000 2
1%
b1101 0
b1101 1
b10000100111001001100001011011100110001101101000001000000110111001101111011101000010000001110100011000010110101101100101011011100011101000100000010100110110010101110001011101010110010101101110011101000110100101100001011011000010000001010000010000110010101100110100 9
b1000000100 8
#44000
b100000000000 !
b100000000000 6
b100000000000 &
b100000000000 2
b10000000000000 )
b10000000000000 3
1(
b1110 0
b1110 1
b10000100111001001100001011011100110001101101000001000000111010001100001011010110110010101101110001110100010000001000010011000010110001101101011011101110110000101110010011001000111001100100000011101000110000101110010011001110110010101110100 9
b100000000 8
#45000
b101000000000000 !
b101000000000000 6
b101000000000000 +
b101000000000000 4
1*
b0 )
b0 3
b0 &
b0 2
0(
0%
b1100000000 ,
b1100000000 5
1-
b1111 0
b1111 1
b10000100111001001100001011011100110001101101000001000000111000001110010011010010110111101110010011010010111010001111001001110100010000001000010011100100110000101101110011000110110100000100000011000100110010101100001011101000111001100100000010010100100000101001100 9
b100000000000 8
0'
#46000
b0 !
b0 6
b0 +
b0 4
b10000 0
b10000 1
b100101001000001010011000101001000111010001000000100101001110101011011010111000000100000011101000110111100100000011100100110010101100111011010010111001101110100011001010111001000100000011101000110000101110010011001110110010101110100 9
b101000000000000 8
#47000
b1100000100 !
b1100000100 6
0*
b10001 0
b10001 1
b100101001000001010011000101001000111010001000000100101001110101011011010111000000100000011101000110111100100000011000010110010001100100011100100110010101110011011100110010000000110000 9
b0 8
#48000
b1000000000000 !
b1000000000000 6
b11000000000000 )
b11000000000000 3
1(
b10000000000000 &
b10000000000000 2
1%
b1000000000000 +
b1000000000000 4
1*
b10000000000 ,
b10000000000 5
1-
b10010 0
b10010 1
b10010100100000101001100010100100010000001100100011010010111001101100001011000100110110001100101011001000011101000100000010100110110010101110001011101010110010101101110011101000110100101100001011011000010000001010000010000110010101100110100 9
b1100000100 8
#49000
b10000000000000 !
b10000000000000 6
0*
b10011 0
b10011 1
b101000001110010011010010110111101110010011010010111010001111001001110100010000001001010010000010100110001010010001000000110001001100101011000010111010001110011001000000100001001110010011000010110111001100011011010000010000001100001011011100110010000100000010010100100000101001100 9
b1000000000000 8
#50000
b11000000000000 !
b11000000000000 6
0%
b10100 0
b10100 1
b101000001110010011010010110111101110010011010010111010001111001001110100010000001000010011100100110000101101110011000110110100000100000011000100110010101100001011101000111001100100000010010100100000101001100 9
b10000000000000 8
1'
#51000
b10000000100 !
b10000000100 6
0(
b10101 0
b10101 1
b10100000111001001101001011011110111001001101001011101000111100100111010001000000100101001000001010011000010000001100010011001010110000101110100011100110010000001110011011001010111000101110101011001010110111001110100011010010110000101101100 9
b11000000000000 8
#52000
b10100000000 !
b10100000000 6
1.
b0 )
b0 3
b0 +
b0 4
b0 &
b0 2
b10100000000 ,
b10100000000 5
1-
0'
b10110 0
b10110 1
b10100000111001001101001011011110111001001101001011101000111100100111010001000000100000101101100011011000010000001100100011010010111001101100001011000100110110001100101011001000010110000100000011100110110010101110001011101010110010101101110011101000110100101100001011011000010000001010000010000110010101100110100 9
b10000000100 8
#53000
b1000000000000 )
b1000000000000 3
1(
b10111 0
b10111 1
b10100110111010001100001011011000110110000111010001000000101000001000011001000000111001101101000011011110111010101101100011001000010000001101110011011110111010000100000011000110110100001100001011011100110011101100101 9
b10100000000 8
#54000
b10000000000000 &
b10000000000000 2
1%
0(
b11000 0
b11000 1
b10100110111010001100001011011000110110000100000011101110110100101110100011010000010000001001010010000010100110000111010001000000101000001000011001000000111001101101000011011110111010101101100011001000010000001101110011011110111010000100000011000110110100001100001011011100110011101100101 9
#55000
b11000000000000 +
b11000000000000 4
1*
0%
b11001 0
b11001 1
b10100110111010001100001011011000110110000100000011101110110100101110100011010000010000001000010011100100110000101101110011000110110100000111010001000000101000001000011001000000111001101101000011011110111010101101100011001000010000001101110011011110111010000100000011000110110100001100001011011100110011101100101 9
1'
#56000
b11000000000000 !
b11000000000000 6
0.
b11010 0
b11010 1
b1010011011101000110000101101100011011000010000001110111011010010111010001101000001000000100101001000001010011000101001000111010001000000101000001000011001000000111001101101000011011110111010101101100011001000010000001101110011011110111010000100000011000110110100001100001011011100110011101100101 9
#57000
b0 !
b0 6
b0 )
b0 3
b0 +
b0 4
b0 &
b0 2
0*
b11111111111111111111111111111100 ,
b11111111111111111111111111111100 5
1-
0'
b11011 0
b11011 1
b1010011011101000110000101101100011011000010000001110010011001010110110001100101011000010111001101100101001110100010000001001010010000010100110001010010001000000111001101101000011011110111010101101100011001000010000001110111011011110111001001101011 9
b11000000000000 8
#58000
b1000000000000 !
b1000000000000 6
b1000000000000 )
b1000000000000 3
b1000000000000 &
b1000000000000 2
b1000000000000 +
b1000000000000 4
1(
1%
1*
b11000000000 ,
b11000000000 5
b11100 0
b11100 1
b100001101101111011100100110111001100101011100100011101000100000010011010110000101111000011010010110110101110101011011010010000001010000010000110010000001110111011100100110000101110000011100110010000001110100011011110010000000110000 9
b0 8
#59000
b11100000000 !
b11100000000 6
b11100000000 &
b11100000000 2
0(
0*
b11100000000 ,
b11100000000 5
b11101 0
b11101 1
b10000110110111101110010011011100110010101110010001110100010000001000001011011000110110000100000011101000110000101110010011001110110010101110100011100110010000001110011011000010110110101100101001011000010000001001010010000010100110001010010001000000111000001110010011010010110111101110010011010010111010001111001 9
b1000000000000 8
#60000
b11100000101 !
b11100000101 6
0%
b11100000001 ,
b11100000001 5
b11110 0
b11110 1
b10000110110111101110010011011100110010101110010001110100010000001000010011100100110000101101110011000110110100000100000011101000110111100100000011100110110000101101101011001010010000001100001011001000110010001110010011001010111001101110011 9
b11100000000 8
1'
#61000
r100 7
b11111 0
b11111 1
b10000110110111101110010011011100110010101110010001110100010000001010101011011100110000101101100011010010110011101101110011001010110010000100000010100000100001100100000001010110010000000110100 9
b11100000101 8
