src/reset_synchronizer.v
// =============================================================================
// Reset Synchronizer Module
// =============================================================================
// Description: Provides async reset, synchronous de-assert functionality
//              Follows RTL design rules for robust reset strategy
// Author: Auto-generated following RTL design rules
// Date: September 15, 2025
// =============================================================================

// =============================================================================
// Local Constants (moved from riscv_constants.vh)
// =============================================================================
// (No constants needed for this module)

module reset_synchronizer #(
    // =================================================================
    // Parameters
    // =================================================================
    parameter SYNC_STAGES = 2,              // Number of sync flip-flops
    parameter RESET_POLARITY = 1'b0         // 0: active low, 1: active high
)(
    // =================================================================
    // Clock and Reset Interface
    // =================================================================
    input  wire clk,                        // Clock input
    input  wire async_rst,                  // Asynchronous reset input
    output wire sync_rst_n                  // Synchronized reset output (always active low)
);

    // =================================================================
    // Local Parameters  
    // =================================================================
    localparam RESET_ACTIVE = RESET_POLARITY;
    // localparam RESET_INACTIVE = ~RESET_POLARITY;  // unused

    // =================================================================
    // Signal Declarations
    // =================================================================
    reg [SYNC_STAGES-1:0] sync_reg;

    // =================================================================
    // Reset Synchronizer Logic
    // =================================================================
    // Async reset, sync de-assert pattern
    always @(posedge clk or posedge (async_rst == RESET_ACTIVE ? 1'b1 : 1'b0)) begin
        if (async_rst == RESET_ACTIVE) begin
            sync_reg <= {SYNC_STAGES{1'b0}};
        end else begin
            sync_reg <= {sync_reg[SYNC_STAGES-2:0], 1'b1};
        end
    end

    // =================================================================
    // Output Assignment
    // =================================================================
    assign sync_rst_n = sync_reg[SYNC_STAGES-1];


endmodule

// =============================================================================
// End of File
// =============================================================================

verify/testbench/reset_synchronizer_tb.v
// =============================================================================
// Reset Synchronizer Testbench - Comprehensive Verification
// =============================================================================
// Description: Tests reset synchronizer for async reset, sync deassert behavior
// Author: Auto-generated testbench
// Date: September 23, 2025
// Features: - Async reset assertion testing
//          - Sync reset deassertion testing
//          - Timing verification  
//          - Multiple sync stages testing
//          - Reset polarity testing
// =============================================================================

`timescale 1ns / 1ps

module reset_synchronizer_tb;

    // =================================================================
    // Testbench Parameters
    // =================================================================
    parameter CLOCK_PERIOD = 10;
    parameter VERBOSE_MODE = 1;
    
    // =================================================================
    // Test Signal Declarations
    // =================================================================
    reg         clk;
    reg         async_rst;
    wire        sync_rst_n;
    
    // Test control
    integer test_count;
    integer pass_count;
    integer fail_count;
    
    // Multiple DUTs for different configurations
    wire sync_rst_n_2stage;
    wire sync_rst_n_3stage; 
    wire sync_rst_n_active_high;
    
    // =================================================================
    // Device Under Test (DUT) - Multiple Configurations
    // =================================================================
    
    // Standard 2-stage, active-low reset
    reset_synchronizer #(
        .SYNC_STAGES(2),
        .RESET_POLARITY(1'b0)  // Active low async reset
    ) dut_2stage (
        .clk(clk),
        .async_rst(async_rst),
        .sync_rst_n(sync_rst_n_2stage)
    );
    
    // 3-stage synchronizer
    reset_synchronizer #(
        .SYNC_STAGES(3),
        .RESET_POLARITY(1'b0)
    ) dut_3stage (
        .clk(clk),
        .async_rst(async_rst),
        .sync_rst_n(sync_rst_n_3stage)
    );
    
    // Active-high reset input
    reset_synchronizer #(
        .SYNC_STAGES(2),
        .RESET_POLARITY(1'b1)  // Active high async reset
    ) dut_active_high (
        .clk(clk),
        .async_rst(~async_rst),  // Invert for active-high testing
        .sync_rst_n(sync_rst_n_active_high)
    );
    
    // Default DUT for main tests
    assign sync_rst_n = sync_rst_n_2stage;
    
    // =================================================================
    // Clock Generation
    // =================================================================
    initial begin
        clk = 0;
        forever #(CLOCK_PERIOD/2) clk = ~clk;
    end
    
    // =================================================================
    // Test Execution Control
    // =================================================================
    initial begin
        // Initialize counters
        test_count = 0;
        pass_count = 0;
        fail_count = 0;
        
        // Initialize inputs - start with reset active
        async_rst = 1'b0; // Active low reset
        
        $display("========================================");
        $display("RESET SYNCHRONIZER TESTBENCH STARTING");
        $display("========================================");
        $display("Time: %0t", $time);
        
        // Wait for initial settling
        #(CLOCK_PERIOD * 3);
        
        // Run test suites
        run_async_reset_tests();
        run_sync_deassert_tests();
        run_timing_tests();
        run_multi_stage_tests();
        run_reset_polarity_tests();
        run_corner_case_tests();
        
        // Display results
        display_test_summary();
        
        #100;
        $finish;
    end
    
    // =================================================================
    // Test Suite: Asynchronous Reset Tests
    // =================================================================
    task run_async_reset_tests();
        begin
            $display("\n[%0t] Running Asynchronous Reset Tests...", $time);
            
            // Test immediate reset assertion (async)
            async_rst = 1'b1;  // Release reset first
            #(CLOCK_PERIOD * 2);
            
            async_rst = 1'b0;  // Assert reset asynchronously (not on clock edge)
            #1; // Immediate check, not waiting for clock
            
            test_reset_signal(sync_rst_n, 1'b0, "Async reset: Should be immediate (not on clock edge)");
            
            // Reset should be active regardless of clock
            #(CLOCK_PERIOD * 0.7); // Check mid-clock cycle
            test_reset_signal(sync_rst_n, 1'b0, "Async reset: Active independent of clock");
            
            // Keep reset asserted through multiple clocks
            #(CLOCK_PERIOD * 2);
            test_reset_signal(sync_rst_n, 1'b0, "Async reset: Remains active");
            
            $display("Asynchronous Reset Tests Completed");
        end
    endtask
    
    // =================================================================
    // Test Suite: Synchronous Deassertion Tests
    // =================================================================
    task run_sync_deassert_tests();
        begin
            $display("\n[%0t] Running Synchronous Deassertion Tests...", $time);
            
            // Start with reset asserted
            async_rst = 1'b0;
            #(CLOCK_PERIOD);
            test_reset_signal(sync_rst_n, 1'b0, "Reset asserted before deassertion test");
            
            // Release async reset and check synchronous deassertion
            async_rst = 1'b1;
            
            // First clock edge - should still be in reset (2-stage synchronizer)
            @(posedge clk);
            #1; // Small delay for propagation
            test_reset_signal(sync_rst_n, 1'b0, "Sync deassert: 1st clock - still in reset");
            
            // Second clock edge - should come out of reset (2-stage)
            @(posedge clk);
            #1;
            test_reset_signal(sync_rst_n, 1'b1, "Sync deassert: 2nd clock - out of reset");
            
            // Should remain out of reset
            @(posedge clk);
            #1;
            test_reset_signal(sync_rst_n, 1'b1, "Sync deassert: Remains out of reset");
            
            $display("Synchronous Deassertion Tests Completed");
        end
    endtask
    
    // =================================================================
    // Test Suite: Timing Verification Tests
    // =================================================================
    task run_timing_tests();
        begin
            $display("\n[%0t] Running Timing Tests...", $time);
            
            // Test setup and hold time behavior
            async_rst = 1'b0; // Assert reset
            #(CLOCK_PERIOD);
            
            // Release reset just before clock edge
            #(CLOCK_PERIOD - 1);
            async_rst = 1'b1;
            #1;
            @(posedge clk);
            #1;
            test_reset_signal(sync_rst_n, 1'b0, "Timing: Reset released just before clock");
            
            // Next clock should start deassertion
            @(posedge clk);
            #1;
            test_reset_signal(sync_rst_n, 1'b0, "Timing: First deassert clock");
            
            @(posedge clk);
            #1;
            test_reset_signal(sync_rst_n, 1'b1, "Timing: Second deassert clock");
            
            // Test reset assertion during deassertion sequence
            async_rst = 1'b0; // Assert reset
            #(CLOCK_PERIOD);
            async_rst = 1'b1; // Release
            
            @(posedge clk);
            async_rst = 1'b0; // Re-assert during deassertion
            #1;
            test_reset_signal(sync_rst_n, 1'b0, "Timing: Re-assert during deassertion");
            
            $display("Timing Tests Completed");
        end
    endtask
    
    // =================================================================
    // Test Suite: Multiple Stage Tests
    // =================================================================
    task run_multi_stage_tests();
        begin
            $display("\n[%0t] Running Multi-Stage Tests...", $time);
            
            // Compare 2-stage vs 3-stage behavior
            async_rst = 1'b0;
            #(CLOCK_PERIOD);
            test_reset_signal(sync_rst_n_2stage, 1'b0, "Multi: 2-stage in reset");
            test_reset_signal(sync_rst_n_3stage, 1'b0, "Multi: 3-stage in reset");
            
            // Release and compare timing
            async_rst = 1'b1;
            
            // 1st clock
            @(posedge clk);
            #1;
            test_reset_signal(sync_rst_n_2stage, 1'b0, "Multi: 2-stage 1st clock - still reset");
            test_reset_signal(sync_rst_n_3stage, 1'b0, "Multi: 3-stage 1st clock - still reset");
            
            // 2nd clock
            @(posedge clk);
            #1;
            test_reset_signal(sync_rst_n_2stage, 1'b1, "Multi: 2-stage 2nd clock - out of reset");
            test_reset_signal(sync_rst_n_3stage, 1'b0, "Multi: 3-stage 2nd clock - still reset");
            
            // 3rd clock
            @(posedge clk);
            #1;
            test_reset_signal(sync_rst_n_2stage, 1'b1, "Multi: 2-stage 3rd clock - out of reset");
            test_reset_signal(sync_rst_n_3stage, 1'b1, "Multi: 3-stage 3rd clock - out of reset");
            
            $display("Multi-Stage Tests Completed");
        end
    endtask
    
    // =================================================================
    // Test Suite: Reset Polarity Tests
    // =================================================================
    task run_reset_polarity_tests();
        begin
            $display("\n[%0t] Running Reset Polarity Tests...", $time);
            
            // Note: async_rst is inverted for active-high DUT
            
            // Test active-high reset assertion
            async_rst = 1'b1;  // This makes ~async_rst = 0 (active for active-high)
            #1;
            test_reset_signal(sync_rst_n_active_high, 1'b0, "Polarity: Active-high reset asserted");
            
            // Test active-high reset release
            async_rst = 1'b0;  // This makes ~async_rst = 1 (inactive for active-high)
            
            @(posedge clk);
            #1;
            test_reset_signal(sync_rst_n_active_high, 1'b0, "Polarity: Active-high 1st clock");
            
            @(posedge clk);
            #1;
            test_reset_signal(sync_rst_n_active_high, 1'b1, "Polarity: Active-high 2nd clock - released");
            
            // Compare with active-low behavior (should be same output timing)
            async_rst = 1'b1;  // Reset both
            #(CLOCK_PERIOD);
            
            async_rst = 1'b0;  // Release both (active-low normal, active-high through inversion)
            
            @(posedge clk);
            #1;
            test_reset_signals_equal(sync_rst_n_2stage, sync_rst_n_active_high, "Polarity: Both should behave same - 1st clock");
            
            @(posedge clk);
            #1;
            test_reset_signals_equal(sync_rst_n_2stage, sync_rst_n_active_high, "Polarity: Both should behave same - 2nd clock");
            
            $display("Reset Polarity Tests Completed");
        end
    endtask
    
    // =================================================================
    // Test Suite: Corner Cases
    // =================================================================
    task run_corner_case_tests();
        begin
            $display("\n[%0t] Running Corner Case Tests...", $time);
            
            // Test multiple reset assertions/releases
            async_rst = 1'b0;
            #(CLOCK_PERIOD/4);
            async_rst = 1'b1;
            #(CLOCK_PERIOD/4);
            async_rst = 1'b0;
            #(CLOCK_PERIOD/4);
            async_rst = 1'b1;
            #1;
            
            // Should be following the last transition
            @(posedge clk);
            #1;
            test_reset_signal(sync_rst_n, 1'b0, "Corner: Multiple toggles - 1st clock");
            
            @(posedge clk);
            #1;
            test_reset_signal(sync_rst_n, 1'b1, "Corner: Multiple toggles - 2nd clock");
            
            // Test very short reset pulse
            async_rst = 1'b0;
            #1; // Very short pulse
            async_rst = 1'b1;
            #1;
            test_reset_signal(sync_rst_n, 1'b0, "Corner: Short reset pulse should still work");
            
            // Wait for deassertion
            @(posedge clk);
            @(posedge clk);
            #1;
            test_reset_signal(sync_rst_n, 1'b1, "Corner: Short pulse recovery");
            
            // Test reset at various clock phases
            async_rst = 1'b0;
            #(CLOCK_PERIOD/2); // Mid clock cycle
            test_reset_signal(sync_rst_n, 1'b0, "Corner: Reset at mid-clock");
            
            async_rst = 1'b1;
            #(CLOCK_PERIOD/4);
            async_rst = 1'b0;
            #(CLOCK_PERIOD/4);
            async_rst = 1'b1;
            
            // Final test - normal operation
            @(posedge clk);
            @(posedge clk);
            #1;
            test_reset_signal(sync_rst_n, 1'b1, "Corner: Final normal operation");
            
            $display("Corner Case Tests Completed");
        end
    endtask
    
    // =================================================================
    // Helper Task: Test Reset Signal
    // =================================================================
    task test_reset_signal(
        input       actual_value,
        input       expected_value,
        input [200*8:1] test_name
    );
        begin
            test_count = test_count + 1;
            
            if (actual_value === expected_value) begin
                pass_count = pass_count + 1;
                if (VERBOSE_MODE) begin
                    $display("  ✅ PASS: %0s", test_name);
                    $display("      sync_rst_n: %b (expected: %b)", actual_value, expected_value);
                end
            end else begin
                fail_count = fail_count + 1;
                $display("  ❌ FAIL: %0s", test_name);
                $display("      Expected: %b, Got: %b", expected_value, actual_value);
                $display("      async_rst: %b, Time: %0t", async_rst, $time);
            end
        end
    endtask
    
    // =================================================================
    // Helper Task: Test Two Signals Equal
    // =================================================================
    task test_reset_signals_equal(
        input       signal1,
        input       signal2,
        input [200*8:1] test_name
    );
        begin
            test_count = test_count + 1;
            
            if (signal1 === signal2) begin
                pass_count = pass_count + 1;
                if (VERBOSE_MODE) begin
                    $display("  ✅ PASS: %0s", test_name);
                    $display("      Both signals: %b", signal1);
                end
            end else begin
                fail_count = fail_count + 1;
                $display("  ❌ FAIL: %0s", test_name);
                $display("      Signal1: %b, Signal2: %b", signal1, signal2);
            end
        end
    endtask
    
    // =================================================================
    // Test Summary Display
    // =================================================================
    task display_test_summary();
        real pass_rate;
        begin
            $display("\n========================================");
            $display("RESET SYNCHRONIZER TESTBENCH SUMMARY");
            $display("========================================");
            $display("Total Tests:  %0d", test_count);
            $display("Passed:       %0d", pass_count);
            $display("Failed:       %0d", fail_count);
            
            if (test_count > 0) begin
                pass_rate = ($itor(pass_count) / $itor(test_count)) * 100.0;
                $display("Pass Rate:    %0.1f%%", pass_rate);
                
                if (fail_count == 0) begin
                    $display("🎉 ALL TESTS PASSED! Reset Synchronizer implementation is correct.");
                end else begin
                    $display("⚠️  Some tests failed. Review Reset Synchronizer implementation.");
                end
            end
            
            $display("========================================");
            $display("Simulation completed at time: %0t", $time);
            $display("\nReset Synchronizer Features Verified:");
            $display("✅ Asynchronous reset assertion");
            $display("✅ Synchronous reset deassertion");  
            $display("✅ 2-stage and 3-stage operation");
            $display("✅ Active-low and active-high polarity");
            $display("✅ Timing and corner cases");
        end
    endtask
    
    // =================================================================
    // Waveform Dumping
    // =================================================================
    initial begin
        $dumpfile("reset_synchronizer_tb.vcd");
        $dumpvars(0, reset_synchronizer_tb);
    end

endmodule

verify/results/reset_synchronizer_tb.vcd
$date
	Fri Sep 26 13:48:59 2025
$end
$version
	Icarus Verilog
$end
$timescale
	1ps
$end
$scope module reset_synchronizer_tb $end
$var wire 1 ! sync_rst_n $end
$var wire 1 " sync_rst_n_active_high $end
$var wire 1 # sync_rst_n_3stage $end
$var wire 1 $ sync_rst_n_2stage $end
$var parameter 32 % CLOCK_PERIOD $end
$var parameter 32 & VERBOSE_MODE $end
$var reg 1 ' async_rst $end
$var reg 1 ( clk $end
$var integer 32 ) fail_count [31:0] $end
$var integer 32 * pass_count [31:0] $end
$var integer 32 + test_count [31:0] $end
$scope module dut_2stage $end
$var wire 1 ' async_rst $end
$var wire 1 ( clk $end
$var wire 1 $ sync_rst_n $end
$var parameter 1 , RESET_ACTIVE $end
$var parameter 1 - RESET_POLARITY $end
$var parameter 32 . SYNC_STAGES $end
$var reg 2 / sync_reg [1:0] $end
$upscope $end
$scope module dut_3stage $end
$var wire 1 ' async_rst $end
$var wire 1 ( clk $end
$var wire 1 # sync_rst_n $end
$var parameter 1 0 RESET_ACTIVE $end
$var parameter 1 1 RESET_POLARITY $end
$var parameter 32 2 SYNC_STAGES $end
$var reg 3 3 sync_reg [2:0] $end
$upscope $end
$scope module dut_active_high $end
$var wire 1 4 async_rst $end
$var wire 1 ( clk $end
$var wire 1 " sync_rst_n $end
$var parameter 1 5 RESET_ACTIVE $end
$var parameter 1 6 RESET_POLARITY $end
$var parameter 32 7 SYNC_STAGES $end
$var reg 2 8 sync_reg [1:0] $end
$upscope $end
$scope task display_test_summary $end
$var real 1 9 pass_rate $end
$upscope $end
$scope task run_async_reset_tests $end
$upscope $end
$scope task run_corner_case_tests $end
$upscope $end
$scope task run_multi_stage_tests $end
$upscope $end
$scope task run_reset_polarity_tests $end
$upscope $end
$scope task run_sync_deassert_tests $end
$upscope $end
$scope task run_timing_tests $end
$upscope $end
$scope task test_reset_signal $end
$var reg 1 : actual_value $end
$var reg 1 ; expected_value $end
$var reg 1600 < test_name [1600:1] $end
$upscope $end
$scope task test_reset_signals_equal $end
$var reg 1 = signal1 $end
$var reg 1 > signal2 $end
$var reg 1600 ? test_name [1600:1] $end
$upscope $end
$upscope $end
$enddefinitions $end
$comment Show the parameter values. $end
$dumpall
b10 7
16
15
b11 2
01
00
b10 .
0-
0,
b1 &
b1010 %
$end
#0
$dumpvars
bx ?
x>
x=
bx <
x;
x:
r0 9
b0 8
14
b0 3
b0 /
b0 +
b0 *
b0 )
0(
0'
0$
0#
0"
0!
$end
#5000
1(
#10000
0(
#15000
1(
#20000
0(
#25000
1(
#30000
04
0(
1'
#35000
b1 /
b1 3
b1 8
1(
#40000
0(
#45000
1!
1$
1"
b11 /
b11 3
b11 8
1(
#50000
0"
0!
0$
b0 8
b0 /
b0 3
14
0(
0'
#51000
b1 *
b1 +
b1000001011100110111100101101110011000110010000001110010011001010111001101100101011101000011101000100000010100110110100001101111011101010110110001100100001000000110001001100101001000000110100101101101011011010110010101100100011010010110000101110100011001010010000000101000011011100110111101110100001000000110111101101110001000000110001101101100011011110110001101101011001000000110010101100100011001110110010100101001 <
0;
0:
#55000
1(
#58000
b10 *
b10 +
b1000001011100110111100101101110011000110010000001110010011001010111001101100101011101000011101000100000010000010110001101110100011010010111011001100101001000000110100101101110011001000110010101110000011001010110111001100100011001010110111001110100001000000110111101100110001000000110001101101100011011110110001101101011 <
#60000
0(
#65000
1(
#70000
0(
#75000
1(
#78000
b11 *
b11 +
b10000010111001101111001011011100110001100100000011100100110010101110011011001010111010000111010001000000101001001100101011011010110000101101001011011100111001100100000011000010110001101110100011010010111011001100101 <
#80000
0(
#85000
1(
#88000
04
1'
b100 *
b100 +
b101001001100101011100110110010101110100001000000110000101110011011100110110010101110010011101000110010101100100001000000110001001100101011001100110111101110010011001010010000001100100011001010110000101110011011100110110010101110010011101000110100101101111011011100010000001110100011001010111001101110100 <
#90000
0(
#95000
b1 /
b1 3
b1 8
1(
#96000
b101 *
b101 +
b101001101111001011011100110001100100000011001000110010101100001011100110111001101100101011100100111010000111010001000000011000101110011011101000010000001100011011011000110111101100011011010110010000000101101001000000111001101110100011010010110110001101100001000000110100101101110001000000111001001100101011100110110010101110100 <
#100000
0(
#105000
1!
1$
1"
b11 /
b11 3
b11 8
1(
#106000
b110 *
b110 +
b10100110111100101101110011000110010000001100100011001010110000101110011011100110110010101110010011101000011101000100000001100100110111001100100001000000110001101101100011011110110001101101011001000000010110100100000011011110111010101110100001000000110111101100110001000000111001001100101011100110110010101110100 <
1;
1:
#110000
0(
#115000
1#
b111 3
1(
#116000
0"
0!
0$
0#
b0 8
b0 /
b0 3
14
0'
b111 *
b111 +
b101001101111001011011100110001100100000011001000110010101100001011100110111001101100101011100100111010000111010001000000101001001100101011011010110000101101001011011100111001100100000011011110111010101110100001000000110111101100110001000000111001001100101011100110110010101110100 <
#120000
0(
#125000
1(
#130000
0(
#135000
b1 /
b1 3
b1 8
04
1(
1'
#140000
0(
#145000
1!
1$
1"
b11 /
b11 3
b11 8
1(
#146000
b1 )
b1000 +
b1010100011010010110110101101001011011100110011100111010001000000101001001100101011100110110010101110100001000000111001001100101011011000110010101100001011100110110010101100100001000000110101001110101011100110111010000100000011000100110010101100110011011110111001001100101001000000110001101101100011011110110001101101011 <
0;
#150000
0(
#155000
1#
b111 3
1(
#156000
b10 )
b1001 +
b1010100011010010110110101101001011011100110011100111010001000000100011001101001011100100111001101110100001000000110010001100101011000010111001101110011011001010111001001110100001000000110001101101100011011110110001101101011 <
#160000
0(
#165000
1(
#166000
0"
0!
0$
0#
b0 8
b0 /
b0 3
14
0'
b1000 *
b1010 +
b101010001101001011011010110100101101110011001110011101000100000010100110110010101100011011011110110111001100100001000000110010001100101011000010111001101110011011001010111001001110100001000000110001101101100011011110110001101101011 <
1;
#170000
0(
#175000
1(
#176000
04
1'
#180000
0(
#185000
b0 8
14
0'
1(
#186000
b1001 *
b1011 +
b10101000110100101101101011010010110111001100111001110100010000001010010011001010010110101100001011100110111001101100101011100100111010000100000011001000111010101110010011010010110111001100111001000000110010001100101011000010111001101110011011001010111001001110100011010010110111101101110 <
0;
0:
#190000
0(
#195000
1(
#196000
04
1'
b1011 *
b1101 +
b100110101110101011011000111010001101001001110100010000000110011001011010111001101110100011000010110011101100101001000000110100101101110001000000111001001100101011100110110010101110100 <
#200000
0(
#205000
b1 /
b1 3
b1 8
1(
#206000
b1101 *
b1111 +
b100110101110101011011000111010001101001001110100010000000110011001011010111001101110100011000010110011101100101001000000011000101110011011101000010000001100011011011000110111101100011011010110010000000101101001000000111001101110100011010010110110001101100001000000111001001100101011100110110010101110100 <
#210000
0(
#215000
1!
1$
1"
b11 /
b11 3
b11 8
1(
#216000
b1111 *
b10001 +
b100110101110101011011000111010001101001001110100010000000110011001011010111001101110100011000010110011101100101001000000011001001101110011001000010000001100011011011000110111101100011011010110010000000101101001000000111001101110100011010010110110001101100001000000111001001100101011100110110010101110100 <
0;
0:
#220000
0(
#225000
1#
b111 3
1(
#226000
b10001 *
b10011 +
b10011010111010101101100011101000110100100111010001000000011001100101101011100110111010001100001011001110110010100100000001100110111001001100100001000000110001101101100011011110110001101101011001000000010110100100000011011110111010101110100001000000110111101100110001000000111001001100101011100110110010101110100 <
1;
1:
#227000
0"
0!
0$
0#
b0 8
b0 /
b0 3
14
0'
b11 )
b10100 +
b10100000110111101101100011000010111001001101001011101000111100100111010001000000100000101100011011101000110100101110110011001010010110101101000011010010110011101101000001000000111001001100101011100110110010101110100001000000110000101110011011100110110010101110010011101000110010101100100 <
0;
#230000
0(
#235000
1(
#236000
b10010 *
b10101 +
b1010000011011110110110001100001011100100110100101110100011110010011101000100000010000010110001101110100011010010111011001100101001011010110100001101001011001110110100000100000001100010111001101110100001000000110001101101100011011110110001101101011 <
0:
#240000
0(
#245000
1(
#246000
04
1'
b100 )
b10110 +
b10100000110111101101100011000010111001001101001011101000111100100111010001000000100000101100011011101000110100101110110011001010010110101101000011010010110011101101000001000000011001001101110011001000010000001100011011011000110111101100011011010110010000000101101001000000111001001100101011011000110010101100001011100110110010101100100 <
1;
#250000
0(
#255000
b1 /
b1 3
b1 8
1(
#256000
b0 8
b0 /
b0 3
14
0'
#260000
0(
#265000
1(
#266000
b10011 *
b10111 +
b10100000110111101101100011000010111001001101001011101000111100100111010001000000100001001101111011101000110100000100000011100110110100001101111011101010110110001100100001000000110001001100101011010000110000101110110011001010010000001110011011000010110110101100101001000000010110100100000001100010111001101110100001000000110001101101100011011110110001101101011 ?
0>
0=
#270000
0(
#275000
1(
#276000
b10100 *
b11000 +
b10100000110111101101100011000010111001001101001011101000111100100111010001000000100001001101111011101000110100000100000011100110110100001101111011101010110110001100100001000000110001001100101011010000110000101110110011001010010000001110011011000010110110101100101001000000010110100100000001100100110111001100100001000000110001101101100011011110110001101101011 ?
#278000
04
1'
#280000
14
0'
0(
#282000
04
1'
#285000
b1 /
b1 3
b1 8
1(
#286000
b10101 *
b11001 +
b10000110110111101110010011011100110010101110010001110100010000001001101011101010110110001110100011010010111000001101100011001010010000001110100011011110110011101100111011011000110010101110011001000000010110100100000001100010111001101110100001000000110001101101100011011110110001101101011 <
0;
#290000
0(
#295000
1!
1$
1"
b11 /
b11 3
b11 8
1(
#296000
0"
0!
0$
b0 8
b0 /
b0 3
14
0'
b10110 *
b11010 +
b10000110110111101110010011011100110010101110010001110100010000001001101011101010110110001110100011010010111000001101100011001010010000001110100011011110110011101100111011011000110010101110011001000000010110100100000001100100110111001100100001000000110001101101100011011110110001101101011 <
1;
1:
#297000
04
1'
#298000
b10111 *
b11011 +
b1000011011011110111001001101110011001010111001000111010001000000101001101101000011011110111001001110100001000000111001001100101011100110110010101110100001000000111000001110101011011000111001101100101001000000111001101101000011011110111010101101100011001000010000001110011011101000110100101101100011011000010000001110111011011110111001001101011 <
0;
0:
#300000
0(
#305000
b1 /
b1 3
b1 8
1(
#310000
0(
#315000
1!
1$
1"
b11 /
b11 3
b11 8
1(
#316000
0"
0!
0$
b0 8
b0 /
b0 3
14
0'
b11000 *
b11100 +
b1000011011011110111001001101110011001010111001000111010001000000101001101101000011011110111001001110100001000000111000001110101011011000111001101100101001000000111001001100101011000110110111101110110011001010111001001111001 <
1;
1:
#320000
0(
#321000
04
1'
b11001 *
b11101 +
b100001101101111011100100110111001100101011100100011101000100000010100100110010101110011011001010111010000100000011000010111010000100000011011010110100101100100001011010110001101101100011011110110001101101011 <
0;
0:
#323000
14
0'
#325000
b1 /
b1 3
04
1'
1(
#330000
0(
#335000
1!
1$
b11 /
b11 3
b1 8
1(
#340000
0(
#345000
1#
1"
b111 3
b11 8
1(
#346000
r86.66666666666667 9
b11010 *
b11110 +
b10000110110111101110010011011100110010101110010001110100010000001000110011010010110111001100001011011000010000001101110011011110111001001101101011000010110110000100000011011110111000001100101011100100110000101110100011010010110111101101110 <
1;
1:
