ALU_Control_Unit/ALU_control_unit.v
module ALU_control_unit (
    input [1:0] ALUOp,         // Control signal from main control unit
    input [2:0] funct3,        // funct3 field from instruction
    input [6:0] funct7,        // funct7 field from instruction
    output reg [4:0] alu_control // Control signal for ALU (expanded to 5 bits)
);

    // ALU control signal breakdown (for 5-bit control)
    // alu_control[4]:   0 = Arithmetic operation, 1 = Logic operation
    // alu_control[3:2]: Operation type for Arithmetic (00: ADD, 01: SUB, 10: MUL, 11: DIV)
    // alu_control[3:0]: Operation type for Logic (see Logic module)
    // alu_control[0]:   Signed flag for arithmetic operations

    // ALUOp encoding
    // 00: Memory access (add)
    // 01: Branch (subtract)
    // 10: R-type (depends on funct3 and funct7)
    // 11: I-type (depends on funct3)

    // RISC-V funct3 codes for R-type and I-type instructions
    localparam F3_ADD_SUB = 3'b000;
    localparam F3_SLL     = 3'b001;
    localparam F3_SLT     = 3'b010;
    localparam F3_SLTU    = 3'b011;
    localparam F3_XOR     = 3'b100;
    localparam F3_SRL_SRA = 3'b101;
    localparam F3_OR      = 3'b110;
    localparam F3_AND     = 3'b111;

    // RISC-V funct7 codes
    localparam F7_DEFAULT = 7'b0000000;
    localparam F7_SUB_SRA = 7'b0100000;
    localparam F7_MUL_DIV = 7'b0000001; // For M extension

    // ALU operations (matching ALU module)
    // Arithmetic Operations
    localparam ADD_UNSIGNED = 5'b00000;
    localparam ADD_SIGNED   = 5'b00001;
    localparam SUB_UNSIGNED = 5'b00100;
    localparam SUB_SIGNED   = 5'b00101;
    localparam MUL_UNSIGNED = 5'b01000;
    localparam MUL_SIGNED   = 5'b01001;
    localparam DIV_UNSIGNED = 5'b01100;
    localparam DIV_SIGNED   = 5'b01101;

    // Logic Operations
    localparam AND_OP       = 5'b10000;
    localparam OR_OP        = 5'b10001;
    localparam XOR_OP       = 5'b10010;
    localparam NOT_OP       = 5'b10011;
    localparam SLL_OP       = 5'b10100;
    localparam SRL_OP       = 5'b10101;
    localparam SRA_OP       = 5'b10110;
    localparam NOR_OP       = 5'b10111;
    localparam EQ_OP        = 5'b11000;
    localparam NE_OP        = 5'b11001;
    localparam LT_SIGNED    = 5'b11010;
    localparam GE_SIGNED    = 5'b11011;
    localparam LT_UNSIGNED  = 5'b11100;
    localparam GE_UNSIGNED  = 5'b11101;

    // Combinational logic to determine ALU operation
    always @(*) begin
        case (ALUOp)
            2'b00: alu_control = ADD_UNSIGNED; // Memory access operations use unsigned addition
            
            2'b01: begin // Branch operations
                case (funct3)
                    3'b000: alu_control = EQ_OP;  // BEQ
                    3'b001: alu_control = NE_OP;  // BNE
                    3'b100: alu_control = LT_SIGNED;    // BLT
                    3'b101: alu_control = GE_SIGNED;    // BGE
                    3'b110: alu_control = LT_UNSIGNED;  // BLTU
                    3'b111: alu_control = GE_UNSIGNED;  // BGEU
                    default: alu_control = SUB_UNSIGNED; // Default for branch
                endcase
            end
            
            2'b10: begin // R-type instructions
                case (funct3)
                    F3_ADD_SUB: begin
                        if (funct7 == F7_DEFAULT)
                            alu_control = ADD_SIGNED;   // ADD
                        else if (funct7 == F7_SUB_SRA)
                            alu_control = SUB_SIGNED;   // SUB
                        else if (funct7 == F7_MUL_DIV)
                            alu_control = MUL_SIGNED;   // MUL (M extension)
                        else
                            alu_control = ADD_SIGNED;   // Default to ADD
                    end
                    
                    F3_SLL: alu_control = SLL_OP;      // SLL
                    
                    F3_SLT: alu_control = LT_SIGNED;   // SLT
                    
                    F3_SLTU: alu_control = LT_UNSIGNED; // SLTU
                    
                    F3_XOR: begin
                        if (funct7 == F7_MUL_DIV)
                            alu_control = DIV_SIGNED;   // DIV (M extension)
                        else
                            alu_control = XOR_OP;       // XOR
                    end
                    
                    F3_SRL_SRA: begin
                        if (funct7 == F7_DEFAULT)
                            alu_control = SRL_OP;       // SRL
                        else if (funct7 == F7_SUB_SRA)
                            alu_control = SRA_OP;       // SRA
                        else
                            alu_control = SRL_OP;       // Default to SRL
                    end
                    
                    F3_OR: alu_control = OR_OP;        // OR
                    
                    F3_AND: alu_control = AND_OP;      // AND
                    
                    default: alu_control = ADD_SIGNED;  // Default to ADD
                endcase
            end
            
            2'b11: begin // I-type instructions
                case (funct3)
                    F3_ADD_SUB: alu_control = ADD_SIGNED;   // ADDI
                    
                    F3_SLL: alu_control = SLL_OP;      // SLLI
                    
                    F3_SLT: alu_control = LT_SIGNED;   // SLTI
                    
                    F3_SLTU: alu_control = LT_UNSIGNED; // SLTIU
                    
                    F3_XOR: alu_control = XOR_OP;      // XORI
                    
                    F3_SRL_SRA: begin
                        if (funct7[5]) // Check bit 5 of funct7 for I-type shift instructions
                            alu_control = SRA_OP;       // SRAI
                        else
                            alu_control = SRL_OP;       // SRLI
                    end
                    
                    F3_OR: alu_control = OR_OP;        // ORI
                    
                    F3_AND: alu_control = AND_OP;      // ANDI
                    
                    default: alu_control = ADD_SIGNED;  // Default to ADD
                endcase
            end
            
            default: alu_control = ADD_UNSIGNED;        // Default operation
        endcase
    end

endmodule

ALU_Control_Unit/ALU_control_unit_tb.v
`timescale 1ns / 1ps

module ALU_control_unit_tb;
    // Parameters
    parameter CLK_PERIOD = 10; // 10ns = 100MHz

    // Inputs
    reg [1:0] ALUOp;
    reg [2:0] funct3;
    reg [6:0] funct7;

    // Outputs
    wire [4:0] alu_control;

    // Clock generation
    reg clk = 0;
    always #(CLK_PERIOD/2) clk = ~clk;

    // Instantiate the Unit Under Test (UUT)
    ALU_control_unit uut (
        .ALUOp(ALUOp),
        .funct3(funct3),
        .funct7(funct7),
        .alu_control(alu_control)
    );

    // VCD file generation for GTKWave
    initial begin
        // Create VCD file for waveform viewing
        $dumpfile("alu_control_unit_waveform.vcd");
        // Dump all variables at all levels
        $dumpvars(0, ALU_control_unit_tb);
    end

    // ALU operations (matching ALU module)
    // Arithmetic Operations
    localparam ADD_UNSIGNED = 5'b00000;
    localparam ADD_SIGNED   = 5'b00001;
    localparam SUB_UNSIGNED = 5'b00100;
    localparam SUB_SIGNED   = 5'b00101;
    localparam MUL_UNSIGNED = 5'b01000;
    localparam MUL_SIGNED   = 5'b01001;
    localparam DIV_UNSIGNED = 5'b01100;
    localparam DIV_SIGNED   = 5'b01101;

    // Logic Operations
    localparam AND_OP       = 5'b10000;
    localparam OR_OP        = 5'b10001;
    localparam XOR_OP       = 5'b10010;
    localparam NOT_OP       = 5'b10011;
    localparam SLL_OP       = 5'b10100;
    localparam SRL_OP       = 5'b10101;
    localparam SRA_OP       = 5'b10110;
    localparam NOR_OP       = 5'b10111;
    localparam EQ_OP        = 5'b11000;
    localparam NE_OP        = 5'b11001;
    localparam LT_SIGNED    = 5'b11010;
    localparam GE_SIGNED    = 5'b11011;
    localparam LT_UNSIGNED  = 5'b11100;
    localparam GE_UNSIGNED  = 5'b11101;

    // Test case counter and expected results
    integer test_case;
    reg [4:0] expected_control;

    // Task to display test results
    task display_test_result;
        input [8*30:1] test_name;
        begin
            $display("Test Case %0d: %s", test_case, test_name);
            $display("  ALUOp = %b, funct3 = %b, funct7 = %b", ALUOp, funct3, funct7);
            $display("  Expected: alu_control = %b", expected_control);
            $display("  Actual:   alu_control = %b", alu_control);
            
            if (alu_control !== expected_control) begin
                $display("  TEST FAILED!");
            end else begin
                $display("  Test passed.");
            end
            $display("--------------------------------------");
        end
    endtask

    // Main test procedure
    initial begin
        // Initialize inputs
        ALUOp = 2'b00;
        funct3 = 3'b000;
        funct7 = 7'b0000000;
        test_case = 0;

        // Wait for global reset
        #100;

        // Test 1: Memory access operation (load/store)
        test_case = test_case + 1;
        ALUOp = 2'b00;
        funct3 = 3'b000;
        funct7 = 7'b0000000;
        expected_control = ADD_UNSIGNED;
        #20;
        display_test_result("Memory Access Operation");

        // Test 2: Branch operation - BEQ
        test_case = test_case + 1;
        ALUOp = 2'b01;
        funct3 = 3'b000; // BEQ
        funct7 = 7'b0000000;
        expected_control = EQ_OP;
        #20;
        display_test_result("Branch - BEQ");

        // Test 3: Branch operation - BNE
        test_case = test_case + 1;
        ALUOp = 2'b01;
        funct3 = 3'b001; // BNE
        funct7 = 7'b0000000;
        expected_control = NE_OP;
        #20;
        display_test_result("Branch - BNE");

        // Test 4: Branch operation - BLT
        test_case = test_case + 1;
        ALUOp = 2'b01;
        funct3 = 3'b100; // BLT
        funct7 = 7'b0000000;
        expected_control = LT_SIGNED;
        #20;
        display_test_result("Branch - BLT");

        // Test 5: Branch operation - BGE
        test_case = test_case + 1;
        ALUOp = 2'b01;
        funct3 = 3'b101; // BGE
        funct7 = 7'b0000000;
        expected_control = GE_SIGNED;
        #20;
        display_test_result("Branch - BGE");

        // Test 6: Branch operation - BLTU
        test_case = test_case + 1;
        ALUOp = 2'b01;
        funct3 = 3'b110; // BLTU
        funct7 = 7'b0000000;
        expected_control = LT_UNSIGNED;
        #20;
        display_test_result("Branch - BLTU");

        // Test 7: Branch operation - BGEU
        test_case = test_case + 1;
        ALUOp = 2'b01;
        funct3 = 3'b111; // BGEU
        funct7 = 7'b0000000;
        expected_control = GE_UNSIGNED;
        #20;
        display_test_result("Branch - BGEU");

        // Test 8: R-type - ADD
        test_case = test_case + 1;
        ALUOp = 2'b10;
        funct3 = 3'b000; // ADD/SUB
        funct7 = 7'b0000000; // ADD
        expected_control = ADD_SIGNED;
        #20;
        display_test_result("R-type - ADD");

        // Test 9: R-type - SUB
        test_case = test_case + 1;
        ALUOp = 2'b10;
        funct3 = 3'b000; // ADD/SUB
        funct7 = 7'b0100000; // SUB
        expected_control = SUB_SIGNED;
        #20;
        display_test_result("R-type - SUB");

        // Test 10: R-type - SLL
        test_case = test_case + 1;
        ALUOp = 2'b10;
        funct3 = 3'b001; // SLL
        funct7 = 7'b0000000;
        expected_control = SLL_OP;
        #20;
        display_test_result("R-type - SLL");

        // Test 11: R-type - SLT
        test_case = test_case + 1;
        ALUOp = 2'b10;
        funct3 = 3'b010; // SLT
        funct7 = 7'b0000000;
        expected_control = LT_SIGNED;
        #20;
        display_test_result("R-type - SLT");

        // Test 12: R-type - SLTU
        test_case = test_case + 1;
        ALUOp = 2'b10;
        funct3 = 3'b011; // SLTU
        funct7 = 7'b0000000;
        expected_control = LT_UNSIGNED;
        #20;
        display_test_result("R-type - SLTU");

        // Test 13: R-type - XOR
        test_case = test_case + 1;
        ALUOp = 2'b10;
        funct3 = 3'b100; // XOR
        funct7 = 7'b0000000;
        expected_control = XOR_OP;
        #20;
        display_test_result("R-type - XOR");

        // Test 14: R-type - SRL
        test_case = test_case + 1;
        ALUOp = 2'b10;
        funct3 = 3'b101; // SRL/SRA
        funct7 = 7'b0000000; // SRL
        expected_control = SRL_OP;
        #20;
        display_test_result("R-type - SRL");

        // Test 15: R-type - SRA
        test_case = test_case + 1;
        ALUOp = 2'b10;
        funct3 = 3'b101; // SRL/SRA
        funct7 = 7'b0100000; // SRA
        expected_control = SRA_OP;
        #20;
        display_test_result("R-type - SRA");

        // Test 16: R-type - OR
        test_case = test_case + 1;
        ALUOp = 2'b10;
        funct3 = 3'b110; // OR
        funct7 = 7'b0000000;
        expected_control = OR_OP;
        #20;
        display_test_result("R-type - OR");

        // Test 17: R-type - AND
        test_case = test_case + 1;
        ALUOp = 2'b10;
        funct3 = 3'b111; // AND
        funct7 = 7'b0000000;
        expected_control = AND_OP;
        #20;
        display_test_result("R-type - AND");

        // Test 18: I-type - ADDI
        test_case = test_case + 1;
        ALUOp = 2'b11;
        funct3 = 3'b000; // ADDI
        funct7 = 7'b0000000; // Don't care for I-type
        expected_control = ADD_SIGNED;
        #20;
        display_test_result("I-type - ADDI");

        // Test 19: I-type - SLTI
        test_case = test_case + 1;
        ALUOp = 2'b11;
        funct3 = 3'b010; // SLTI
        funct7 = 7'b0000000; // Don't care for I-type
        expected_control = LT_SIGNED;
        #20;
        display_test_result("I-type - SLTI");

        // Test 20: I-type - SLTIU
        test_case = test_case + 1;
        ALUOp = 2'b11;
        funct3 = 3'b011; // SLTIU
        funct7 = 7'b0000000; // Don't care for I-type
        expected_control = LT_UNSIGNED;
        #20;
        display_test_result("I-type - SLTIU");

        // Test 21: I-type - XORI
        test_case = test_case + 1;
        ALUOp = 2'b11;
        funct3 = 3'b100; // XORI
        funct7 = 7'b0000000; // Don't care for I-type
        expected_control = XOR_OP;
        #20;
        display_test_result("I-type - XORI");

        // Test 22: I-type - ORI
        test_case = test_case + 1;
        ALUOp = 2'b11;
        funct3 = 3'b110; // ORI
        funct7 = 7'b0000000; // Don't care for I-type
        expected_control = OR_OP;
        #20;
        display_test_result("I-type - ORI");

        // Test 23: I-type - ANDI
        test_case = test_case + 1;
        ALUOp = 2'b11;
        funct3 = 3'b111; // ANDI
        funct7 = 7'b0000000; // Don't care for I-type
        expected_control = AND_OP;
        #20;
        display_test_result("I-type - ANDI");

        // Test 24: I-type - SLLI
        test_case = test_case + 1;
        ALUOp = 2'b11;
        funct3 = 3'b001; // SLLI
        funct7 = 7'b0000000; // Don't care for I-type
        expected_control = SLL_OP;
        #20;
        display_test_result("I-type - SLLI");

        // Test 25: I-type - SRLI
        test_case = test_case + 1;
        ALUOp = 2'b11;
        funct3 = 3'b101; // SRLI/SRAI
        funct7 = 7'b0000000; // SRLI (bit 5 = 0)
        expected_control = SRL_OP;
        #20;
        display_test_result("I-type - SRLI");

        // Test 26: I-type - SRAI
        test_case = test_case + 1;
        ALUOp = 2'b11;
        funct3 = 3'b101; // SRLI/SRAI
        funct7 = 7'b0100000; // SRAI (bit 5 = 1)
        expected_control = SRA_OP;
        #20;
        display_test_result("I-type - SRAI");

        // Test 27: R-type - MUL (M extension)
        test_case = test_case + 1;
        ALUOp = 2'b10;
        funct3 = 3'b000; // MUL
        funct7 = 7'b0000001; // M extension
        expected_control = MUL_SIGNED;
        #20;
        display_test_result("R-type - MUL (M extension)");

        // Test 28: R-type - DIV (M extension)
        test_case = test_case + 1;
        ALUOp = 2'b10;
        funct3 = 3'b100; // DIV
        funct7 = 7'b0000001; // M extension
        expected_control = DIV_SIGNED;
        #20;
        display_test_result("R-type - DIV (M extension)");

        // Finish simulation
        $display("All tests completed!");
        #(CLK_PERIOD*2);
        $finish;
    end

endmodule

ALU_Control_Unit/alu_control_unit_waveform.vcd
$date
	Fri Jun 20 13:44:28 2025
$end
$version
	Icarus Verilog
$end
$timescale
	1ps
$end
$scope module ALU_control_unit_tb $end
$var wire 5 ! alu_control [4:0] $end
$var parameter 5 " ADD_SIGNED $end
$var parameter 5 # ADD_UNSIGNED $end
$var parameter 5 $ AND_OP $end
$var parameter 32 % CLK_PERIOD $end
$var parameter 5 & DIV_SIGNED $end
$var parameter 5 ' DIV_UNSIGNED $end
$var parameter 5 ( EQ_OP $end
$var parameter 5 ) GE_SIGNED $end
$var parameter 5 * GE_UNSIGNED $end
$var parameter 5 + LT_SIGNED $end
$var parameter 5 , LT_UNSIGNED $end
$var parameter 5 - MUL_SIGNED $end
$var parameter 5 . MUL_UNSIGNED $end
$var parameter 5 / NE_OP $end
$var parameter 5 0 NOR_OP $end
$var parameter 5 1 NOT_OP $end
$var parameter 5 2 OR_OP $end
$var parameter 5 3 SLL_OP $end
$var parameter 5 4 SRA_OP $end
$var parameter 5 5 SRL_OP $end
$var parameter 5 6 SUB_SIGNED $end
$var parameter 5 7 SUB_UNSIGNED $end
$var parameter 5 8 XOR_OP $end
$var reg 2 9 ALUOp [1:0] $end
$var reg 1 : clk $end
$var reg 5 ; expected_control [4:0] $end
$var reg 3 < funct3 [2:0] $end
$var reg 7 = funct7 [6:0] $end
$var integer 32 > test_case [31:0] $end
$scope module uut $end
$var wire 2 ? ALUOp [1:0] $end
$var wire 3 @ funct3 [2:0] $end
$var wire 7 A funct7 [6:0] $end
$var parameter 5 B ADD_SIGNED $end
$var parameter 5 C ADD_UNSIGNED $end
$var parameter 5 D AND_OP $end
$var parameter 5 E DIV_SIGNED $end
$var parameter 5 F DIV_UNSIGNED $end
$var parameter 5 G EQ_OP $end
$var parameter 3 H F3_ADD_SUB $end
$var parameter 3 I F3_AND $end
$var parameter 3 J F3_OR $end
$var parameter 3 K F3_SLL $end
$var parameter 3 L F3_SLT $end
$var parameter 3 M F3_SLTU $end
$var parameter 3 N F3_SRL_SRA $end
$var parameter 3 O F3_XOR $end
$var parameter 7 P F7_DEFAULT $end
$var parameter 7 Q F7_MUL_DIV $end
$var parameter 7 R F7_SUB_SRA $end
$var parameter 5 S GE_SIGNED $end
$var parameter 5 T GE_UNSIGNED $end
$var parameter 5 U LT_SIGNED $end
$var parameter 5 V LT_UNSIGNED $end
$var parameter 5 W MUL_SIGNED $end
$var parameter 5 X MUL_UNSIGNED $end
$var parameter 5 Y NE_OP $end
$var parameter 5 Z NOR_OP $end
$var parameter 5 [ NOT_OP $end
$var parameter 5 \ OR_OP $end
$var parameter 5 ] SLL_OP $end
$var parameter 5 ^ SRA_OP $end
$var parameter 5 _ SRL_OP $end
$var parameter 5 ` SUB_SIGNED $end
$var parameter 5 a SUB_UNSIGNED $end
$var parameter 5 b XOR_OP $end
$var reg 5 c alu_control [4:0] $end
$upscope $end
$scope task display_test_result $end
$var reg 240 d test_name [240:1] $end
$upscope $end
$upscope $end
$enddefinitions $end
$comment Show the parameter values. $end
$dumpall
b10010 b
b100 a
b101 `
b10101 _
b10110 ^
b10100 ]
b10001 \
b10011 [
b10111 Z
b11001 Y
b1000 X
b1001 W
b11100 V
b11010 U
b11101 T
b11011 S
b100000 R
b1 Q
b0 P
b100 O
b101 N
b11 M
b10 L
b1 K
b110 J
b111 I
b0 H
b11000 G
b1100 F
b1101 E
b10000 D
b0 C
b1 B
b10010 8
b100 7
b101 6
b10101 5
b10110 4
b10100 3
b10001 2
b10011 1
b10111 0
b11001 /
b1000 .
b1001 -
b11100 ,
b11010 +
b11101 *
b11011 )
b11000 (
b1100 '
b1101 &
b1010 %
b10000 $
b0 #
b1 "
$end
#0
$dumpvars
bx d
b0 c
b0 A
b0 @
b0 ?
b0 >
b0 =
b0 <
bx ;
0:
b0 9
b0 !
$end
#5000
1:
#10000
0:
#15000
1:
#20000
0:
#25000
1:
#30000
0:
#35000
1:
#40000
0:
#45000
1:
#50000
0:
#55000
1:
#60000
0:
#65000
1:
#70000
0:
#75000
1:
#80000
0:
#85000
1:
#90000
0:
#95000
1:
#100000
0:
b0 ;
b1 >
#105000
1:
#110000
0:
#115000
1:
#120000
b11000 !
b11000 c
0:
b11000 ;
b1 9
b1 ?
b10 >
b100110101100101011011010110111101110010011110010010000001000001011000110110001101100101011100110111001100100000010011110111000001100101011100100110000101110100011010010110111101101110 d
#125000
1:
#130000
0:
#135000
1:
#140000
b11001 !
b11001 c
0:
b11001 ;
b1 <
b1 @
b11 >
b10000100111001001100001011011100110001101101000001000000010110100100000010000100100010101010001 d
#145000
1:
#150000
0:
#155000
1:
#160000
b11010 !
b11010 c
0:
b11010 ;
b100 <
b100 @
b100 >
b10000100111001001100001011011100110001101101000001000000010110100100000010000100100111001000101 d
#165000
1:
#170000
0:
#175000
1:
#180000
b11011 !
b11011 c
0:
b11011 ;
b101 <
b101 @
b101 >
b10000100111001001100001011011100110001101101000001000000010110100100000010000100100110001010100 d
#185000
1:
#190000
0:
#195000
1:
#200000
b11100 !
b11100 c
0:
b11100 ;
b110 <
b110 @
b110 >
b10000100111001001100001011011100110001101101000001000000010110100100000010000100100011101000101 d
#205000
1:
#210000
0:
#215000
1:
#220000
b11101 !
b11101 c
0:
b11101 ;
b111 <
b111 @
b111 >
b1000010011100100110000101101110011000110110100000100000001011010010000001000010010011000101010001010101 d
#225000
1:
#230000
0:
#235000
1:
#240000
b1 !
b1 c
0:
b1 ;
b0 <
b0 @
b10 9
b10 ?
b1000 >
b1000010011100100110000101101110011000110110100000100000001011010010000001000010010001110100010101010101 d
#245000
1:
#250000
0:
#255000
1:
#260000
b101 !
b101 c
0:
b101 ;
b100000 =
b100000 A
b1001 >
b10100100010110101110100011110010111000001100101001000000010110100100000010000010100010001000100 d
#265000
1:
#270000
0:
#275000
1:
#280000
b10100 !
b10100 c
0:
b10100 ;
b0 =
b0 A
b1 <
b1 @
b1010 >
b10100100010110101110100011110010111000001100101001000000010110100100000010100110101010101000010 d
#285000
1:
#290000
0:
#295000
1:
#300000
b11010 !
b11010 c
0:
b11010 ;
b10 <
b10 @
b1011 >
b10100100010110101110100011110010111000001100101001000000010110100100000010100110100110001001100 d
#305000
1:
#310000
0:
#315000
1:
#320000
b11100 !
b11100 c
0:
b11100 ;
b11 <
b11 @
b1100 >
b10100100010110101110100011110010111000001100101001000000010110100100000010100110100110001010100 d
#325000
1:
#330000
0:
#335000
1:
#340000
b10010 !
b10010 c
0:
b10010 ;
b100 <
b100 @
b1101 >
b1010010001011010111010001111001011100000110010100100000001011010010000001010011010011000101010001010101 d
#345000
1:
#350000
0:
#355000
1:
#360000
b10101 !
b10101 c
0:
b10101 ;
b101 <
b101 @
b1110 >
b10100100010110101110100011110010111000001100101001000000010110100100000010110000100111101010010 d
#365000
1:
#370000
0:
#375000
1:
#380000
b10110 !
b10110 c
0:
b10110 ;
b100000 =
b100000 A
b1111 >
b10100100010110101110100011110010111000001100101001000000010110100100000010100110101001001001100 d
#385000
1:
#390000
0:
#395000
1:
#400000
b10001 !
b10001 c
0:
b10001 ;
b0 =
b0 A
b110 <
b110 @
b10000 >
b10100100010110101110100011110010111000001100101001000000010110100100000010100110101001001000001 d
#405000
1:
#410000
0:
#415000
1:
#420000
b10000 !
b10000 c
0:
b10000 ;
b111 <
b111 @
b10001 >
b101001000101101011101000111100101110000011001010010000000101101001000000100111101010010 d
#425000
1:
#430000
0:
#435000
1:
#440000
b1 !
b1 c
0:
b1 ;
b0 <
b0 @
b11 9
b11 ?
b10010 >
b10100100010110101110100011110010111000001100101001000000010110100100000010000010100111001000100 d
#445000
1:
#450000
0:
#455000
1:
#460000
b11010 !
b11010 c
0:
b11010 ;
b10 <
b10 @
b10011 >
b1001001001011010111010001111001011100000110010100100000001011010010000001000001010001000100010001001001 d
#465000
1:
#470000
0:
#475000
1:
#480000
b11100 !
b11100 c
0:
b11100 ;
b11 <
b11 @
b10100 >
b1001001001011010111010001111001011100000110010100100000001011010010000001010011010011000101010001001001 d
#485000
1:
#490000
0:
#495000
1:
#500000
b10010 !
b10010 c
0:
b10010 ;
b100 <
b100 @
b10101 >
b100100100101101011101000111100101110000011001010010000000101101001000000101001101001100010101000100100101010101 d
#505000
1:
#510000
0:
#515000
1:
#520000
b10001 !
b10001 c
0:
b10001 ;
b110 <
b110 @
b10110 >
b1001001001011010111010001111001011100000110010100100000001011010010000001011000010011110101001001001001 d
#525000
1:
#530000
0:
#535000
1:
#540000
b10000 !
b10000 c
0:
b10000 ;
b111 <
b111 @
b10111 >
b10010010010110101110100011110010111000001100101001000000010110100100000010011110101001001001001 d
#545000
1:
#550000
0:
#555000
1:
#560000
b10100 !
b10100 c
0:
b10100 ;
b1 <
b1 @
b11000 >
b1001001001011010111010001111001011100000110010100100000001011010010000001000001010011100100010001001001 d
#565000
1:
#570000
0:
#575000
1:
#580000
b10101 !
b10101 c
0:
b10101 ;
b101 <
b101 @
b11001 >
b1001001001011010111010001111001011100000110010100100000001011010010000001010011010011000100110001001001 d
#585000
1:
#590000
0:
#595000
1:
#600000
b10110 !
b10110 c
0:
b10110 ;
b100000 =
b100000 A
b11010 >
b1001001001011010111010001111001011100000110010100100000001011010010000001010011010100100100110001001001 d
#605000
1:
#610000
0:
#615000
1:
#620000
b1001 !
b1001 c
0:
b1001 ;
b1 =
b1 A
b0 <
b0 @
b10 9
b10 ?
b11011 >
b1001001001011010111010001111001011100000110010100100000001011010010000001010011010100100100000101001001 d
#625000
1:
#630000
0:
#635000
1:
#640000
b1101 !
b1101 c
0:
b1101 ;
b100 <
b100 @
b11100 >
b101001000101101011101000111100101110000011001010010000000101101001000000100110101010101010011000010000000101000010011010010000001100101011110000111010001100101011011100111001101101001011011110110111000101001 d
#645000
1:
#650000
0:
#655000
1:
#660000
0:
b101001000101101011101000111100101110000011001010010000000101101001000000100010001001001010101100010000000101000010011010010000001100101011110000111010001100101011011100111001101101001011011110110111000101001 d
