Instruction_Register/Instruction_Register.v
module Instruction_Register (
    input wire clk,
    input wire reset,
    input wire ir_write,
    input wire [31:0] instruction_in,
    output wire [31:0] instruction_out,
    output wire [6:0] opcode,
    output wire [4:0] rd,
    output wire [4:0] rs1,
    output wire [4:0] rs2,
    output wire [2:0] funct3,
    output wire [6:0] funct7
);

    // Internal register to store the instruction
    reg [31:0] instruction_reg;

    // Synchronous update of instruction register
    always @(posedge clk or posedge reset) begin
        if (reset) begin
            instruction_reg <= 32'h0; // Reset to NOP instruction
        end else if (ir_write) begin
            instruction_reg <= instruction_in; // Update when ir_write is enabled
        end
    end

    // Output the full instruction
    assign instruction_out = instruction_reg;

    // Decode instruction fields based on RISC-V format
    // RISC-V instruction format: [31:25](funct7) [24:20](rs2) [19:15](rs1) [14:12](funct3) [11:7](rd) [6:0](opcode)
    assign opcode = instruction_reg[6:0];
    assign rd = instruction_reg[11:7];
    assign rs1 = instruction_reg[19:15];
    assign rs2 = instruction_reg[24:20];
    assign funct3 = instruction_reg[14:12];
    assign funct7 = instruction_reg[31:25];

endmodule

Instruction_Register/Instruction_Register_tb.v
module Instruction_Register_tb;
    // Parameters
    parameter CLK_PERIOD = 10; // 10ns clock period (100MHz)
    
    // Inputs
    reg clk;
    reg reset;
    reg ir_write;
    reg [31:0] instruction_in;
    
    // Outputs
    wire [31:0] instruction_out;
    wire [6:0] opcode;
    wire [4:0] rd;
    wire [4:0] rs1;
    wire [4:0] rs2;
    wire [2:0] funct3;
    wire [6:0] funct7;
    
    // Instantiate the Instruction Register
    Instruction_Register dut (
        .clk(clk),
        .reset(reset),
        .ir_write(ir_write),
        .instruction_in(instruction_in),
        .instruction_out(instruction_out),
        .opcode(opcode),
        .rd(rd),
        .rs1(rs1),
        .rs2(rs2),
        .funct3(funct3),
        .funct7(funct7)
    );
    
    // Clock generation
    initial begin
        clk = 0;
        forever #(CLK_PERIOD/2) clk = ~clk;
    end
    
    // Test sequence
    initial begin
        // Initialize inputs
        reset = 1;
        ir_write = 0;
        instruction_in = 32'h0;
        
        // Apply reset
        #(CLK_PERIOD*2);
        reset = 0;
        #CLK_PERIOD;
        
        // Test 1: Write R-type instruction (add x1, x2, x3)
        // R-type format: funct7 rs2 rs1 funct3 rd opcode
        // For add x1, x2, x3: funct7=0000000, rs2=00011(3), rs1=00010(2), funct3=000, rd=00001(1), opcode=0110011
        ir_write = 1;
        instruction_in = 32'h003100B3; // add x1, x2, x3 - correct encoding
        #CLK_PERIOD;
        ir_write = 0;
        #CLK_PERIOD;
        
        // Verify instruction fields
        if (instruction_out !== 32'h003100B3) begin
            $display("Test 1 Failed: instruction_out = %h, expected = %h", instruction_out, 32'h003100B3);
        end else begin
            $display("Test 1 Passed: instruction_out = %h", instruction_out);
        end
        
        if (opcode !== 7'b0110011) begin
            $display("Test 1 Failed: opcode = %b, expected = %b", opcode, 7'b0110011);
        end else begin
            $display("Test 1 Passed: opcode = %b", opcode);
        end
        
        if (rd !== 5'd1) begin
            $display("Test 1 Failed: rd = %d, expected = %d", rd, 5'd1);
        end else begin
            $display("Test 1 Passed: rd = %d", rd);
        end
        
        if (rs1 !== 5'd2) begin
            $display("Test 1 Failed: rs1 = %d, expected = %d", rs1, 5'd2);
        end else begin
            $display("Test 1 Passed: rs1 = %d", rs1);
        end
        
        if (rs2 !== 5'd3) begin
            $display("Test 1 Failed: rs2 = %d, expected = %d", rs2, 5'd3);
        end else begin
            $display("Test 1 Passed: rs2 = %d", rs2);
        end
        
        if (funct3 !== 3'b000) begin
            $display("Test 1 Failed: funct3 = %b, expected = %b", funct3, 3'b000);
        end else begin
            $display("Test 1 Passed: funct3 = %b", funct3);
        end
        
        if (funct7 !== 7'b0000000) begin
            $display("Test 1 Failed: funct7 = %b, expected = %b", funct7, 7'b0000000);
        end else begin
            $display("Test 1 Passed: funct7 = %b", funct7);
        end
        
        // Test 2: Write I-type instruction (addi x4, x5, 42)
        // addi instruction: imm[11:0] rs1 funct3 rd opcode
        // 000000101010 00101 000 00100 0010011
        ir_write = 1;
        instruction_in = 32'h02A28213; // addi x4, x5, 42
        #CLK_PERIOD;
        ir_write = 0;
        #CLK_PERIOD;
        
        // Verify instruction fields
        if (opcode !== 7'b0010011) begin
            $display("Test 2 Failed: opcode = %b, expected = %b", opcode, 7'b0010011);
        end else begin
            $display("Test 2 Passed: opcode = %b", opcode);
        end
        
        if (rd !== 5'd4) begin
            $display("Test 2 Failed: rd = %d, expected = %d", rd, 5'd4);
        end else begin
            $display("Test 2 Passed: rd = %d", rd);
        end
        
        if (rs1 !== 5'd5) begin
            $display("Test 2 Failed: rs1 = %d, expected = %d", rs1, 5'd5);
        end else begin
            $display("Test 2 Passed: rs1 = %d", rs1);
        end
        
        if (funct3 !== 3'b000) begin
            $display("Test 2 Failed: funct3 = %b, expected = %b", funct3, 3'b000);
        end else begin
            $display("Test 2 Passed: funct3 = %b", funct3);
        end
        
        // Test 3: Test ir_write control (should not update when ir_write=0)
        ir_write = 0;
        instruction_in = 32'hFFFFFFFF;
        #CLK_PERIOD;
        
        // Verify instruction didn't change
        if (instruction_out !== 32'h02A28213) begin
            $display("Test 3 Failed: instruction_out = %h, expected = %h", instruction_out, 32'h02A28213);
        end else begin
            $display("Test 3 Passed: instruction didn't change when ir_write=0");
        end
        
        // Test 4: Write S-type instruction (sw x6, 8(x7))
        // S-type: imm[11:5] rs2 rs1 funct3 imm[4:0] opcode
        // S-type format: imm[11:5] rs2 rs1 funct3 imm[4:0] opcode
        // For sw x6, 8(x7): imm=8 (000000001000), rs2=6, rs1=7, funct3=010, opcode=0100011
        // imm[11:5]=0000000, rs2=00110, rs1=00111, funct3=010, imm[4:0]=01000, opcode=0100011
        ir_write = 1;
        instruction_in = 32'h0063A423; // sw x6, 8(x7) - correct encoding
        #CLK_PERIOD;
        ir_write = 0;
        #CLK_PERIOD;
        
        // Verify instruction fields
        if (opcode !== 7'b0100011) begin
            $display("Test 4 Failed: opcode = %b, expected = %b", opcode, 7'b0100011);
        end else begin
            $display("Test 4 Passed: opcode = %b", opcode);
        end
        
        if (rs1 !== 5'd7) begin
            $display("Test 4 Failed: rs1 = %d, expected = %d", rs1, 5'd7);
        end else begin
            $display("Test 4 Passed: rs1 = %d", rs1);
        end
        
        if (rs2 !== 5'd6) begin
            $display("Test 4 Failed: rs2 = %d, expected = %d", rs2, 5'd6);
        end else begin
            $display("Test 4 Passed: rs2 = %d", rs2);
        end
        
        if (funct3 !== 3'b010) begin
            $display("Test 4 Failed: funct3 = %b, expected = %b", funct3, 3'b010);
        end else begin
            $display("Test 4 Passed: funct3 = %b", funct3);
        end
        
        // Test 5: Reset test
        reset = 1;
        #CLK_PERIOD;
        reset = 0;
        #CLK_PERIOD;
        
        // Verify registers are reset to 0
        if (instruction_out !== 32'h0) begin
            $display("Test 5 Failed: After reset, instruction_out = %h, expected = %h", instruction_out, 32'h0);
        end else begin
            $display("Test 5 Passed: instruction_out reset to 0");
        end
        
        $display("All tests completed");
        $finish;
    end
    
    // Optional: Generate VCD file for waveform viewing
    initial begin
        $dumpfile("instruction_register_waveform.vcd");
        $dumpvars(0, Instruction_Register_tb);
    end
    
endmodule

Instruction_Register/instruction_register_waveform.vcd
$date
	Fri Jun 20 22:03:59 2025
$end
$version
	Icarus Verilog
$end
$timescale
	1s
$end
$scope module Instruction_Register_tb $end
$var wire 5 ! rs2 [4:0] $end
$var wire 5 " rs1 [4:0] $end
$var wire 5 # rd [4:0] $end
$var wire 7 $ opcode [6:0] $end
$var wire 32 % instruction_out [31:0] $end
$var wire 7 & funct7 [6:0] $end
$var wire 3 ' funct3 [2:0] $end
$var parameter 32 ( CLK_PERIOD $end
$var reg 1 ) clk $end
$var reg 32 * instruction_in [31:0] $end
$var reg 1 + ir_write $end
$var reg 1 , reset $end
$scope module dut $end
$var wire 1 ) clk $end
$var wire 32 - instruction_in [31:0] $end
$var wire 32 . instruction_out [31:0] $end
$var wire 1 + ir_write $end
$var wire 1 , reset $end
$var wire 5 / rs2 [4:0] $end
$var wire 5 0 rs1 [4:0] $end
$var wire 5 1 rd [4:0] $end
$var wire 7 2 opcode [6:0] $end
$var wire 7 3 funct7 [6:0] $end
$var wire 3 4 funct3 [2:0] $end
$var reg 32 5 instruction_reg [31:0] $end
$upscope $end
$upscope $end
$enddefinitions $end
$comment Show the parameter values. $end
$dumpall
b1010 (
$end
#0
$dumpvars
b0 5
b0 4
b0 3
b0 2
b0 1
b0 0
b0 /
b0 .
b0 -
1,
0+
b0 *
0)
b0 '
b0 &
b0 %
b0 $
b0 #
b0 "
b0 !
$end
#5
1)
#10
0)
#15
1)
#20
0)
0,
#25
1)
#30
0)
b1100010000000010110011 *
b1100010000000010110011 -
1+
#35
b110011 $
b110011 2
b1 #
b1 1
b10 "
b10 0
b11 !
b11 /
b1100010000000010110011 %
b1100010000000010110011 .
b1100010000000010110011 5
1)
#40
0)
0+
#45
1)
#50
0)
b10101000101000001000010011 *
b10101000101000001000010011 -
1+
#55
b10011 $
b10011 2
b100 #
b100 1
b101 "
b101 0
b1010 !
b1010 /
b1 &
b1 3
b10101000101000001000010011 %
b10101000101000001000010011 .
b10101000101000001000010011 5
1)
#60
0)
0+
#65
1)
#70
0)
b11111111111111111111111111111111 *
b11111111111111111111111111111111 -
#75
1)
#80
0)
b11000111010010000100011 *
b11000111010010000100011 -
1+
#85
b100011 $
b100011 2
b1000 #
b1000 1
b111 "
b111 0
b110 !
b110 /
b10 '
b10 4
b0 &
b0 3
b11000111010010000100011 %
b11000111010010000100011 .
b11000111010010000100011 5
1)
#90
0)
0+
#95
1)
#100
b0 $
b0 2
b0 #
b0 1
b0 "
b0 0
b0 !
b0 /
b0 '
b0 4
b0 %
b0 .
b0 5
0)
1,
#105
1)
#110
0)
0,
