ALU_Output_Register/ALU_output_register.v
module ALU_output_register (
    input wire clk,              // Clock signal
    input wire reset,            // Reset signal
    input wire alu_out_write,    // Write enable signal
    input wire [31:0] result,    // Result input from ALU (renamed from result_in to match ALU output)
    output reg [31:0] result_out // Result output
);

    // Update the register on positive clock edge when write is enabled
    always @(posedge clk) begin
        if (reset) begin
            // Reset the register to 0
            result_out <= 32'b0;
        end else if (alu_out_write) begin
            // Store the ALU result when write is enabled
            result_out <= result;
        end
        // Otherwise, maintain the current value
    end

endmodule

ALU_Output_Register/ALU_output_register_tb.v
`timescale 1ns / 1ps

module ALU_output_register_tb;
    // Parameters
    parameter WIDTH = 32;
    parameter CLK_PERIOD = 10; // 10ns = 100MHz

    // Inputs
    reg clk;
    reg reset;
    reg alu_out_write;
    reg [WIDTH-1:0] result;

    // Outputs
    wire [WIDTH-1:0] result_out;

    // Clock generation
    always #(CLK_PERIOD/2) clk = ~clk;

    // Instantiate the Unit Under Test (UUT)
    ALU_output_register uut (
        .clk(clk),
        .reset(reset),
        .alu_out_write(alu_out_write),
        .result(result),
        .result_out(result_out)
    );

    // VCD file generation for GTKWave
    initial begin
        // Create VCD file for waveform viewing
        $dumpfile("alu_output_register_waveform.vcd");
        // Dump all variables at all levels
        $dumpvars(0, ALU_output_register_tb);
    end

    // Test case counter and expected results
    integer test_case;
    reg [WIDTH-1:0] expected_result;

    // Task to display test results
    task display_test_result;
        input [8*30:1] test_name;
        begin
            $display("Test Case %0d: %s", test_case, test_name);
            $display("  Input result = %h, alu_out_write = %b", result, alu_out_write);
            $display("  Expected: result_out = %h", expected_result);
            $display("  Actual:   result_out = %h", result_out);
            
            if (result_out !== expected_result) begin
                $display("  TEST FAILED!");
            end else begin
                $display("  Test passed.");
            end
            $display("--------------------------------------");
        end
    endtask

    // Main test procedure
    initial begin
        // Initialize inputs
        clk = 0;
        reset = 1;
        alu_out_write = 0;
        result = 0;
        test_case = 0;
        expected_result = 0;

        // Apply reset
        #(CLK_PERIOD*2);
        reset = 0;
        #CLK_PERIOD;

        // Test 1: Write value when alu_out_write is enabled
        test_case = test_case + 1;
        result = 32'h12345678;
        alu_out_write = 1;
        expected_result = 32'h12345678;
        #CLK_PERIOD;
        display_test_result("Write value with alu_out_write enabled");

        // Test 2: Keep value when alu_out_write is disabled
        test_case = test_case + 1;
        result = 32'h87654321;
        alu_out_write = 0;
        expected_result = 32'h12345678; // Should keep previous value
        #CLK_PERIOD;
        display_test_result("Keep value with alu_out_write disabled");

        // Test 3: Write new value when alu_out_write is enabled again
        test_case = test_case + 1;
        result = 32'hABCDEF01;
        alu_out_write = 1;
        expected_result = 32'hABCDEF01;
        #CLK_PERIOD;
        display_test_result("Write new value with alu_out_write enabled");

        // Test 4: Reset should clear the register
        test_case = test_case + 1;
        reset = 1;
        expected_result = 32'h00000000;
        #CLK_PERIOD;
        display_test_result("Reset clears the register");
        reset = 0;

        // Test 5: Write after reset
        test_case = test_case + 1;
        result = 32'h55555555;
        alu_out_write = 1;
        expected_result = 32'h55555555;
        #CLK_PERIOD;
        display_test_result("Write after reset");

        // Test 6: Test with ALU addition result (10 + 15 = 25)
        test_case = test_case + 1;
        result = 32'd25; // Simulating ALU addition result of 10 + 15
        alu_out_write = 1;
        expected_result = 32'd25;
        #CLK_PERIOD;
        display_test_result("Store ALU addition result");

        // Test 7: Test with ALU subtraction result (20 - 10 = 10)
        test_case = test_case + 1;
        result = 32'd10; // Simulating ALU subtraction result of 20 - 10
        alu_out_write = 1;
        expected_result = 32'd10;
        #CLK_PERIOD;
        display_test_result("Store ALU subtraction result");

        // Test 8: Test with ALU logic result (AND operation)
        test_case = test_case + 1;
        result = 32'h00FF00FF; // Simulating ALU AND result
        alu_out_write = 1;
        expected_result = 32'h00FF00FF;
        #CLK_PERIOD;
        display_test_result("Store ALU logic result");

        // Finish simulation
        $display("All tests completed!");
        #(CLK_PERIOD*2);
        $finish;
    end

endmodule

ALU_Output_Register/alu_output_register_waveform.vcd
$date
	Fri Jun 20 13:09:15 2025
$end
$version
	Icarus Verilog
$end
$timescale
	1ps
$end
$scope module ALU_output_register_tb $end
$var wire 32 ! result_out [31:0] $end
$var parameter 32 " CLK_PERIOD $end
$var parameter 32 # WIDTH $end
$var reg 1 $ alu_out_write $end
$var reg 1 % clk $end
$var reg 32 & expected_result [31:0] $end
$var reg 1 ' reset $end
$var reg 32 ( result [31:0] $end
$var integer 32 ) test_case [31:0] $end
$scope module uut $end
$var wire 1 $ alu_out_write $end
$var wire 1 % clk $end
$var wire 1 ' reset $end
$var wire 32 * result [31:0] $end
$var reg 32 + result_out [31:0] $end
$upscope $end
$scope task display_test_result $end
$var reg 240 , test_name [240:1] $end
$upscope $end
$upscope $end
$enddefinitions $end
$comment Show the parameter values. $end
$dumpall
b100000 #
b1010 "
$end
#0
$dumpvars
bx ,
bx +
b0 *
b0 )
b0 (
1'
b0 &
0%
0$
bx !
$end
#5000
b0 !
b0 +
1%
#10000
0%
#15000
1%
#20000
0%
0'
#25000
1%
#30000
0%
b10010001101000101011001111000 &
1$
b10010001101000101011001111000 (
b10010001101000101011001111000 *
b1 )
#35000
b10010001101000101011001111000 !
b10010001101000101011001111000 +
1%
#40000
0%
0$
b10000111011001010100001100100001 (
b10000111011001010100001100100001 *
b10 )
b11011000111010101100101001000000111011101101001011101000110100000100000011000010110110001110101010111110110111101110101011101000101111101110111011100100110100101110100011001010010000001100101011011100110000101100010011011000110010101100100 ,
#45000
1%
#50000
0%
b10101011110011011110111100000001 &
1$
b10101011110011011110111100000001 (
b10101011110011011110111100000001 *
b11 )
b11101010110010100100000011101110110100101110100011010000010000001100001011011000111010101011111011011110111010101110100010111110111011101110010011010010111010001100101001000000110010001101001011100110110000101100010011011000110010101100100 ,
#55000
b10101011110011011110111100000001 !
b10101011110011011110111100000001 +
1%
#60000
0%
b0 &
1'
b100 )
b11011000111010101100101001000000111011101101001011101000110100000100000011000010110110001110101010111110110111101110101011101000101111101110111011100100110100101110100011001010010000001100101011011100110000101100010011011000110010101100100 ,
#65000
b0 !
b0 +
1%
#70000
0%
b1010101010101010101010101010101 &
b1010101010101010101010101010101 (
b1010101010101010101010101010101 *
b101 )
0'
b1010010011001010111001101100101011101000010000001100011011011000110010101100001011100100111001100100000011101000110100001100101001000000111001001100101011001110110100101110011011101000110010101110010 ,
#75000
b1010101010101010101010101010101 !
b1010101010101010101010101010101 +
1%
#80000
0%
b11001 &
b11001 (
b11001 *
b110 )
b101011101110010011010010111010001100101001000000110000101100110011101000110010101110010001000000111001001100101011100110110010101110100 ,
#85000
b11001 !
b11001 +
1%
#90000
0%
b1010 &
b1010 (
b1010 *
b111 )
b1010011011101000110111101110010011001010010000001000001010011000101010100100000011000010110010001100100011010010111010001101001011011110110111000100000011100100110010101110011011101010110110001110100 ,
#95000
b1010 !
b1010 +
1%
#100000
0%
b111111110000000011111111 &
b111111110000000011111111 (
b111111110000000011111111 *
b1000 )
b1010011011101000110111101110010011001010010000001000001010011000101010100100000011100110111010101100010011101000111001001100001011000110111010001101001011011110110111000100000011100100110010101110011011101010110110001110100 ,
#105000
b111111110000000011111111 !
b111111110000000011111111 +
1%
#110000
0%
b1010011011101000110111101110010011001010010000001000001010011000101010100100000011011000110111101100111011010010110001100100000011100100110010101110011011101010110110001110100 ,
