Register_File/Register_File.v
module Register_File (
    input wire clk,
    input wire reset,
    input wire reg_write,
    input wire [4:0] rs1_addr,
    input wire [4:0] rs2_addr,
    input wire [4:0] rd_addr,
    input wire [31:0] write_data,
    output wire [31:0] rs1_data,
    output wire [31:0] rs2_data
);

    // Register file with 32 registers of 32 bits each
    reg [31:0] registers [0:31];
    integer i;

    // Asynchronous read (combinational)
    assign rs1_data = (rs1_addr == 5'b00000) ? 32'h00000000 : registers[rs1_addr];
    assign rs2_data = (rs2_addr == 5'b00000) ? 32'h00000000 : registers[rs2_addr];

    // Synchronous write
    always @(posedge clk or posedge reset) begin
        if (reset) begin
            // Reset all registers to 0
            for (i = 0; i < 32; i = i + 1) begin
                registers[i] <= 32'h00000000;
            end
        end else begin
            // Write to register if reg_write is enabled and rd_addr is not x0
            if (reg_write && (rd_addr != 5'b00000)) begin
                registers[rd_addr] <= write_data;
            end
        end
    end

endmodule

Register_File/Register_File_tb.v
module Register_File_tb;
    // Parameters
    parameter CLK_PERIOD = 10; // 10ns clock period (100MHz)
    
    // Inputs
    reg clk;
    reg reset;
    reg reg_write;
    reg [4:0] rs1_addr;
    reg [4:0] rs2_addr;
    reg [4:0] rd_addr;
    reg [31:0] write_data;
    
    // Outputs
    wire [31:0] rs1_data;
    wire [31:0] rs2_data;
    
    // Instantiate the Register File
    Register_File dut (
        .clk(clk),
        .reset(reset),
        .reg_write(reg_write),
        .rs1_addr(rs1_addr),
        .rs2_addr(rs2_addr),
        .rd_addr(rd_addr),
        .write_data(write_data),
        .rs1_data(rs1_data),
        .rs2_data(rs2_data)
    );
    
    // Clock generation
    initial begin
        clk = 0;
        forever #(CLK_PERIOD/2) clk = ~clk;
    end
    
    // Test sequence
    initial begin
        // Initialize inputs
        reset = 1;
        reg_write = 0;
        rs1_addr = 0;
        rs2_addr = 0;
        rd_addr = 0;
        write_data = 0;
        
        // Apply reset
        #(CLK_PERIOD*2);
        reset = 0;
        #CLK_PERIOD;
        
        // Test 1: Write to register x1 and read it back
        rd_addr = 5'd1;
        write_data = 32'hA5A5A5A5;
        reg_write = 1;
        #CLK_PERIOD;
        reg_write = 0;
        rs1_addr = 5'd1;
        #CLK_PERIOD;
        
        // Verify read data
        if (rs1_data !== 32'hA5A5A5A5) begin
            $display("Test 1 Failed: rs1_data = %h, expected = %h", rs1_data, 32'hA5A5A5A5);
        end else begin
            $display("Test 1 Passed: rs1_data = %h", rs1_data);
        end
        
        // Test 2: Write to register x2 and read it back
        rd_addr = 5'd2;
        write_data = 32'h5A5A5A5A;
        reg_write = 1;
        #CLK_PERIOD;
        reg_write = 0;
        rs1_addr = 5'd1;
        rs2_addr = 5'd2;
        #CLK_PERIOD;
        
        // Verify read data
        if (rs1_data !== 32'hA5A5A5A5 || rs2_data !== 32'h5A5A5A5A) begin
            $display("Test 2 Failed: rs1_data = %h, rs2_data = %h", rs1_data, rs2_data);
        end else begin
            $display("Test 2 Passed: rs1_data = %h, rs2_data = %h", rs1_data, rs2_data);
        end
        
        // Test 3: Try to write to register x0 (should remain 0)
        rd_addr = 5'd0;
        write_data = 32'hFFFFFFFF;
        reg_write = 1;
        #CLK_PERIOD;
        reg_write = 0;
        rs1_addr = 5'd0;
        #CLK_PERIOD;
        
        // Verify x0 remains 0
        if (rs1_data !== 32'h0) begin
            $display("Test 3 Failed: rs1_data = %h, expected = %h", rs1_data, 32'h0);
        end else begin
            $display("Test 3 Passed: x0 remains 0 as expected");
        end
        
        // Test 4: Test write enable signal
        rd_addr = 5'd3;
        write_data = 32'hAAAAAAAA;
        reg_write = 0; // Disable write
        #CLK_PERIOD;
        rs1_addr = 5'd3;
        #CLK_PERIOD;
        
        // Verify register wasn't written when reg_write=0
        if (rs1_data !== 32'h0) begin
            $display("Test 4 Failed: rs1_data = %h, expected = %h", rs1_data, 32'h0);
        end else begin
            $display("Test 4 Passed: No write occurred when reg_write=0");
        end
        
        // Test 5: Write to multiple registers and read them back
        // Write to x3
        rd_addr = 5'd3;
        write_data = 32'h33333333;
        reg_write = 1;
        #CLK_PERIOD;
        
        // Write to x4
        rd_addr = 5'd4;
        write_data = 32'h44444444;
        #CLK_PERIOD;
        
        // Write to x5
        rd_addr = 5'd5;
        write_data = 32'h55555555;
        #CLK_PERIOD;
        
        reg_write = 0;
        
        // Read and verify x3
        rs1_addr = 5'd3;
        #CLK_PERIOD;
        if (rs1_data !== 32'h33333333) begin
            $display("Test 5a Failed: rs1_data (x3) = %h", rs1_data);
        end else begin
            $display("Test 5a Passed: rs1_data (x3) = %h", rs1_data);
        end
        
        // Read and verify x4
        rs1_addr = 5'd4;
        #CLK_PERIOD;
        if (rs1_data !== 32'h44444444) begin
            $display("Test 5b Failed: rs1_data (x4) = %h", rs1_data);
        end else begin
            $display("Test 5b Passed: rs1_data (x4) = %h", rs1_data);
        end
        
        // Read and verify x5
        rs1_addr = 5'd5;
        #CLK_PERIOD;
        if (rs1_data !== 32'h55555555) begin
            $display("Test 5c Failed: rs1_data (x5) = %h", rs1_data);
        end else begin
            $display("Test 5c Passed: rs1_data (x5) = %h", rs1_data);
        end
        
        // Test 6: Reset test
        reset = 1;
        #CLK_PERIOD;
        reset = 0;
        
        // Verify registers are reset to 0
        rs1_addr = 5'd1;
        rs2_addr = 5'd2;
        #CLK_PERIOD;
        
        if (rs1_data !== 32'h0 || rs2_data !== 32'h0) begin
            $display("Test 6 Failed: After reset, rs1_data = %h, rs2_data = %h", rs1_data, rs2_data);
        end else begin
            $display("Test 6 Passed: All registers reset to 0");
        end
        
        $display("All tests completed");
        $finish;
    end
    
    // Optional: Generate VCD file for waveform viewing
    initial begin
        $dumpfile("register_file_waveform.vcd");
        $dumpvars(0, Register_File_tb);
    end
    
endmodule

Register_File/register_file_waveform.vcd
$date
	Fri Jun 20 21:43:57 2025
$end
$version
	Icarus Verilog
$end
$timescale
	1s
$end
$scope module Register_File_tb $end
$var wire 32 ! rs2_data [31:0] $end
$var wire 32 " rs1_data [31:0] $end
$var parameter 32 # CLK_PERIOD $end
$var reg 1 $ clk $end
$var reg 5 % rd_addr [4:0] $end
$var reg 1 & reg_write $end
$var reg 1 ' reset $end
$var reg 5 ( rs1_addr [4:0] $end
$var reg 5 ) rs2_addr [4:0] $end
$var reg 32 * write_data [31:0] $end
$scope module dut $end
$var wire 1 $ clk $end
$var wire 5 + rd_addr [4:0] $end
$var wire 1 & reg_write $end
$var wire 1 ' reset $end
$var wire 5 , rs1_addr [4:0] $end
$var wire 5 - rs2_addr [4:0] $end
$var wire 32 . write_data [31:0] $end
$var wire 32 / rs2_data [31:0] $end
$var wire 32 0 rs1_data [31:0] $end
$var integer 32 1 i [31:0] $end
$upscope $end
$upscope $end
$enddefinitions $end
$comment Show the parameter values. $end
$dumpall
b1010 #
$end
#0
$dumpvars
b100000 1
b0 0
b0 /
b0 .
b0 -
b0 ,
b0 +
b0 *
b0 )
b0 (
1'
0&
b0 %
0$
b0 "
b0 !
$end
#5
b100000 1
1$
#10
0$
#15
b100000 1
1$
#20
0$
0'
#25
1$
#30
0$
1&
b10100101101001011010010110100101 *
b10100101101001011010010110100101 .
b1 %
b1 +
#35
1$
#40
b10100101101001011010010110100101 "
b10100101101001011010010110100101 0
0$
b1 (
b1 ,
0&
#45
1$
#50
0$
1&
b1011010010110100101101001011010 *
b1011010010110100101101001011010 .
b10 %
b10 +
#55
1$
#60
b1011010010110100101101001011010 !
b1011010010110100101101001011010 /
0$
b10 )
b10 -
0&
#65
1$
#70
0$
1&
b11111111111111111111111111111111 *
b11111111111111111111111111111111 .
b0 %
b0 +
#75
1$
#80
b0 "
b0 0
0$
b0 (
b0 ,
0&
#85
1$
#90
0$
b10101010101010101010101010101010 *
b10101010101010101010101010101010 .
b11 %
b11 +
#95
1$
#100
0$
b11 (
b11 ,
#105
1$
#110
0$
1&
b110011001100110011001100110011 *
b110011001100110011001100110011 .
#115
b110011001100110011001100110011 "
b110011001100110011001100110011 0
1$
#120
0$
b1000100010001000100010001000100 *
b1000100010001000100010001000100 .
b100 %
b100 +
#125
1$
#130
0$
b1010101010101010101010101010101 *
b1010101010101010101010101010101 .
b101 %
b101 +
#135
1$
#140
0$
0&
#145
1$
#150
b1000100010001000100010001000100 "
b1000100010001000100010001000100 0
0$
b100 (
b100 ,
#155
1$
#160
b1010101010101010101010101010101 "
b1010101010101010101010101010101 0
0$
b101 (
b101 ,
#165
1$
#170
b0 "
b0 0
b0 !
b0 /
b100000 1
0$
1'
#175
b100000 1
1$
#180
0$
b1 (
b1 ,
0'
